/*     */ import java.awt.Component;
/*     */ 
/*     */ public abstract class ac
/*     */ {
/*     */   static fq n;
/*     */ 
/*     */   public abstract void s(Component paramComponent);
/*     */ 
/*     */   public abstract void d(Component paramComponent, int paramInt);
/*     */ 
/*     */   public abstract void l(Component paramComponent, byte paramByte);
/*     */ 
/*     */   public abstract int m(int paramInt);
/*     */ 
/*     */   public static ac c()
/*     */   {
/*     */     try
/*     */     {
/*  10 */       return new dh();
/*     */     } catch (Throwable localThrowable) {
/*     */     }
/*  13 */     return null;
/*     */   }
/*     */ 
/*     */   public static ac n()
/*     */   {
/*     */     try
/*     */     {
/*  10 */       return new dh();
/*     */     } catch (Throwable localThrowable) {
/*     */     }
/*  13 */     return null;
/*     */   }
/*     */ 
/*     */   public static ac j()
/*     */   {
/*     */     try
/*     */     {
/*  10 */       return new dh();
/*     */     } catch (Throwable localThrowable) {
/*     */     }
/*  13 */     return null;
/*     */   }
/*     */ 
/*     */   public static ac g()
/*     */   {
/*     */     try
/*     */     {
/*  10 */       return new dh();
/*     */     } catch (Throwable localThrowable) {
/*     */     }
/*  13 */     return null;
/*     */   }
/*     */ 
/*     */   public abstract void e(Component paramComponent);
/*     */ 
/*     */   public abstract void i(Component paramComponent);
/*     */ 
/*     */   public abstract int t();
/*     */ 
/*     */   public abstract void u(Component paramComponent);
/*     */ 
/*     */   public abstract void v(Component paramComponent);
/*     */ 
/*     */   public abstract void w(Component paramComponent);
/*     */ 
/*     */   public static ac z()
/*     */   {
/*     */     try
/*     */     {
/*  10 */       return new dh();
/*     */     } catch (Throwable localThrowable) {
/*     */     }
/*  13 */     return null;
/*     */   }
/*     */ 
/*     */   public abstract void b(Component paramComponent);
/*     */ 
/*     */   public abstract int y();
/*     */ 
/*     */   public abstract void q(Component paramComponent);
/*     */ 
/*     */   // ERROR //
/*     */   static void q(int paramInt)
/*     */   {
/*     */     // Byte code:
/*     */     //   0: getstatic 47	l:ag	Li;
/*     */     //   3: ifnonnull +38 -> 41
/*     */     //   6: iload_0
/*     */     //   7: ldc 48
/*     */     //   9: if_icmpgt +6 -> 15
/*     */     //   12: goto +0 -> 12
/*     */     //   15: new 49	i
/*     */     //   18: dup
/*     */     //   19: getstatic 55	dj:r	Lak;
/*     */     //   22: new 57	java/net/URL
/*     */     //   25: dup
/*     */     //   26: getstatic 63	be:aq	Ljava/lang/String;
/*     */     //   29: invokespecial 66	java/net/URL:<init>	(Ljava/lang/String;)V
/*     */     //   32: invokespecial 69	i:<init>	(Lak;Ljava/net/URL;)V
/*     */     //   35: putstatic 47	l:ag	Li;
/*     */     //   38: goto +228 -> 266
/*     */     //   41: getstatic 47	l:ag	Li;
/*     */     //   44: ldc 70
/*     */     //   46: invokevirtual 73	i:r	(I)[B
/*     */     //   49: astore_1
/*     */     //   50: aconst_null
/*     */     //   51: aload_1
/*     */     //   52: if_acmpeq +214 -> 266
/*     */     //   55: iload_0
/*     */     //   56: ldc 48
/*     */     //   58: if_icmpgt +6 -> 64
/*     */     //   61: goto +3 -> 64
/*     */     //   64: new 77	ev
/*     */     //   67: dup
/*     */     //   68: aload_1
/*     */     //   69: invokespecial 80	ev:<init>	([B)V
/*     */     //   72: astore_2
/*     */     //   73: aload_2
/*     */     //   74: ldc 81
/*     */     //   76: invokevirtual 84	ev:k	(I)I
/*     */     //   79: ldc 85
/*     */     //   81: imul
/*     */     //   82: putstatic 90	g:ax	I
/*     */     //   85: ldc 91
/*     */     //   87: getstatic 90	g:ax	I
/*     */     //   90: imul
/*     */     //   91: anewarray 92	c
/*     */     //   94: putstatic 97	v:ai	[Lc;
/*     */     //   97: iconst_0
/*     */     //   98: istore_3
/*     */     //   99: iload_3
/*     */     //   100: getstatic 90	g:ax	I
/*     */     //   103: ldc 91
/*     */     //   105: imul
/*     */     //   106: if_icmpge +131 -> 237
/*     */     //   109: iload_0
/*     */     //   110: ldc 48
/*     */     //   112: if_icmpgt +6 -> 118
/*     */     //   115: goto +0 -> 115
/*     */     //   118: getstatic 97	v:ai	[Lc;
/*     */     //   121: iload_3
/*     */     //   122: new 92	c
/*     */     //   125: dup
/*     */     //   126: invokespecial 98	c:<init>	()V
/*     */     //   129: dup_x2
/*     */     //   130: aastore
/*     */     //   131: astore 4
/*     */     //   133: aload_2
/*     */     //   134: ldc 81
/*     */     //   136: invokevirtual 84	ev:k	(I)I
/*     */     //   139: istore 5
/*     */     //   141: aload 4
/*     */     //   143: iload 5
/*     */     //   145: sipush 32767
/*     */     //   148: iand
/*     */     //   149: ldc 99
/*     */     //   151: imul
/*     */     //   152: putfield 101	c:r	I
/*     */     //   155: aload 4
/*     */     //   157: iconst_0
/*     */     //   158: iload 5
/*     */     //   160: ldc 102
/*     */     //   162: iand
/*     */     //   163: if_icmpeq +16 -> 179
/*     */     //   166: iload_0
/*     */     //   167: ldc 48
/*     */     //   169: if_icmpgt +6 -> 175
/*     */     //   172: goto +3 -> 175
/*     */     //   175: iconst_1
/*     */     //   176: goto +4 -> 180
/*     */     //   179: iconst_0
/*     */     //   180: putfield 105	c:n	Z
/*     */     //   183: aload 4
/*     */     //   185: aload_2
/*     */     //   186: ldc 106
/*     */     //   188: invokevirtual 110	ev:ad	(I)Ljava/lang/String;
/*     */     //   191: putfield 112	c:l	Ljava/lang/String;
/*     */     //   194: aload 4
/*     */     //   196: aload_2
/*     */     //   197: ldc 113
/*     */     //   199: invokevirtual 115	ev:t	(I)I
/*     */     //   202: ldc 116
/*     */     //   204: imul
/*     */     //   205: putfield 118	c:m	I
/*     */     //   208: aload 4
/*     */     //   210: aload_2
/*     */     //   211: ldc 119
/*     */     //   213: invokevirtual 122	ev:o	(I)I
/*     */     //   216: ldc 123
/*     */     //   218: imul
/*     */     //   219: putfield 125	c:d	I
/*     */     //   222: aload 4
/*     */     //   224: ldc 126
/*     */     //   226: iload_3
/*     */     //   227: imul
/*     */     //   228: putfield 128	c:c	I
/*     */     //   231: iinc 3 1
/*     */     //   234: goto -135 -> 99
/*     */     //   237: getstatic 97	v:ai	[Lc;
/*     */     //   240: iconst_0
/*     */     //   241: getstatic 97	v:ai	[Lc;
/*     */     //   244: arraylength
/*     */     //   245: iconst_1
/*     */     //   246: isub
/*     */     //   247: getstatic 132	g:bi	[I
/*     */     //   250: getstatic 135	g:bs	[I
/*     */     //   253: ldc 136
/*     */     //   255: invokestatic 141	bh:s	([Lc;II[I[II)V
/*     */     //   258: iconst_1
/*     */     //   259: putstatic 144	g:ao	Z
/*     */     //   262: aconst_null
/*     */     //   263: putstatic 47	l:ag	Li;
/*     */     //   266: goto +12 -> 278
/*     */     //   269: astore_1
/*     */     //   270: aload_1
/*     */     //   271: invokevirtual 147	java/lang/Exception:printStackTrace	()V
/*     */     //   274: aconst_null
/*     */     //   275: putstatic 47	l:ag	Li;
/*     */     //   278: return
/*     */     //
/*     */     // Exception table:
/*     */     //   from	to	target	type
/*     */     //   0	266	269	java/lang/Exception
/*     */   }
/*     */ }

/* Location:           C:\Users\Mike\IdeaProjects\RealityBot-2007 Updater\client-deob.jar
 * Qualified Name:     ac
 * JD-Core Version:    0.6.2
 */