/*     */ public class cm
/*     */ {
/*  17 */   public static int[] l = new int[2000];
/*     */   public static int[] d;
/*   6 */   public static int[] r = new int[32];
/*     */ 
/*     */   cm()
/*     */     throws Throwable
/*     */   {
/*  20 */     throw new Error();
/*     */   }
/*     */ 
/*     */   static
/*     */   {
/*   9 */     int i = 2;
/*  10 */     for (int j = 0; j < 32; j++) {
/*  11 */       r[j] = (i - 1);
/*  12 */       i += i;
/*     */     }
/*     */ 
/*  16 */     d = new int[2000]; } 
/*     */   // ERROR //
/*     */   public static final y d(ak paramak, java.awt.Component paramComponent, int paramInt1, int paramInt2, int paramInt3) { // Byte code:
/*     */     //   0: iconst_0
/*     */     //   1: ldc 27
/*     */     //   3: getstatic 32	y:r	I
/*     */     //   6: imul
/*     */     //   7: if_icmpne +26 -> 33
/*     */     //   10: iload 4
/*     */     //   12: ldc 33
/*     */     //   14: if_icmpgt +11 -> 25
/*     */     //   17: new 35	java/lang/IllegalStateException
/*     */     //   20: dup
/*     */     //   21: invokespecial 36	java/lang/IllegalStateException:<init>	()V
/*     */     //   24: athrow
/*     */     //   25: new 35	java/lang/IllegalStateException
/*     */     //   28: dup
/*     */     //   29: invokespecial 36	java/lang/IllegalStateException:<init>	()V
/*     */     //   32: athrow
/*     */     //   33: iload_2
/*     */     //   34: iflt +38 -> 72
/*     */     //   37: iload 4
/*     */     //   39: ldc 33
/*     */     //   41: if_icmpgt +11 -> 52
/*     */     //   44: new 35	java/lang/IllegalStateException
/*     */     //   47: dup
/*     */     //   48: invokespecial 36	java/lang/IllegalStateException:<init>	()V
/*     */     //   51: athrow
/*     */     //   52: iload_2
/*     */     //   53: iconst_2
/*     */     //   54: if_icmplt +26 -> 80
/*     */     //   57: iload 4
/*     */     //   59: ldc 33
/*     */     //   61: if_icmpgt +11 -> 72
/*     */     //   64: new 35	java/lang/IllegalStateException
/*     */     //   67: dup
/*     */     //   68: invokespecial 36	java/lang/IllegalStateException:<init>	()V
/*     */     //   71: athrow
/*     */     //   72: new 38	java/lang/IllegalArgumentException
/*     */     //   75: dup
/*     */     //   76: invokespecial 39	java/lang/IllegalArgumentException:<init>	()V
/*     */     //   79: athrow
/*     */     //   80: iload_3
/*     */     //   81: sipush 256
/*     */     //   84: if_icmpge +22 -> 106
/*     */     //   87: iload 4
/*     */     //   89: ldc 33
/*     */     //   91: if_icmpgt +11 -> 102
/*     */     //   94: new 35	java/lang/IllegalStateException
/*     */     //   97: dup
/*     */     //   98: invokespecial 36	java/lang/IllegalStateException:<init>	()V
/*     */     //   101: athrow
/*     */     //   102: sipush 256
/*     */     //   105: istore_3
/*     */     //   106: new 41	ds
/*     */     //   109: dup
/*     */     //   110: invokespecial 42	ds:<init>	()V
/*     */     //   113: astore 5
/*     */     //   115: aload 5
/*     */     //   117: sipush 256
/*     */     //   120: getstatic 45	y:d	Z
/*     */     //   123: ifeq +17 -> 140
/*     */     //   126: iload 4
/*     */     //   128: ldc 33
/*     */     //   130: if_icmpgt +6 -> 136
/*     */     //   133: goto +3 -> 136
/*     */     //   136: iconst_2
/*     */     //   137: goto +4 -> 141
/*     */     //   140: iconst_1
/*     */     //   141: imul
/*     */     //   142: newarray int
/*     */     //   144: putfield 52	y:j	[I
/*     */     //   147: aload 5
/*     */     //   149: ldc 53
/*     */     //   151: iload_3
/*     */     //   152: imul
/*     */     //   153: putfield 56	y:s	I
/*     */     //   156: aload 5
/*     */     //   158: aload_1
/*     */     //   159: invokevirtual 59	y:s	(Ljava/awt/Component;)V
/*     */     //   162: aload 5
/*     */     //   164: sipush 1024
/*     */     //   167: iload_3
/*     */     //   168: sipush -1024
/*     */     //   171: iand
/*     */     //   172: iadd
/*     */     //   173: ldc 60
/*     */     //   175: imul
/*     */     //   176: putfield 63	y:i	I
/*     */     //   179: aload 5
/*     */     //   181: getfield 63	y:i	I
/*     */     //   184: ldc 64
/*     */     //   186: imul
/*     */     //   187: sipush 16384
/*     */     //   190: if_icmple +20 -> 210
/*     */     //   193: iload 4
/*     */     //   195: ldc 33
/*     */     //   197: if_icmpgt +6 -> 203
/*     */     //   200: goto +3 -> 203
/*     */     //   203: aload 5
/*     */     //   205: ldc 65
/*     */     //   207: putfield 63	y:i	I
/*     */     //   210: aload 5
/*     */     //   212: aload 5
/*     */     //   214: getfield 63	y:i	I
/*     */     //   217: ldc 64
/*     */     //   219: imul
/*     */     //   220: invokevirtual 69	y:u	(I)V
/*     */     //   223: getstatic 71	y:l	I
/*     */     //   226: ldc 72
/*     */     //   228: imul
/*     */     //   229: ifle +73 -> 302
/*     */     //   232: iload 4
/*     */     //   234: ldc 33
/*     */     //   236: if_icmpgt +11 -> 247
/*     */     //   239: new 35	java/lang/IllegalStateException
/*     */     //   242: dup
/*     */     //   243: invokespecial 36	java/lang/IllegalStateException:<init>	()V
/*     */     //   246: athrow
/*     */     //   247: aconst_null
/*     */     //   248: getstatic 76	y:m	Lf;
/*     */     //   251: if_acmpne +51 -> 302
/*     */     //   254: iload 4
/*     */     //   256: ldc 33
/*     */     //   258: if_icmpgt +11 -> 269
/*     */     //   261: new 35	java/lang/IllegalStateException
/*     */     //   264: dup
/*     */     //   265: invokespecial 36	java/lang/IllegalStateException:<init>	()V
/*     */     //   268: athrow
/*     */     //   269: new 78	f
/*     */     //   272: dup
/*     */     //   273: invokespecial 79	f:<init>	()V
/*     */     //   276: putstatic 76	y:m	Lf;
/*     */     //   279: getstatic 76	y:m	Lf;
/*     */     //   282: aload_0
/*     */     //   283: putfield 82	f:r	Lak;
/*     */     //   286: aload_0
/*     */     //   287: getstatic 76	y:m	Lf;
/*     */     //   290: getstatic 71	y:l	I
/*     */     //   293: ldc 72
/*     */     //   295: imul
/*     */     //   296: ldc 83
/*     */     //   298: invokevirtual 86	ak:j	(Ljava/lang/Runnable;II)Lah;
/*     */     //   301: pop
/*     */     //   302: getstatic 76	y:m	Lf;
/*     */     //   305: ifnull +63 -> 368
/*     */     //   308: iload 4
/*     */     //   310: ldc 33
/*     */     //   312: if_icmpgt +11 -> 323
/*     */     //   315: new 35	java/lang/IllegalStateException
/*     */     //   318: dup
/*     */     //   319: invokespecial 36	java/lang/IllegalStateException:<init>	()V
/*     */     //   322: athrow
/*     */     //   323: aconst_null
/*     */     //   324: getstatic 76	y:m	Lf;
/*     */     //   327: getfield 89	f:d	[Ly;
/*     */     //   330: iload_2
/*     */     //   331: aaload
/*     */     //   332: if_acmpeq +26 -> 358
/*     */     //   335: iload 4
/*     */     //   337: ldc 33
/*     */     //   339: if_icmpgt +11 -> 350
/*     */     //   342: new 35	java/lang/IllegalStateException
/*     */     //   345: dup
/*     */     //   346: invokespecial 36	java/lang/IllegalStateException:<init>	()V
/*     */     //   349: athrow
/*     */     //   350: new 38	java/lang/IllegalArgumentException
/*     */     //   353: dup
/*     */     //   354: invokespecial 39	java/lang/IllegalArgumentException:<init>	()V
/*     */     //   357: athrow
/*     */     //   358: getstatic 76	y:m	Lf;
/*     */     //   361: getfield 89	f:d	[Ly;
/*     */     //   364: iload_2
/*     */     //   365: aload 5
/*     */     //   367: aastore
/*     */     //   368: aload 5
/*     */     //   370: areturn
/*     */     //   371: astore 5
/*     */     //   373: new 91	dv
/*     */     //   376: dup
/*     */     //   377: aload_0
/*     */     //   378: iload_2
/*     */     //   379: invokespecial 94	dv:<init>	(Lak;I)V
/*     */     //   382: astore 5
/*     */     //   384: aload 5
/*     */     //   386: sipush 256
/*     */     //   389: getstatic 45	y:d	Z
/*     */     //   392: ifeq +17 -> 409
/*     */     //   395: iload 4
/*     */     //   397: ldc 33
/*     */     //   399: if_icmpgt +6 -> 405
/*     */     //   402: goto +0 -> 402
/*     */     //   405: iconst_2
/*     */     //   406: goto +4 -> 410
/*     */     //   409: iconst_1
/*     */     //   410: imul
/*     */     //   411: newarray int
/*     */     //   413: putfield 52	y:j	[I
/*     */     //   416: aload 5
/*     */     //   418: ldc 53
/*     */     //   420: iload_3
/*     */     //   421: imul
/*     */     //   422: putfield 56	y:s	I
/*     */     //   425: aload 5
/*     */     //   427: aload_1
/*     */     //   428: invokevirtual 59	y:s	(Ljava/awt/Component;)V
/*     */     //   431: aload 5
/*     */     //   433: ldc 65
/*     */     //   435: putfield 63	y:i	I
/*     */     //   438: aload 5
/*     */     //   440: aload 5
/*     */     //   442: getfield 63	y:i	I
/*     */     //   445: ldc 64
/*     */     //   447: imul
/*     */     //   448: invokevirtual 69	y:u	(I)V
/*     */     //   451: ldc 72
/*     */     //   453: getstatic 71	y:l	I
/*     */     //   456: imul
/*     */     //   457: ifle +67 -> 524
/*     */     //   460: iload 4
/*     */     //   462: ldc 33
/*     */     //   464: if_icmpgt +11 -> 475
/*     */     //   467: new 35	java/lang/IllegalStateException
/*     */     //   470: dup
/*     */     //   471: invokespecial 36	java/lang/IllegalStateException:<init>	()V
/*     */     //   474: athrow
/*     */     //   475: getstatic 76	y:m	Lf;
/*     */     //   478: ifnonnull +46 -> 524
/*     */     //   481: iload 4
/*     */     //   483: ldc 33
/*     */     //   485: if_icmpgt +6 -> 491
/*     */     //   488: goto +0 -> 488
/*     */     //   491: new 78	f
/*     */     //   494: dup
/*     */     //   495: invokespecial 79	f:<init>	()V
/*     */     //   498: putstatic 76	y:m	Lf;
/*     */     //   501: getstatic 76	y:m	Lf;
/*     */     //   504: aload_0
/*     */     //   505: putfield 82	f:r	Lak;
/*     */     //   508: aload_0
/*     */     //   509: getstatic 76	y:m	Lf;
/*     */     //   512: getstatic 71	y:l	I
/*     */     //   515: ldc 72
/*     */     //   517: imul
/*     */     //   518: ldc 95
/*     */     //   520: invokevirtual 86	ak:j	(Ljava/lang/Runnable;II)Lah;
/*     */     //   523: pop
/*     */     //   524: getstatic 76	y:m	Lf;
/*     */     //   527: ifnull +58 -> 585
/*     */     //   530: iload 4
/*     */     //   532: ldc 33
/*     */     //   534: if_icmpgt +6 -> 540
/*     */     //   537: goto +3 -> 540
/*     */     //   540: aconst_null
/*     */     //   541: getstatic 76	y:m	Lf;
/*     */     //   544: getfield 89	f:d	[Ly;
/*     */     //   547: iload_2
/*     */     //   548: aaload
/*     */     //   549: if_acmpeq +26 -> 575
/*     */     //   552: iload 4
/*     */     //   554: ldc 33
/*     */     //   556: if_icmpgt +11 -> 567
/*     */     //   559: new 35	java/lang/IllegalStateException
/*     */     //   562: dup
/*     */     //   563: invokespecial 36	java/lang/IllegalStateException:<init>	()V
/*     */     //   566: athrow
/*     */     //   567: new 38	java/lang/IllegalArgumentException
/*     */     //   570: dup
/*     */     //   571: invokespecial 39	java/lang/IllegalArgumentException:<init>	()V
/*     */     //   574: athrow
/*     */     //   575: getstatic 76	y:m	Lf;
/*     */     //   578: getfield 89	f:d	[Ly;
/*     */     //   581: iload_2
/*     */     //   582: aload 5
/*     */     //   584: aastore
/*     */     //   585: aload 5
/*     */     //   587: areturn
/*     */     //   588: astore 5
/*     */     //   590: new 29	y
/*     */     //   593: dup
/*     */     //   594: invokespecial 96	y:<init>	()V
/*     */     //   597: areturn
/*     */     //
/*     */     // Exception table:
/*     */     //   from	to	target	type
/*     */     //   106	370	371	java/lang/Throwable
/*     */     //   373	587	588	java/lang/Throwable } 
/*  32 */   public static eu z(int paramInt, byte paramByte) { eu localeu = (eu)eu.z.r(paramInt);
/*  33 */     if (localeu != null) { if (paramByte == 70) throw new IllegalStateException(); return localeu; }
/*  34 */     byte[] arrayOfByte = eu.n.l(13, paramInt, 1963269374);
/*  35 */     localeu = new eu();
/*  36 */     localeu.q = (paramInt * -963347997);
/*  37 */     if (arrayOfByte != null) { if (paramByte == 70) throw new IllegalStateException(); localeu.g(new ev(arrayOfByte), 1570192895); }
/*  38 */     eu.z.l(localeu, paramInt);
/*  39 */     return localeu;
/*     */   }
/*     */ 
/*     */   // ERROR //
/*     */   static void g(dj paramdj, int paramInt)
/*     */   {
/*     */     // Byte code:
/*     */     //   0: getstatic 145	an:u	I
/*     */     //   3: ldc 146
/*     */     //   5: imul
/*     */     //   6: iconst_1
/*     */     //   7: if_icmpne +1232 -> 1239
/*     */     //   10: iload_1
/*     */     //   11: ldc 147
/*     */     //   13: if_icmpeq +4 -> 17
/*     */     //   16: return
/*     */     //   17: sipush 280
/*     */     //   20: istore_2
/*     */     //   21: ldc 148
/*     */     //   23: getstatic 151	an:v	I
/*     */     //   26: imul
/*     */     //   27: iload_2
/*     */     //   28: if_icmplt +82 -> 110
/*     */     //   31: iload_1
/*     */     //   32: ldc 147
/*     */     //   34: if_icmpeq +4 -> 38
/*     */     //   37: return
/*     */     //   38: getstatic 151	an:v	I
/*     */     //   41: ldc 148
/*     */     //   43: imul
/*     */     //   44: bipush 14
/*     */     //   46: iload_2
/*     */     //   47: iadd
/*     */     //   48: if_icmpgt +62 -> 110
/*     */     //   51: iload_1
/*     */     //   52: ldc 147
/*     */     //   54: if_icmpeq +11 -> 65
/*     */     //   57: new 35	java/lang/IllegalStateException
/*     */     //   60: dup
/*     */     //   61: invokespecial 36	java/lang/IllegalStateException:<init>	()V
/*     */     //   64: athrow
/*     */     //   65: getstatic 154	an:w	I
/*     */     //   68: ldc 155
/*     */     //   70: imul
/*     */     //   71: iconst_4
/*     */     //   72: if_icmplt +38 -> 110
/*     */     //   75: iload_1
/*     */     //   76: ldc 147
/*     */     //   78: if_icmpeq +4 -> 82
/*     */     //   81: return
/*     */     //   82: ldc 155
/*     */     //   84: getstatic 154	an:w	I
/*     */     //   87: imul
/*     */     //   88: bipush 18
/*     */     //   90: if_icmpgt +20 -> 110
/*     */     //   93: iload_1
/*     */     //   94: ldc 147
/*     */     //   96: if_icmpeq +6 -> 102
/*     */     //   99: goto +3 -> 102
/*     */     //   102: iconst_0
/*     */     //   103: iconst_0
/*     */     //   104: ldc 156
/*     */     //   106: invokestatic 161	client:i	(III)V
/*     */     //   109: return
/*     */     //   110: getstatic 151	an:v	I
/*     */     //   113: ldc 148
/*     */     //   115: imul
/*     */     //   116: iload_2
/*     */     //   117: bipush 15
/*     */     //   119: iadd
/*     */     //   120: if_icmplt +86 -> 206
/*     */     //   123: iload_1
/*     */     //   124: ldc 147
/*     */     //   126: if_icmpeq +6 -> 132
/*     */     //   129: goto +3 -> 132
/*     */     //   132: getstatic 151	an:v	I
/*     */     //   135: ldc 148
/*     */     //   137: imul
/*     */     //   138: bipush 80
/*     */     //   140: iload_2
/*     */     //   141: iadd
/*     */     //   142: if_icmpgt +64 -> 206
/*     */     //   145: iload_1
/*     */     //   146: ldc 147
/*     */     //   148: if_icmpeq +11 -> 159
/*     */     //   151: new 35	java/lang/IllegalStateException
/*     */     //   154: dup
/*     */     //   155: invokespecial 36	java/lang/IllegalStateException:<init>	()V
/*     */     //   158: athrow
/*     */     //   159: ldc 155
/*     */     //   161: getstatic 154	an:w	I
/*     */     //   164: imul
/*     */     //   165: iconst_4
/*     */     //   166: if_icmplt +40 -> 206
/*     */     //   169: iload_1
/*     */     //   170: ldc 147
/*     */     //   172: if_icmpeq +6 -> 178
/*     */     //   175: goto +0 -> 175
/*     */     //   178: getstatic 154	an:w	I
/*     */     //   181: ldc 155
/*     */     //   183: imul
/*     */     //   184: bipush 18
/*     */     //   186: if_icmpgt +20 -> 206
/*     */     //   189: iload_1
/*     */     //   190: ldc 147
/*     */     //   192: if_icmpeq +6 -> 198
/*     */     //   195: goto +0 -> 195
/*     */     //   198: iconst_0
/*     */     //   199: iconst_1
/*     */     //   200: ldc 162
/*     */     //   202: invokestatic 161	client:i	(III)V
/*     */     //   205: return
/*     */     //   206: sipush 390
/*     */     //   209: istore_3
/*     */     //   210: getstatic 151	an:v	I
/*     */     //   213: ldc 148
/*     */     //   215: imul
/*     */     //   216: iload_3
/*     */     //   217: if_icmplt +89 -> 306
/*     */     //   220: iload_1
/*     */     //   221: ldc 147
/*     */     //   223: if_icmpeq +4 -> 227
/*     */     //   226: return
/*     */     //   227: ldc 148
/*     */     //   229: getstatic 151	an:v	I
/*     */     //   232: imul
/*     */     //   233: bipush 14
/*     */     //   235: iload_3
/*     */     //   236: iadd
/*     */     //   237: if_icmpgt +69 -> 306
/*     */     //   240: iload_1
/*     */     //   241: ldc 147
/*     */     //   243: if_icmpeq +6 -> 249
/*     */     //   246: goto +3 -> 249
/*     */     //   249: getstatic 154	an:w	I
/*     */     //   252: ldc 155
/*     */     //   254: imul
/*     */     //   255: iconst_4
/*     */     //   256: if_icmplt +50 -> 306
/*     */     //   259: iload_1
/*     */     //   260: ldc 147
/*     */     //   262: if_icmpeq +11 -> 273
/*     */     //   265: new 35	java/lang/IllegalStateException
/*     */     //   268: dup
/*     */     //   269: invokespecial 36	java/lang/IllegalStateException:<init>	()V
/*     */     //   272: athrow
/*     */     //   273: ldc 155
/*     */     //   275: getstatic 154	an:w	I
/*     */     //   278: imul
/*     */     //   279: bipush 18
/*     */     //   281: if_icmpgt +25 -> 306
/*     */     //   284: iload_1
/*     */     //   285: ldc 147
/*     */     //   287: if_icmpeq +11 -> 298
/*     */     //   290: new 35	java/lang/IllegalStateException
/*     */     //   293: dup
/*     */     //   294: invokespecial 36	java/lang/IllegalStateException:<init>	()V
/*     */     //   297: athrow
/*     */     //   298: iconst_1
/*     */     //   299: iconst_0
/*     */     //   300: ldc 163
/*     */     //   302: invokestatic 161	client:i	(III)V
/*     */     //   305: return
/*     */     //   306: ldc 148
/*     */     //   308: getstatic 151	an:v	I
/*     */     //   311: imul
/*     */     //   312: iload_3
/*     */     //   313: bipush 15
/*     */     //   315: iadd
/*     */     //   316: if_icmplt +77 -> 393
/*     */     //   319: iload_1
/*     */     //   320: ldc 147
/*     */     //   322: if_icmpeq +6 -> 328
/*     */     //   325: goto +0 -> 325
/*     */     //   328: getstatic 151	an:v	I
/*     */     //   331: ldc 148
/*     */     //   333: imul
/*     */     //   334: iload_3
/*     */     //   335: bipush 80
/*     */     //   337: iadd
/*     */     //   338: if_icmpgt +55 -> 393
/*     */     //   341: iload_1
/*     */     //   342: ldc 147
/*     */     //   344: if_icmpeq +6 -> 350
/*     */     //   347: goto +3 -> 350
/*     */     //   350: getstatic 154	an:w	I
/*     */     //   353: ldc 155
/*     */     //   355: imul
/*     */     //   356: iconst_4
/*     */     //   357: if_icmplt +36 -> 393
/*     */     //   360: iload_1
/*     */     //   361: ldc 147
/*     */     //   363: if_icmpeq +4 -> 367
/*     */     //   366: return
/*     */     //   367: getstatic 154	an:w	I
/*     */     //   370: ldc 155
/*     */     //   372: imul
/*     */     //   373: bipush 18
/*     */     //   375: if_icmpgt +18 -> 393
/*     */     //   378: iload_1
/*     */     //   379: ldc 147
/*     */     //   381: if_icmpeq +4 -> 385
/*     */     //   384: return
/*     */     //   385: iconst_1
/*     */     //   386: iconst_1
/*     */     //   387: ldc 164
/*     */     //   389: invokestatic 161	client:i	(III)V
/*     */     //   392: return
/*     */     //   393: sipush 500
/*     */     //   396: istore 4
/*     */     //   398: getstatic 151	an:v	I
/*     */     //   401: ldc 148
/*     */     //   403: imul
/*     */     //   404: iload 4
/*     */     //   406: if_icmplt +78 -> 484
/*     */     //   409: iload_1
/*     */     //   410: ldc 147
/*     */     //   412: if_icmpeq +4 -> 416
/*     */     //   415: return
/*     */     //   416: getstatic 151	an:v	I
/*     */     //   419: ldc 148
/*     */     //   421: imul
/*     */     //   422: iload 4
/*     */     //   424: bipush 14
/*     */     //   426: iadd
/*     */     //   427: if_icmpgt +57 -> 484
/*     */     //   430: iload_1
/*     */     //   431: ldc 147
/*     */     //   433: if_icmpeq +6 -> 439
/*     */     //   436: goto +0 -> 436
/*     */     //   439: getstatic 154	an:w	I
/*     */     //   442: ldc 155
/*     */     //   444: imul
/*     */     //   445: iconst_4
/*     */     //   446: if_icmplt +38 -> 484
/*     */     //   449: iload_1
/*     */     //   450: ldc 147
/*     */     //   452: if_icmpeq +4 -> 456
/*     */     //   455: return
/*     */     //   456: getstatic 154	an:w	I
/*     */     //   459: ldc 155
/*     */     //   461: imul
/*     */     //   462: bipush 18
/*     */     //   464: if_icmpgt +20 -> 484
/*     */     //   467: iload_1
/*     */     //   468: ldc 147
/*     */     //   470: if_icmpeq +6 -> 476
/*     */     //   473: goto +0 -> 473
/*     */     //   476: iconst_2
/*     */     //   477: iconst_0
/*     */     //   478: ldc 165
/*     */     //   480: invokestatic 161	client:i	(III)V
/*     */     //   483: return
/*     */     //   484: ldc 148
/*     */     //   486: getstatic 151	an:v	I
/*     */     //   489: imul
/*     */     //   490: iload 4
/*     */     //   492: bipush 15
/*     */     //   494: iadd
/*     */     //   495: if_icmplt +85 -> 580
/*     */     //   498: iload_1
/*     */     //   499: ldc 147
/*     */     //   501: if_icmpeq +4 -> 505
/*     */     //   504: return
/*     */     //   505: getstatic 151	an:v	I
/*     */     //   508: ldc 148
/*     */     //   510: imul
/*     */     //   511: bipush 80
/*     */     //   513: iload 4
/*     */     //   515: iadd
/*     */     //   516: if_icmpgt +64 -> 580
/*     */     //   519: iload_1
/*     */     //   520: ldc 147
/*     */     //   522: if_icmpeq +6 -> 528
/*     */     //   525: goto +3 -> 528
/*     */     //   528: ldc 155
/*     */     //   530: getstatic 154	an:w	I
/*     */     //   533: imul
/*     */     //   534: iconst_4
/*     */     //   535: if_icmplt +45 -> 580
/*     */     //   538: iload_1
/*     */     //   539: ldc 147
/*     */     //   541: if_icmpeq +6 -> 547
/*     */     //   544: goto +3 -> 547
/*     */     //   547: ldc 155
/*     */     //   549: getstatic 154	an:w	I
/*     */     //   552: imul
/*     */     //   553: bipush 18
/*     */     //   555: if_icmpgt +25 -> 580
/*     */     //   558: iload_1
/*     */     //   559: ldc 147
/*     */     //   561: if_icmpeq +11 -> 572
/*     */     //   564: new 35	java/lang/IllegalStateException
/*     */     //   567: dup
/*     */     //   568: invokespecial 36	java/lang/IllegalStateException:<init>	()V
/*     */     //   571: athrow
/*     */     //   572: iconst_2
/*     */     //   573: iconst_1
/*     */     //   574: ldc 166
/*     */     //   576: invokestatic 161	client:i	(III)V
/*     */     //   579: return
/*     */     //   580: sipush 610
/*     */     //   583: istore 5
/*     */     //   585: getstatic 151	an:v	I
/*     */     //   588: ldc 148
/*     */     //   590: imul
/*     */     //   591: iload 5
/*     */     //   593: if_icmplt +83 -> 676
/*     */     //   596: iload_1
/*     */     //   597: ldc 147
/*     */     //   599: if_icmpeq +4 -> 603
/*     */     //   602: return
/*     */     //   603: ldc 148
/*     */     //   605: getstatic 151	an:v	I
/*     */     //   608: imul
/*     */     //   609: iload 5
/*     */     //   611: bipush 14
/*     */     //   613: iadd
/*     */     //   614: if_icmpgt +62 -> 676
/*     */     //   617: iload_1
/*     */     //   618: ldc 147
/*     */     //   620: if_icmpeq +6 -> 626
/*     */     //   623: goto +3 -> 626
/*     */     //   626: ldc 155
/*     */     //   628: getstatic 154	an:w	I
/*     */     //   631: imul
/*     */     //   632: iconst_4
/*     */     //   633: if_icmplt +43 -> 676
/*     */     //   636: iload_1
/*     */     //   637: ldc 147
/*     */     //   639: if_icmpeq +4 -> 643
/*     */     //   642: return
/*     */     //   643: ldc 155
/*     */     //   645: getstatic 154	an:w	I
/*     */     //   648: imul
/*     */     //   649: bipush 18
/*     */     //   651: if_icmpgt +25 -> 676
/*     */     //   654: iload_1
/*     */     //   655: ldc 147
/*     */     //   657: if_icmpeq +11 -> 668
/*     */     //   660: new 35	java/lang/IllegalStateException
/*     */     //   663: dup
/*     */     //   664: invokespecial 36	java/lang/IllegalStateException:<init>	()V
/*     */     //   667: athrow
/*     */     //   668: iconst_3
/*     */     //   669: iconst_0
/*     */     //   670: ldc 167
/*     */     //   672: invokestatic 161	client:i	(III)V
/*     */     //   675: return
/*     */     //   676: getstatic 151	an:v	I
/*     */     //   679: ldc 148
/*     */     //   681: imul
/*     */     //   682: iload 5
/*     */     //   684: bipush 15
/*     */     //   686: iadd
/*     */     //   687: if_icmplt +87 -> 774
/*     */     //   690: iload_1
/*     */     //   691: ldc 147
/*     */     //   693: if_icmpeq +6 -> 699
/*     */     //   696: goto +3 -> 699
/*     */     //   699: ldc 148
/*     */     //   701: getstatic 151	an:v	I
/*     */     //   704: imul
/*     */     //   705: bipush 80
/*     */     //   707: iload 5
/*     */     //   709: iadd
/*     */     //   710: if_icmpgt +64 -> 774
/*     */     //   713: iload_1
/*     */     //   714: ldc 147
/*     */     //   716: if_icmpeq +11 -> 727
/*     */     //   719: new 35	java/lang/IllegalStateException
/*     */     //   722: dup
/*     */     //   723: invokespecial 36	java/lang/IllegalStateException:<init>	()V
/*     */     //   726: athrow
/*     */     //   727: ldc 155
/*     */     //   729: getstatic 154	an:w	I
/*     */     //   732: imul
/*     */     //   733: iconst_4
/*     */     //   734: if_icmplt +40 -> 774
/*     */     //   737: iload_1
/*     */     //   738: ldc 147
/*     */     //   740: if_icmpeq +6 -> 746
/*     */     //   743: goto +3 -> 746
/*     */     //   746: getstatic 154	an:w	I
/*     */     //   749: ldc 155
/*     */     //   751: imul
/*     */     //   752: bipush 18
/*     */     //   754: if_icmpgt +20 -> 774
/*     */     //   757: iload_1
/*     */     //   758: ldc 147
/*     */     //   760: if_icmpeq +6 -> 766
/*     */     //   763: goto +3 -> 766
/*     */     //   766: iconst_3
/*     */     //   767: iconst_1
/*     */     //   768: ldc 168
/*     */     //   770: invokestatic 161	client:i	(III)V
/*     */     //   773: return
/*     */     //   774: getstatic 151	an:v	I
/*     */     //   777: ldc 148
/*     */     //   779: imul
/*     */     //   780: sipush 708
/*     */     //   783: if_icmplt +120 -> 903
/*     */     //   786: iload_1
/*     */     //   787: ldc 147
/*     */     //   789: if_icmpeq +6 -> 795
/*     */     //   792: goto +0 -> 792
/*     */     //   795: getstatic 154	an:w	I
/*     */     //   798: ldc 155
/*     */     //   800: imul
/*     */     //   801: iconst_4
/*     */     //   802: if_icmplt +101 -> 903
/*     */     //   805: iload_1
/*     */     //   806: ldc 147
/*     */     //   808: if_icmpeq +6 -> 814
/*     */     //   811: goto +0 -> 811
/*     */     //   814: ldc 148
/*     */     //   816: getstatic 151	an:v	I
/*     */     //   819: imul
/*     */     //   820: sipush 758
/*     */     //   823: if_icmpgt +80 -> 903
/*     */     //   826: iload_1
/*     */     //   827: ldc 147
/*     */     //   829: if_icmpeq +6 -> 835
/*     */     //   832: goto +0 -> 832
/*     */     //   835: getstatic 154	an:w	I
/*     */     //   838: ldc 155
/*     */     //   840: imul
/*     */     //   841: bipush 20
/*     */     //   843: if_icmpgt +60 -> 903
/*     */     //   846: iload_1
/*     */     //   847: ldc 147
/*     */     //   849: if_icmpeq +11 -> 860
/*     */     //   852: new 35	java/lang/IllegalStateException
/*     */     //   855: dup
/*     */     //   856: invokespecial 36	java/lang/IllegalStateException:<init>	()V
/*     */     //   859: athrow
/*     */     //   860: iconst_0
/*     */     //   861: putstatic 172	g:ao	Z
/*     */     //   864: getstatic 176	g:c	Lfq;
/*     */     //   867: iconst_0
/*     */     //   868: iconst_0
/*     */     //   869: invokevirtual 182	fq:cr	(II)V
/*     */     //   872: getstatic 186	ac:n	Lfq;
/*     */     //   875: sipush 382
/*     */     //   878: iconst_0
/*     */     //   879: invokevirtual 182	fq:cr	(II)V
/*     */     //   882: getstatic 189	g:j	Lft;
/*     */     //   885: sipush 382
/*     */     //   888: getstatic 189	g:j	Lft;
/*     */     //   891: getfield 192	ft:w	I
/*     */     //   894: iconst_2
/*     */     //   895: idiv
/*     */     //   896: isub
/*     */     //   897: bipush 18
/*     */     //   899: invokevirtual 195	ft:be	(II)V
/*     */     //   902: return
/*     */     //   903: iconst_m1
/*     */     //   904: getstatic 198	g:bk	I
/*     */     //   907: ldc 199
/*     */     //   909: imul
/*     */     //   910: if_icmpeq +329 -> 1239
/*     */     //   913: iload_1
/*     */     //   914: ldc 147
/*     */     //   916: if_icmpeq +6 -> 922
/*     */     //   919: goto +0 -> 919
/*     */     //   922: getstatic 204	v:ai	[Lc;
/*     */     //   925: getstatic 198	g:bk	I
/*     */     //   928: ldc 199
/*     */     //   930: imul
/*     */     //   931: aaload
/*     */     //   932: astore 6
/*     */     //   934: aload 6
/*     */     //   936: getfield 207	c:n	Z
/*     */     //   939: getstatic 210	client:ab	Z
/*     */     //   942: if_icmpne +169 -> 1111
/*     */     //   945: iload_1
/*     */     //   946: ldc 147
/*     */     //   948: if_icmpeq +4 -> 952
/*     */     //   951: return
/*     */     //   952: aload 6
/*     */     //   954: getfield 213	c:l	Ljava/lang/String;
/*     */     //   957: putstatic 216	c:ck	Ljava/lang/String;
/*     */     //   960: aload 6
/*     */     //   962: getfield 217	c:r	I
/*     */     //   965: ldc 218
/*     */     //   967: imul
/*     */     //   968: putstatic 221	client:az	I
/*     */     //   971: iconst_0
/*     */     //   972: ldc 222
/*     */     //   974: getstatic 225	client:ah	I
/*     */     //   977: imul
/*     */     //   978: if_icmpne +22 -> 1000
/*     */     //   981: iload_1
/*     */     //   982: ldc 147
/*     */     //   984: if_icmpeq +11 -> 995
/*     */     //   987: new 35	java/lang/IllegalStateException
/*     */     //   990: dup
/*     */     //   991: invokespecial 36	java/lang/IllegalStateException:<init>	()V
/*     */     //   994: athrow
/*     */     //   995: ldc 226
/*     */     //   997: goto +14 -> 1011
/*     */     //   1000: ldc 227
/*     */     //   1002: ldc 228
/*     */     //   1004: aload 6
/*     */     //   1006: getfield 217	c:r	I
/*     */     //   1009: imul
/*     */     //   1010: iadd
/*     */     //   1011: ldc 229
/*     */     //   1013: imul
/*     */     //   1014: putstatic 234	dn:cy	I
/*     */     //   1017: ldc 235
/*     */     //   1019: iconst_0
/*     */     //   1020: ldc 222
/*     */     //   1022: getstatic 225	client:ah	I
/*     */     //   1025: imul
/*     */     //   1026: if_icmpne +18 -> 1044
/*     */     //   1029: iload_1
/*     */     //   1030: ldc 147
/*     */     //   1032: if_icmpeq +6 -> 1038
/*     */     //   1035: goto +0 -> 1035
/*     */     //   1038: sipush 443
/*     */     //   1041: goto +14 -> 1055
/*     */     //   1044: ldc 228
/*     */     //   1046: aload 6
/*     */     //   1048: getfield 217	c:r	I
/*     */     //   1051: imul
/*     */     //   1052: ldc 236
/*     */     //   1054: iadd
/*     */     //   1055: imul
/*     */     //   1056: putstatic 242	d:cq	I
/*     */     //   1059: ldc 243
/*     */     //   1061: getstatic 234	dn:cy	I
/*     */     //   1064: imul
/*     */     //   1065: putstatic 248	cu:cd	I
/*     */     //   1068: iconst_0
/*     */     //   1069: putstatic 172	g:ao	Z
/*     */     //   1072: getstatic 176	g:c	Lfq;
/*     */     //   1075: iconst_0
/*     */     //   1076: iconst_0
/*     */     //   1077: invokevirtual 182	fq:cr	(II)V
/*     */     //   1080: getstatic 186	ac:n	Lfq;
/*     */     //   1083: sipush 382
/*     */     //   1086: iconst_0
/*     */     //   1087: invokevirtual 182	fq:cr	(II)V
/*     */     //   1090: getstatic 189	g:j	Lft;
/*     */     //   1093: sipush 382
/*     */     //   1096: getstatic 189	g:j	Lft;
/*     */     //   1099: getfield 192	ft:w	I
/*     */     //   1102: iconst_2
/*     */     //   1103: idiv
/*     */     //   1104: isub
/*     */     //   1105: bipush 18
/*     */     //   1107: invokevirtual 195	ft:be	(II)V
/*     */     //   1110: return
/*     */     //   1111: ldc 250
/*     */     //   1113: astore 7
/*     */     //   1115: getstatic 225	client:ah	I
/*     */     //   1118: ldc 222
/*     */     //   1120: imul
/*     */     //   1121: ifeq +45 -> 1166
/*     */     //   1124: iload_1
/*     */     //   1125: ldc 147
/*     */     //   1127: if_icmpeq +6 -> 1133
/*     */     //   1130: goto +3 -> 1133
/*     */     //   1133: new 254	java/lang/StringBuilder
/*     */     //   1136: dup
/*     */     //   1137: invokespecial 255	java/lang/StringBuilder:<init>	()V
/*     */     //   1140: ldc_w 257
/*     */     //   1143: invokevirtual 261	java/lang/StringBuilder:append	(Ljava/lang/String;)Ljava/lang/StringBuilder;
/*     */     //   1146: ldc 228
/*     */     //   1148: aload 6
/*     */     //   1150: getfield 217	c:r	I
/*     */     //   1153: imul
/*     */     //   1154: sipush 7000
/*     */     //   1157: iadd
/*     */     //   1158: invokevirtual 264	java/lang/StringBuilder:append	(I)Ljava/lang/StringBuilder;
/*     */     //   1161: invokevirtual 268	java/lang/StringBuilder:toString	()Ljava/lang/String;
/*     */     //   1164: astore 7
/*     */     //   1166: new 254	java/lang/StringBuilder
/*     */     //   1169: dup
/*     */     //   1170: invokespecial 255	java/lang/StringBuilder:<init>	()V
/*     */     //   1173: ldc_w 270
/*     */     //   1176: invokevirtual 261	java/lang/StringBuilder:append	(Ljava/lang/String;)Ljava/lang/StringBuilder;
/*     */     //   1179: aload 6
/*     */     //   1181: getfield 213	c:l	Ljava/lang/String;
/*     */     //   1184: invokevirtual 261	java/lang/StringBuilder:append	(Ljava/lang/String;)Ljava/lang/StringBuilder;
/*     */     //   1187: aload 7
/*     */     //   1189: invokevirtual 261	java/lang/StringBuilder:append	(Ljava/lang/String;)Ljava/lang/StringBuilder;
/*     */     //   1192: ldc_w 272
/*     */     //   1195: invokevirtual 261	java/lang/StringBuilder:append	(Ljava/lang/String;)Ljava/lang/StringBuilder;
/*     */     //   1198: ldc_w 273
/*     */     //   1201: getstatic 276	client:ar	I
/*     */     //   1204: imul
/*     */     //   1205: invokevirtual 264	java/lang/StringBuilder:append	(I)Ljava/lang/StringBuilder;
/*     */     //   1208: invokevirtual 268	java/lang/StringBuilder:toString	()Ljava/lang/String;
/*     */     //   1211: astore 8
/*     */     //   1213: aload_0
/*     */     //   1214: invokevirtual 280	dj:getAppletContext	()Ljava/applet/AppletContext;
/*     */     //   1217: new 282	java/net/URL
/*     */     //   1220: dup
/*     */     //   1221: aload 8
/*     */     //   1223: invokespecial 285	java/net/URL:<init>	(Ljava/lang/String;)V
/*     */     //   1226: ldc_w 287
/*     */     //   1229: invokeinterface 293 3 0
/*     */     //   1234: goto +5 -> 1239
/*     */     //   1237: astore 9
/*     */     //   1239: return
/*     */     //
/*     */     // Exception table:
/*     */     //   from	to	target	type
/*     */     //   1213	1234	1237	java/lang/Exception
/*     */   }
/*     */ 
/*     */   public static synchronized long r(int paramInt)
/*     */   {
/*  14 */     long l1 = System.currentTimeMillis();
/*  15 */     if (l1 < bx.r * 553834852874162873L) { if (paramInt <= 808825319) throw new IllegalStateException();
/*  16 */       bx.d += (bx.r * 553834852874162873L - l1) * 2366144303545568725L;
/*     */     }
/*  18 */     bx.r = l1 * -272556416233843831L;
/*  19 */     return l1 + 2846342234207224701L * bx.d;
/*     */   }
/*     */ }

/* Location:           C:\Users\Mike\IdeaProjects\RealityBot-2007 Updater\client-deob.jar
 * Qualified Name:     cm
 * JD-Core Version:    0.6.2
 */