/*      */ public final class de extends dg
/*      */ {
/*      */   int s;
/*      */   int c;
/*      */   et u;
/*      */   int[] w;
/*      */   int z;
/*      */   int j;
/*      */   int q;
/*      */   int i;
/*      */   int n;
/*      */   int g;
/*      */   int v;
/*   11 */   static cg m = new cg();
/*      */   int e;
/*      */   et b;
/*      */   ey y;
/*      */   static int oy;
/*      */ 
/*      */   static void g()
/*      */   {
/*   30 */     for (de localde = (de)m.j(); null != localde; localde = (de)m.g())
/*   31 */       if (null != localde.y) localde.n(-212036419);
/*      */   }
/*      */ 
/*      */   void n(int paramInt)
/*      */   {
/*   36 */     int k = this.i * 1995197999;
/*   37 */     ey localey = this.y.t((byte)-1);
/*   38 */     if (null != localey) { if (paramInt < 776390842);
/*   39 */       this.i = (localey.af * -151395397);
/*   40 */       this.q = (localey.bh * 94712448);
/*   41 */       this.s = (-427594353 * localey.bi);
/*   42 */       this.v = (-1121775919 * localey.bs);
/*   43 */       this.w = localey.bk;
/*      */     } else
/*      */     {
/*   46 */       this.i = -1630910671;
/*   47 */       this.q = 0;
/*   48 */       this.s = 0;
/*   49 */       this.v = 0;
/*   50 */       this.w = null;
/*      */     }
/*   52 */     if ((this.i * 1995197999 != k) && ((paramInt >= 776390842) || (null != this.u))) { if (paramInt >= 776390842) return;
/*   53 */       cq.oc.ad(this.u);
/*   54 */       this.u = null;
/*      */     }
/*      */   }
/*      */ 
/*      */   void s()
/*      */   {
/*   36 */     int k = this.i * 1995197999;
/*   37 */     ey localey = this.y.t((byte)-68);
/*   38 */     if (null != localey) {
/*   39 */       this.i = (localey.af * -151395397);
/*   40 */       this.q = (localey.bh * 94712448);
/*   41 */       this.s = (-427594353 * localey.bi);
/*   42 */       this.v = (-1121775919 * localey.bs);
/*   43 */       this.w = localey.bk;
/*      */     }
/*      */     else {
/*   46 */       this.i = -1630910671;
/*   47 */       this.q = 0;
/*   48 */       this.s = 0;
/*   49 */       this.v = 0;
/*   50 */       this.w = null;
/*      */     }
/*   52 */     if ((this.i * 1995197999 != k) && (null != this.u)) {
/*   53 */       cq.oc.ad(this.u);
/*   54 */       this.u = null;
/*      */     }
/*      */   }
/*      */ 
/*      */   static void i()
/*      */   {
/*   30 */     for (de localde = (de)m.j(); null != localde; localde = (de)m.g())
/*   31 */       if (null != localde.y) localde.n(187342575);
/*      */   }
/*      */ 
/*      */   static void q()
/*      */   {
/*   30 */     for (de localde = (de)m.j(); null != localde; localde = (de)m.g())
/*   31 */       if (null != localde.y) localde.n(-852292044);
/*      */   }
/*      */ 
/*      */   void u()
/*      */   {
/*   36 */     int k = this.i * 1995197999;
/*   37 */     ey localey = this.y.t((byte)83);
/*   38 */     if (null != localey) {
/*   39 */       this.i = (localey.af * -151395397);
/*   40 */       this.q = (localey.bh * 94712448);
/*   41 */       this.s = (-427594353 * localey.bi);
/*   42 */       this.v = (-1121775919 * localey.bs);
/*   43 */       this.w = localey.bk;
/*      */     }
/*      */     else {
/*   46 */       this.i = -1630910671;
/*   47 */       this.q = 0;
/*   48 */       this.s = 0;
/*   49 */       this.v = 0;
/*   50 */       this.w = null;
/*      */     }
/*   52 */     if ((this.i * 1995197999 != k) && (null != this.u)) {
/*   53 */       cq.oc.ad(this.u);
/*   54 */       this.u = null;
/*      */     }
/*      */   }
/*      */ 
/*      */   static void v(int paramInt1, int paramInt2, int paramInt3, ey paramey, int paramInt4) {
/*   59 */     de localde = new de();
/*   60 */     localde.c = (116794091 * paramInt1);
/*   61 */     localde.n = (1283318912 * paramInt2);
/*   62 */     localde.j = (-956376192 * paramInt3);
/*   63 */     int k = 533735227 * paramey.o;
/*   64 */     int i1 = paramey.a * -1137199387;
/*   65 */     if ((paramInt4 == 1) || (3 == paramInt4)) {
/*   66 */       k = paramey.a * -1137199387;
/*   67 */       i1 = 533735227 * paramey.o;
/*      */     }
/*   69 */     localde.z = ((k + paramInt2) * 1316003456);
/*   70 */     localde.g = (-175821184 * (paramInt3 + i1));
/*   71 */     localde.i = (-151395397 * paramey.af);
/*   72 */     localde.q = (94712448 * paramey.bh);
/*   73 */     localde.s = (-427594353 * paramey.bi);
/*   74 */     localde.v = (-1121775919 * paramey.bs);
/*   75 */     localde.w = paramey.bk;
/*   76 */     if (null != paramey.ai) {
/*   77 */       localde.y = paramey;
/*   78 */       localde.n(-1207841183);
/*      */     }
/*   80 */     m.d(localde);
/*   81 */     if (null != localde.w) localde.e = ((localde.s * 126224035 + (int)(Math.random() * (540356717 * localde.v - localde.s * 126224035))) * 1914159225);
/*      */   }
/*      */ 
/*      */   static void w(int paramInt1, int paramInt2, int paramInt3, ey paramey, int paramInt4)
/*      */   {
/*   59 */     de localde = new de();
/*   60 */     localde.c = (116794091 * paramInt1);
/*   61 */     localde.n = (1283318912 * paramInt2);
/*   62 */     localde.j = (-956376192 * paramInt3);
/*   63 */     int k = 533735227 * paramey.o;
/*   64 */     int i1 = paramey.a * -1137199387;
/*   65 */     if ((paramInt4 == 1) || (3 == paramInt4)) {
/*   66 */       k = paramey.a * -1137199387;
/*   67 */       i1 = 533735227 * paramey.o;
/*      */     }
/*   69 */     localde.z = ((k + paramInt2) * 1316003456);
/*   70 */     localde.g = (-175821184 * (paramInt3 + i1));
/*   71 */     localde.i = (-151395397 * paramey.af);
/*   72 */     localde.q = (94712448 * paramey.bh);
/*   73 */     localde.s = (-427594353 * paramey.bi);
/*   74 */     localde.v = (-1121775919 * paramey.bs);
/*   75 */     localde.w = paramey.bk;
/*   76 */     if (null != paramey.ai) {
/*   77 */       localde.y = paramey;
/*   78 */       localde.n(-1177251418);
/*      */     }
/*   80 */     m.d(localde);
/*   81 */     if (null != localde.w) localde.e = ((localde.s * 126224035 + (int)(Math.random() * (540356717 * localde.v - localde.s * 126224035))) * 1914159225);
/*      */   }
/*      */ 
/*      */   static void dv(eo parameo, int paramInt1, int paramInt2, int paramInt3, int paramInt4)
/*      */   {
/* 4397 */     if (client.os * 1331520119 < 50) { if (paramInt4 != 1509628094) throw new IllegalStateException(); if (client.oz * -1639239111 != 0) break label46; if (paramInt4 != 1509628094); } return;
/* 4398 */     label46: if (parameo.v != null) { if (paramInt4 != 1509628094) throw new IllegalStateException(); if (paramInt1 < parameo.v.length) break label88; if (paramInt4 != 1509628094); } return;
/* 4399 */     label88: int k = parameo.v[paramInt1];
/* 4400 */     if (k == 0) { if (paramInt4 != 1509628094) return; return; }
/* 4401 */     int i1 = k >> 8;
/* 4402 */     int i2 = k >> 4 & 0x7;
/* 4403 */     int i3 = k & 0xF;
/* 4404 */     client.oe[(client.os * 1331520119)] = i1;
/* 4405 */     client.of[(client.os * 1331520119)] = i2;
/* 4406 */     client.ov[(client.os * 1331520119)] = 0;
/* 4407 */     client.ok[(1331520119 * client.os)] = null;
/* 4408 */     int i4 = (paramInt2 - 64) / 128;
/* 4409 */     int i5 = (paramInt3 - 64) / 128;
/* 4410 */     client.oo[(client.os * 1331520119)] = (i3 + ((i5 << 8) + (i4 << 16)));
/* 4411 */     client.os += 1476859719;
/*      */   }
/*      */ 
/*      */   // ERROR //
/*      */   static void z(fm paramfm1, fm paramfm2, int paramInt)
/*      */   {
/*      */     // Byte code:
/*      */     //   0: getstatic 192	da:ar	[Lfq;
/*      */     //   3: ifnonnull +27 -> 30
/*      */     //   6: iload_2
/*      */     //   7: ldc 193
/*      */     //   9: if_icmpne +6 -> 15
/*      */     //   12: goto +0 -> 12
/*      */     //   15: getstatic 197	client:cj	Ldq;
/*      */     //   18: ldc 199
/*      */     //   20: ldc 201
/*      */     //   22: ldc 202
/*      */     //   24: invokestatic 208	bx:l	(Lch;Ljava/lang/String;Ljava/lang/String;I)[Lfq;
/*      */     //   27: putstatic 192	da:ar	[Lfq;
/*      */     //   30: getstatic 214	fn:aq	[Lft;
/*      */     //   33: ifnonnull +27 -> 60
/*      */     //   36: iload_2
/*      */     //   37: ldc 193
/*      */     //   39: if_icmpne +6 -> 45
/*      */     //   42: goto +0 -> 42
/*      */     //   45: getstatic 197	client:cj	Ldq;
/*      */     //   48: ldc 216
/*      */     //   50: ldc 201
/*      */     //   52: bipush 253
/*      */     //   54: invokestatic 222	al:r	(Lch;Ljava/lang/String;Ljava/lang/String;B)[Lft;
/*      */     //   57: putstatic 214	fn:aq	[Lft;
/*      */     //   60: aconst_null
/*      */     //   61: getstatic 227	au:at	[Lft;
/*      */     //   64: if_acmpne +27 -> 91
/*      */     //   67: iload_2
/*      */     //   68: ldc 193
/*      */     //   70: if_icmpne +6 -> 76
/*      */     //   73: goto +3 -> 76
/*      */     //   76: getstatic 197	client:cj	Ldq;
/*      */     //   79: ldc 229
/*      */     //   81: ldc 201
/*      */     //   83: bipush 208
/*      */     //   85: invokestatic 222	al:r	(Lch;Ljava/lang/String;Ljava/lang/String;B)[Lft;
/*      */     //   88: putstatic 227	au:at	[Lft;
/*      */     //   91: getstatic 232	bx:ae	[Lft;
/*      */     //   94: ifnonnull +27 -> 121
/*      */     //   97: iload_2
/*      */     //   98: ldc 193
/*      */     //   100: if_icmpne +6 -> 106
/*      */     //   103: goto +3 -> 106
/*      */     //   106: getstatic 197	client:cj	Ldq;
/*      */     //   109: ldc 234
/*      */     //   111: ldc 201
/*      */     //   113: bipush 132
/*      */     //   115: invokestatic 222	al:r	(Lch;Ljava/lang/String;Ljava/lang/String;B)[Lft;
/*      */     //   118: putstatic 232	bx:ae	[Lft;
/*      */     //   121: iconst_0
/*      */     //   122: bipush 23
/*      */     //   124: sipush 765
/*      */     //   127: sipush 480
/*      */     //   130: iconst_0
/*      */     //   131: invokestatic 239	fv:e	(IIIII)V
/*      */     //   134: iconst_0
/*      */     //   135: iconst_0
/*      */     //   136: bipush 125
/*      */     //   138: bipush 23
/*      */     //   140: ldc 240
/*      */     //   142: ldc 241
/*      */     //   144: invokestatic 244	fv:b	(IIIIII)V
/*      */     //   147: bipush 125
/*      */     //   149: iconst_0
/*      */     //   150: sipush 640
/*      */     //   153: bipush 23
/*      */     //   155: ldc 245
/*      */     //   157: ldc 246
/*      */     //   159: invokestatic 244	fv:b	(IIIIII)V
/*      */     //   162: aload_0
/*      */     //   163: getstatic 252	ba:hn	Ljava/lang/String;
/*      */     //   166: bipush 62
/*      */     //   168: bipush 15
/*      */     //   170: iconst_0
/*      */     //   171: iconst_m1
/*      */     //   172: invokevirtual 258	fm:cs	(Ljava/lang/String;IIII)V
/*      */     //   175: aconst_null
/*      */     //   176: getstatic 232	bx:ae	[Lft;
/*      */     //   179: if_acmpeq +69 -> 248
/*      */     //   182: iload_2
/*      */     //   183: ldc 193
/*      */     //   185: if_icmpne +6 -> 191
/*      */     //   188: goto +3 -> 191
/*      */     //   191: getstatic 232	bx:ae	[Lft;
/*      */     //   194: iconst_1
/*      */     //   195: aaload
/*      */     //   196: sipush 140
/*      */     //   199: iconst_1
/*      */     //   200: invokevirtual 264	ft:be	(II)V
/*      */     //   203: aload_1
/*      */     //   204: getstatic 267	ba:hs	Ljava/lang/String;
/*      */     //   207: sipush 152
/*      */     //   210: bipush 10
/*      */     //   212: ldc_w 268
/*      */     //   215: iconst_m1
/*      */     //   216: invokevirtual 271	fm:bd	(Ljava/lang/String;IIII)V
/*      */     //   219: getstatic 232	bx:ae	[Lft;
/*      */     //   222: iconst_0
/*      */     //   223: aaload
/*      */     //   224: sipush 140
/*      */     //   227: bipush 12
/*      */     //   229: invokevirtual 264	ft:be	(II)V
/*      */     //   232: aload_1
/*      */     //   233: getstatic 274	ba:hf	Ljava/lang/String;
/*      */     //   236: sipush 152
/*      */     //   239: bipush 21
/*      */     //   241: ldc_w 268
/*      */     //   244: iconst_m1
/*      */     //   245: invokevirtual 271	fm:bd	(Ljava/lang/String;IIII)V
/*      */     //   248: getstatic 227	au:at	[Lft;
/*      */     //   251: ifnull +641 -> 892
/*      */     //   254: iload_2
/*      */     //   255: ldc 193
/*      */     //   257: if_icmpne +4 -> 261
/*      */     //   260: return
/*      */     //   261: sipush 280
/*      */     //   264: istore_3
/*      */     //   265: iconst_0
/*      */     //   266: getstatic 277	g:bi	[I
/*      */     //   269: iconst_0
/*      */     //   270: iaload
/*      */     //   271: if_icmpne +52 -> 323
/*      */     //   274: iload_2
/*      */     //   275: ldc 193
/*      */     //   277: if_icmpne +11 -> 288
/*      */     //   280: new 157	java/lang/IllegalStateException
/*      */     //   283: dup
/*      */     //   284: invokespecial 158	java/lang/IllegalStateException:<init>	()V
/*      */     //   287: athrow
/*      */     //   288: getstatic 279	g:bs	[I
/*      */     //   291: iconst_0
/*      */     //   292: iaload
/*      */     //   293: ifne +30 -> 323
/*      */     //   296: iload_2
/*      */     //   297: ldc 193
/*      */     //   299: if_icmpne +11 -> 310
/*      */     //   302: new 157	java/lang/IllegalStateException
/*      */     //   305: dup
/*      */     //   306: invokespecial 158	java/lang/IllegalStateException:<init>	()V
/*      */     //   309: athrow
/*      */     //   310: getstatic 227	au:at	[Lft;
/*      */     //   313: iconst_2
/*      */     //   314: aaload
/*      */     //   315: iload_3
/*      */     //   316: iconst_4
/*      */     //   317: invokevirtual 264	ft:be	(II)V
/*      */     //   320: goto +13 -> 333
/*      */     //   323: getstatic 227	au:at	[Lft;
/*      */     //   326: iconst_0
/*      */     //   327: aaload
/*      */     //   328: iload_3
/*      */     //   329: iconst_4
/*      */     //   330: invokevirtual 264	ft:be	(II)V
/*      */     //   333: getstatic 277	g:bi	[I
/*      */     //   336: iconst_0
/*      */     //   337: iaload
/*      */     //   338: ifne +44 -> 382
/*      */     //   341: iload_2
/*      */     //   342: ldc 193
/*      */     //   344: if_icmpne +4 -> 348
/*      */     //   347: return
/*      */     //   348: iconst_1
/*      */     //   349: getstatic 279	g:bs	[I
/*      */     //   352: iconst_0
/*      */     //   353: iaload
/*      */     //   354: if_icmpne +28 -> 382
/*      */     //   357: iload_2
/*      */     //   358: ldc 193
/*      */     //   360: if_icmpne +6 -> 366
/*      */     //   363: goto +3 -> 366
/*      */     //   366: getstatic 227	au:at	[Lft;
/*      */     //   369: iconst_3
/*      */     //   370: aaload
/*      */     //   371: iload_3
/*      */     //   372: bipush 15
/*      */     //   374: iadd
/*      */     //   375: iconst_4
/*      */     //   376: invokevirtual 264	ft:be	(II)V
/*      */     //   379: goto +16 -> 395
/*      */     //   382: getstatic 227	au:at	[Lft;
/*      */     //   385: iconst_1
/*      */     //   386: aaload
/*      */     //   387: iload_3
/*      */     //   388: bipush 15
/*      */     //   390: iadd
/*      */     //   391: iconst_4
/*      */     //   392: invokevirtual 264	ft:be	(II)V
/*      */     //   395: aload_0
/*      */     //   396: getstatic 282	ba:hi	Ljava/lang/String;
/*      */     //   399: iload_3
/*      */     //   400: bipush 32
/*      */     //   402: iadd
/*      */     //   403: bipush 17
/*      */     //   405: ldc_w 268
/*      */     //   408: iconst_m1
/*      */     //   409: invokevirtual 271	fm:bd	(Ljava/lang/String;IIII)V
/*      */     //   412: sipush 390
/*      */     //   415: istore 4
/*      */     //   417: iconst_1
/*      */     //   418: getstatic 277	g:bi	[I
/*      */     //   421: iconst_0
/*      */     //   422: iaload
/*      */     //   423: if_icmpne +49 -> 472
/*      */     //   426: iload_2
/*      */     //   427: ldc 193
/*      */     //   429: if_icmpne +11 -> 440
/*      */     //   432: new 157	java/lang/IllegalStateException
/*      */     //   435: dup
/*      */     //   436: invokespecial 158	java/lang/IllegalStateException:<init>	()V
/*      */     //   439: athrow
/*      */     //   440: iconst_0
/*      */     //   441: getstatic 279	g:bs	[I
/*      */     //   444: iconst_0
/*      */     //   445: iaload
/*      */     //   446: if_icmpne +26 -> 472
/*      */     //   449: iload_2
/*      */     //   450: ldc 193
/*      */     //   452: if_icmpne +6 -> 458
/*      */     //   455: goto +3 -> 458
/*      */     //   458: getstatic 227	au:at	[Lft;
/*      */     //   461: iconst_2
/*      */     //   462: aaload
/*      */     //   463: iload 4
/*      */     //   465: iconst_4
/*      */     //   466: invokevirtual 264	ft:be	(II)V
/*      */     //   469: goto +14 -> 483
/*      */     //   472: getstatic 227	au:at	[Lft;
/*      */     //   475: iconst_0
/*      */     //   476: aaload
/*      */     //   477: iload 4
/*      */     //   479: iconst_4
/*      */     //   480: invokevirtual 264	ft:be	(II)V
/*      */     //   483: getstatic 277	g:bi	[I
/*      */     //   486: iconst_0
/*      */     //   487: iaload
/*      */     //   488: iconst_1
/*      */     //   489: if_icmpne +47 -> 536
/*      */     //   492: iload_2
/*      */     //   493: ldc 193
/*      */     //   495: if_icmpne +6 -> 501
/*      */     //   498: goto +3 -> 501
/*      */     //   501: getstatic 279	g:bs	[I
/*      */     //   504: iconst_0
/*      */     //   505: iaload
/*      */     //   506: iconst_1
/*      */     //   507: if_icmpne +29 -> 536
/*      */     //   510: iload_2
/*      */     //   511: ldc 193
/*      */     //   513: if_icmpne +6 -> 519
/*      */     //   516: goto +3 -> 519
/*      */     //   519: getstatic 227	au:at	[Lft;
/*      */     //   522: iconst_3
/*      */     //   523: aaload
/*      */     //   524: bipush 15
/*      */     //   526: iload 4
/*      */     //   528: iadd
/*      */     //   529: iconst_4
/*      */     //   530: invokevirtual 264	ft:be	(II)V
/*      */     //   533: goto +17 -> 550
/*      */     //   536: getstatic 227	au:at	[Lft;
/*      */     //   539: iconst_1
/*      */     //   540: aaload
/*      */     //   541: bipush 15
/*      */     //   543: iload 4
/*      */     //   545: iadd
/*      */     //   546: iconst_4
/*      */     //   547: invokevirtual 264	ft:be	(II)V
/*      */     //   550: aload_0
/*      */     //   551: getstatic 285	ba:hd	Ljava/lang/String;
/*      */     //   554: bipush 32
/*      */     //   556: iload 4
/*      */     //   558: iadd
/*      */     //   559: bipush 17
/*      */     //   561: ldc_w 268
/*      */     //   564: iconst_m1
/*      */     //   565: invokevirtual 271	fm:bd	(Ljava/lang/String;IIII)V
/*      */     //   568: sipush 500
/*      */     //   571: istore 5
/*      */     //   573: getstatic 277	g:bi	[I
/*      */     //   576: iconst_0
/*      */     //   577: iaload
/*      */     //   578: iconst_2
/*      */     //   579: if_icmpne +54 -> 633
/*      */     //   582: iload_2
/*      */     //   583: ldc 193
/*      */     //   585: if_icmpne +11 -> 596
/*      */     //   588: new 157	java/lang/IllegalStateException
/*      */     //   591: dup
/*      */     //   592: invokespecial 158	java/lang/IllegalStateException:<init>	()V
/*      */     //   595: athrow
/*      */     //   596: iconst_0
/*      */     //   597: getstatic 279	g:bs	[I
/*      */     //   600: iconst_0
/*      */     //   601: iaload
/*      */     //   602: if_icmpne +31 -> 633
/*      */     //   605: iload_2
/*      */     //   606: ldc 193
/*      */     //   608: if_icmpne +11 -> 619
/*      */     //   611: new 157	java/lang/IllegalStateException
/*      */     //   614: dup
/*      */     //   615: invokespecial 158	java/lang/IllegalStateException:<init>	()V
/*      */     //   618: athrow
/*      */     //   619: getstatic 227	au:at	[Lft;
/*      */     //   622: iconst_2
/*      */     //   623: aaload
/*      */     //   624: iload 5
/*      */     //   626: iconst_4
/*      */     //   627: invokevirtual 264	ft:be	(II)V
/*      */     //   630: goto +14 -> 644
/*      */     //   633: getstatic 227	au:at	[Lft;
/*      */     //   636: iconst_0
/*      */     //   637: aaload
/*      */     //   638: iload 5
/*      */     //   640: iconst_4
/*      */     //   641: invokevirtual 264	ft:be	(II)V
/*      */     //   644: getstatic 277	g:bi	[I
/*      */     //   647: iconst_0
/*      */     //   648: iaload
/*      */     //   649: iconst_2
/*      */     //   650: if_icmpne +52 -> 702
/*      */     //   653: iload_2
/*      */     //   654: ldc 193
/*      */     //   656: if_icmpne +11 -> 667
/*      */     //   659: new 157	java/lang/IllegalStateException
/*      */     //   662: dup
/*      */     //   663: invokespecial 158	java/lang/IllegalStateException:<init>	()V
/*      */     //   666: athrow
/*      */     //   667: iconst_1
/*      */     //   668: getstatic 279	g:bs	[I
/*      */     //   671: iconst_0
/*      */     //   672: iaload
/*      */     //   673: if_icmpne +29 -> 702
/*      */     //   676: iload_2
/*      */     //   677: ldc 193
/*      */     //   679: if_icmpne +6 -> 685
/*      */     //   682: goto +0 -> 682
/*      */     //   685: getstatic 227	au:at	[Lft;
/*      */     //   688: iconst_3
/*      */     //   689: aaload
/*      */     //   690: bipush 15
/*      */     //   692: iload 5
/*      */     //   694: iadd
/*      */     //   695: iconst_4
/*      */     //   696: invokevirtual 264	ft:be	(II)V
/*      */     //   699: goto +17 -> 716
/*      */     //   702: getstatic 227	au:at	[Lft;
/*      */     //   705: iconst_1
/*      */     //   706: aaload
/*      */     //   707: bipush 15
/*      */     //   709: iload 5
/*      */     //   711: iadd
/*      */     //   712: iconst_4
/*      */     //   713: invokevirtual 264	ft:be	(II)V
/*      */     //   716: aload_0
/*      */     //   717: getstatic 288	ba:ha	Ljava/lang/String;
/*      */     //   720: bipush 32
/*      */     //   722: iload 5
/*      */     //   724: iadd
/*      */     //   725: bipush 17
/*      */     //   727: ldc_w 268
/*      */     //   730: iconst_m1
/*      */     //   731: invokevirtual 271	fm:bd	(Ljava/lang/String;IIII)V
/*      */     //   734: sipush 610
/*      */     //   737: istore 6
/*      */     //   739: getstatic 277	g:bi	[I
/*      */     //   742: iconst_0
/*      */     //   743: iaload
/*      */     //   744: iconst_3
/*      */     //   745: if_icmpne +46 -> 791
/*      */     //   748: iload_2
/*      */     //   749: ldc 193
/*      */     //   751: if_icmpne +4 -> 755
/*      */     //   754: return
/*      */     //   755: getstatic 279	g:bs	[I
/*      */     //   758: iconst_0
/*      */     //   759: iaload
/*      */     //   760: ifne +31 -> 791
/*      */     //   763: iload_2
/*      */     //   764: ldc 193
/*      */     //   766: if_icmpne +11 -> 777
/*      */     //   769: new 157	java/lang/IllegalStateException
/*      */     //   772: dup
/*      */     //   773: invokespecial 158	java/lang/IllegalStateException:<init>	()V
/*      */     //   776: athrow
/*      */     //   777: getstatic 227	au:at	[Lft;
/*      */     //   780: iconst_2
/*      */     //   781: aaload
/*      */     //   782: iload 6
/*      */     //   784: iconst_4
/*      */     //   785: invokevirtual 264	ft:be	(II)V
/*      */     //   788: goto +14 -> 802
/*      */     //   791: getstatic 227	au:at	[Lft;
/*      */     //   794: iconst_0
/*      */     //   795: aaload
/*      */     //   796: iload 6
/*      */     //   798: iconst_4
/*      */     //   799: invokevirtual 264	ft:be	(II)V
/*      */     //   802: getstatic 277	g:bi	[I
/*      */     //   805: iconst_0
/*      */     //   806: iaload
/*      */     //   807: iconst_3
/*      */     //   808: if_icmpne +52 -> 860
/*      */     //   811: iload_2
/*      */     //   812: ldc 193
/*      */     //   814: if_icmpne +11 -> 825
/*      */     //   817: new 157	java/lang/IllegalStateException
/*      */     //   820: dup
/*      */     //   821: invokespecial 158	java/lang/IllegalStateException:<init>	()V
/*      */     //   824: athrow
/*      */     //   825: iconst_1
/*      */     //   826: getstatic 279	g:bs	[I
/*      */     //   829: iconst_0
/*      */     //   830: iaload
/*      */     //   831: if_icmpne +29 -> 860
/*      */     //   834: iload_2
/*      */     //   835: ldc 193
/*      */     //   837: if_icmpne +6 -> 843
/*      */     //   840: goto +0 -> 840
/*      */     //   843: getstatic 227	au:at	[Lft;
/*      */     //   846: iconst_3
/*      */     //   847: aaload
/*      */     //   848: bipush 15
/*      */     //   850: iload 6
/*      */     //   852: iadd
/*      */     //   853: iconst_4
/*      */     //   854: invokevirtual 264	ft:be	(II)V
/*      */     //   857: goto +17 -> 874
/*      */     //   860: getstatic 227	au:at	[Lft;
/*      */     //   863: iconst_1
/*      */     //   864: aaload
/*      */     //   865: iload 6
/*      */     //   867: bipush 15
/*      */     //   869: iadd
/*      */     //   870: iconst_4
/*      */     //   871: invokevirtual 264	ft:be	(II)V
/*      */     //   874: aload_0
/*      */     //   875: getstatic 291	ba:hg	Ljava/lang/String;
/*      */     //   878: iload 6
/*      */     //   880: bipush 32
/*      */     //   882: iadd
/*      */     //   883: bipush 17
/*      */     //   885: ldc_w 268
/*      */     //   888: iconst_m1
/*      */     //   889: invokevirtual 271	fm:bd	(Ljava/lang/String;IIII)V
/*      */     //   892: sipush 708
/*      */     //   895: iconst_4
/*      */     //   896: bipush 50
/*      */     //   898: bipush 16
/*      */     //   900: iconst_0
/*      */     //   901: invokestatic 239	fv:e	(IIIII)V
/*      */     //   904: aload_1
/*      */     //   905: getstatic 294	ba:hk	Ljava/lang/String;
/*      */     //   908: sipush 733
/*      */     //   911: bipush 16
/*      */     //   913: ldc_w 268
/*      */     //   916: iconst_m1
/*      */     //   917: invokevirtual 258	fm:cs	(Ljava/lang/String;IIII)V
/*      */     //   920: ldc_w 295
/*      */     //   923: putstatic 297	g:bk	I
/*      */     //   926: aconst_null
/*      */     //   927: getstatic 192	da:ar	[Lfq;
/*      */     //   930: if_acmpeq +799 -> 1729
/*      */     //   933: iload_2
/*      */     //   934: ldc 193
/*      */     //   936: if_icmpne +11 -> 947
/*      */     //   939: new 157	java/lang/IllegalStateException
/*      */     //   942: dup
/*      */     //   943: invokespecial 158	java/lang/IllegalStateException:<init>	()V
/*      */     //   946: athrow
/*      */     //   947: bipush 88
/*      */     //   949: istore_3
/*      */     //   950: bipush 19
/*      */     //   952: istore 4
/*      */     //   954: sipush 765
/*      */     //   957: iload_3
/*      */     //   958: iconst_1
/*      */     //   959: iadd
/*      */     //   960: idiv
/*      */     //   961: istore 5
/*      */     //   963: sipush 480
/*      */     //   966: iload 4
/*      */     //   968: iconst_1
/*      */     //   969: iadd
/*      */     //   970: idiv
/*      */     //   971: istore 6
/*      */     //   973: iload 6
/*      */     //   975: istore 7
/*      */     //   977: iload 5
/*      */     //   979: istore 8
/*      */     //   981: iload 6
/*      */     //   983: iload 5
/*      */     //   985: iconst_1
/*      */     //   986: isub
/*      */     //   987: imul
/*      */     //   988: ldc_w 298
/*      */     //   991: getstatic 301	g:ax	I
/*      */     //   994: imul
/*      */     //   995: if_icmplt +13 -> 1008
/*      */     //   998: iload_2
/*      */     //   999: ldc 193
/*      */     //   1001: if_icmpne +4 -> 1005
/*      */     //   1004: return
/*      */     //   1005: iinc 5 255
/*      */     //   1008: iload 6
/*      */     //   1010: iconst_1
/*      */     //   1011: isub
/*      */     //   1012: iload 5
/*      */     //   1014: imul
/*      */     //   1015: ldc_w 298
/*      */     //   1018: getstatic 301	g:ax	I
/*      */     //   1021: imul
/*      */     //   1022: if_icmplt +13 -> 1035
/*      */     //   1025: iload_2
/*      */     //   1026: ldc 193
/*      */     //   1028: if_icmpne +4 -> 1032
/*      */     //   1031: return
/*      */     //   1032: iinc 6 255
/*      */     //   1035: iload 5
/*      */     //   1037: iload 6
/*      */     //   1039: iconst_1
/*      */     //   1040: isub
/*      */     //   1041: imul
/*      */     //   1042: ldc_w 298
/*      */     //   1045: getstatic 301	g:ax	I
/*      */     //   1048: imul
/*      */     //   1049: if_icmplt +20 -> 1069
/*      */     //   1052: iload_2
/*      */     //   1053: ldc 193
/*      */     //   1055: if_icmpne +11 -> 1066
/*      */     //   1058: new 157	java/lang/IllegalStateException
/*      */     //   1061: dup
/*      */     //   1062: invokespecial 158	java/lang/IllegalStateException:<init>	()V
/*      */     //   1065: athrow
/*      */     //   1066: iinc 6 255
/*      */     //   1069: iload 6
/*      */     //   1071: iload 7
/*      */     //   1073: if_icmpne +34 -> 1107
/*      */     //   1076: iload_2
/*      */     //   1077: ldc 193
/*      */     //   1079: if_icmpne +4 -> 1083
/*      */     //   1082: return
/*      */     //   1083: iload 8
/*      */     //   1085: iload 5
/*      */     //   1087: if_icmpne +20 -> 1107
/*      */     //   1090: iload_2
/*      */     //   1091: ldc 193
/*      */     //   1093: if_icmpne +11 -> 1104
/*      */     //   1096: new 157	java/lang/IllegalStateException
/*      */     //   1099: dup
/*      */     //   1100: invokespecial 158	java/lang/IllegalStateException:<init>	()V
/*      */     //   1103: athrow
/*      */     //   1104: goto +6 -> 1110
/*      */     //   1107: goto -134 -> 973
/*      */     //   1110: sipush 765
/*      */     //   1113: iload_3
/*      */     //   1114: iload 5
/*      */     //   1116: imul
/*      */     //   1117: isub
/*      */     //   1118: iload 5
/*      */     //   1120: iconst_1
/*      */     //   1121: iadd
/*      */     //   1122: idiv
/*      */     //   1123: istore 7
/*      */     //   1125: iload 7
/*      */     //   1127: iconst_5
/*      */     //   1128: if_icmple +20 -> 1148
/*      */     //   1131: iload_2
/*      */     //   1132: ldc 193
/*      */     //   1134: if_icmpne +11 -> 1145
/*      */     //   1137: new 157	java/lang/IllegalStateException
/*      */     //   1140: dup
/*      */     //   1141: invokespecial 158	java/lang/IllegalStateException:<init>	()V
/*      */     //   1144: athrow
/*      */     //   1145: iconst_5
/*      */     //   1146: istore 7
/*      */     //   1148: sipush 480
/*      */     //   1151: iload 4
/*      */     //   1153: iload 6
/*      */     //   1155: imul
/*      */     //   1156: isub
/*      */     //   1157: iload 6
/*      */     //   1159: iconst_1
/*      */     //   1160: iadd
/*      */     //   1161: idiv
/*      */     //   1162: istore 8
/*      */     //   1164: iload 8
/*      */     //   1166: iconst_5
/*      */     //   1167: if_icmple +15 -> 1182
/*      */     //   1170: iload_2
/*      */     //   1171: ldc 193
/*      */     //   1173: if_icmpne +6 -> 1179
/*      */     //   1176: goto +0 -> 1176
/*      */     //   1179: iconst_5
/*      */     //   1180: istore 8
/*      */     //   1182: sipush 765
/*      */     //   1185: iload_3
/*      */     //   1186: iload 5
/*      */     //   1188: imul
/*      */     //   1189: isub
/*      */     //   1190: iload 5
/*      */     //   1192: iconst_1
/*      */     //   1193: isub
/*      */     //   1194: iload 7
/*      */     //   1196: imul
/*      */     //   1197: isub
/*      */     //   1198: iconst_2
/*      */     //   1199: idiv
/*      */     //   1200: istore 9
/*      */     //   1202: sipush 480
/*      */     //   1205: iload 6
/*      */     //   1207: iload 4
/*      */     //   1209: imul
/*      */     //   1210: isub
/*      */     //   1211: iload 8
/*      */     //   1213: iload 6
/*      */     //   1215: iconst_1
/*      */     //   1216: isub
/*      */     //   1217: imul
/*      */     //   1218: isub
/*      */     //   1219: iconst_2
/*      */     //   1220: idiv
/*      */     //   1221: istore 10
/*      */     //   1223: bipush 23
/*      */     //   1225: iload 10
/*      */     //   1227: iadd
/*      */     //   1228: istore 11
/*      */     //   1230: iload 9
/*      */     //   1232: istore 12
/*      */     //   1234: iconst_0
/*      */     //   1235: istore 13
/*      */     //   1237: iconst_0
/*      */     //   1238: istore 14
/*      */     //   1240: iload 14
/*      */     //   1242: ldc_w 298
/*      */     //   1245: getstatic 301	g:ax	I
/*      */     //   1248: imul
/*      */     //   1249: if_icmpge +480 -> 1729
/*      */     //   1252: iload_2
/*      */     //   1253: ldc 193
/*      */     //   1255: if_icmpne +4 -> 1259
/*      */     //   1258: return
/*      */     //   1259: getstatic 305	v:ai	[Lc;
/*      */     //   1262: iload 14
/*      */     //   1264: aaload
/*      */     //   1265: astore 15
/*      */     //   1267: iconst_1
/*      */     //   1268: istore 16
/*      */     //   1270: ldc_w 306
/*      */     //   1273: aload 15
/*      */     //   1275: getfield 309	c:d	I
/*      */     //   1278: imul
/*      */     //   1279: invokestatic 315	java/lang/Integer:toString	(I)Ljava/lang/String;
/*      */     //   1282: astore 17
/*      */     //   1284: iconst_m1
/*      */     //   1285: aload 15
/*      */     //   1287: getfield 309	c:d	I
/*      */     //   1290: ldc_w 306
/*      */     //   1293: imul
/*      */     //   1294: if_icmpne +28 -> 1322
/*      */     //   1297: iload_2
/*      */     //   1298: ldc 193
/*      */     //   1300: if_icmpne +11 -> 1311
/*      */     //   1303: new 157	java/lang/IllegalStateException
/*      */     //   1306: dup
/*      */     //   1307: invokespecial 158	java/lang/IllegalStateException:<init>	()V
/*      */     //   1310: athrow
/*      */     //   1311: getstatic 320	ba:hq	Ljava/lang/String;
/*      */     //   1314: astore 17
/*      */     //   1316: iconst_0
/*      */     //   1317: istore 16
/*      */     //   1319: goto +35 -> 1354
/*      */     //   1322: aload 15
/*      */     //   1324: getfield 309	c:d	I
/*      */     //   1327: ldc_w 306
/*      */     //   1330: imul
/*      */     //   1331: sipush 1980
/*      */     //   1334: if_icmple +20 -> 1354
/*      */     //   1337: iload_2
/*      */     //   1338: ldc 193
/*      */     //   1340: if_icmpne +6 -> 1346
/*      */     //   1343: goto +0 -> 1343
/*      */     //   1346: getstatic 323	ba:hh	Ljava/lang/String;
/*      */     //   1349: astore 17
/*      */     //   1351: iconst_0
/*      */     //   1352: istore 16
/*      */     //   1354: getstatic 326	an:j	I
/*      */     //   1357: ldc_w 327
/*      */     //   1360: imul
/*      */     //   1361: iload 12
/*      */     //   1363: if_icmplt +163 -> 1526
/*      */     //   1366: iload_2
/*      */     //   1367: ldc 193
/*      */     //   1369: if_icmpne +11 -> 1380
/*      */     //   1372: new 157	java/lang/IllegalStateException
/*      */     //   1375: dup
/*      */     //   1376: invokespecial 158	java/lang/IllegalStateException:<init>	()V
/*      */     //   1379: athrow
/*      */     //   1380: getstatic 328	an:z	I
/*      */     //   1383: ldc_w 329
/*      */     //   1386: imul
/*      */     //   1387: iload 11
/*      */     //   1389: if_icmplt +137 -> 1526
/*      */     //   1392: iload_2
/*      */     //   1393: ldc 193
/*      */     //   1395: if_icmpne +4 -> 1399
/*      */     //   1398: return
/*      */     //   1399: ldc_w 327
/*      */     //   1402: getstatic 326	an:j	I
/*      */     //   1405: imul
/*      */     //   1406: iload_3
/*      */     //   1407: iload 12
/*      */     //   1409: iadd
/*      */     //   1410: if_icmpge +116 -> 1526
/*      */     //   1413: iload_2
/*      */     //   1414: ldc 193
/*      */     //   1416: if_icmpne +11 -> 1427
/*      */     //   1419: new 157	java/lang/IllegalStateException
/*      */     //   1422: dup
/*      */     //   1423: invokespecial 158	java/lang/IllegalStateException:<init>	()V
/*      */     //   1426: athrow
/*      */     //   1427: getstatic 328	an:z	I
/*      */     //   1430: ldc_w 329
/*      */     //   1433: imul
/*      */     //   1434: iload 11
/*      */     //   1436: iload 4
/*      */     //   1438: iadd
/*      */     //   1439: if_icmpge +87 -> 1526
/*      */     //   1442: iload_2
/*      */     //   1443: ldc 193
/*      */     //   1445: if_icmpne +11 -> 1456
/*      */     //   1448: new 157	java/lang/IllegalStateException
/*      */     //   1451: dup
/*      */     //   1452: invokespecial 158	java/lang/IllegalStateException:<init>	()V
/*      */     //   1455: athrow
/*      */     //   1456: iload 16
/*      */     //   1458: ifeq +68 -> 1526
/*      */     //   1461: iload_2
/*      */     //   1462: ldc 193
/*      */     //   1464: if_icmpne +11 -> 1475
/*      */     //   1467: new 157	java/lang/IllegalStateException
/*      */     //   1470: dup
/*      */     //   1471: invokespecial 158	java/lang/IllegalStateException:<init>	()V
/*      */     //   1474: athrow
/*      */     //   1475: iload 14
/*      */     //   1477: ldc_w 330
/*      */     //   1480: imul
/*      */     //   1481: putstatic 297	g:bk	I
/*      */     //   1484: getstatic 192	da:ar	[Lfq;
/*      */     //   1487: aload 15
/*      */     //   1489: getfield 333	c:n	Z
/*      */     //   1492: ifeq +16 -> 1508
/*      */     //   1495: iload_2
/*      */     //   1496: ldc 193
/*      */     //   1498: if_icmpne +6 -> 1504
/*      */     //   1501: goto +0 -> 1501
/*      */     //   1504: iconst_1
/*      */     //   1505: goto +4 -> 1509
/*      */     //   1508: iconst_0
/*      */     //   1509: aaload
/*      */     //   1510: iload 12
/*      */     //   1512: iload 11
/*      */     //   1514: sipush 128
/*      */     //   1517: ldc_w 268
/*      */     //   1520: invokevirtual 340	fq:co	(IIII)V
/*      */     //   1523: goto +36 -> 1559
/*      */     //   1526: getstatic 192	da:ar	[Lfq;
/*      */     //   1529: aload 15
/*      */     //   1531: getfield 333	c:n	Z
/*      */     //   1534: ifeq +16 -> 1550
/*      */     //   1537: iload_2
/*      */     //   1538: ldc 193
/*      */     //   1540: if_icmpne +6 -> 1546
/*      */     //   1543: goto +0 -> 1543
/*      */     //   1546: iconst_1
/*      */     //   1547: goto +4 -> 1551
/*      */     //   1550: iconst_0
/*      */     //   1551: aaload
/*      */     //   1552: iload 12
/*      */     //   1554: iload 11
/*      */     //   1556: invokevirtual 343	fq:cr	(II)V
/*      */     //   1559: getstatic 214	fn:aq	[Lft;
/*      */     //   1562: ifnull +59 -> 1621
/*      */     //   1565: iload_2
/*      */     //   1566: ldc 193
/*      */     //   1568: if_icmpne +6 -> 1574
/*      */     //   1571: goto +0 -> 1571
/*      */     //   1574: getstatic 214	fn:aq	[Lft;
/*      */     //   1577: aload 15
/*      */     //   1579: getfield 345	c:m	I
/*      */     //   1582: ldc_w 346
/*      */     //   1585: imul
/*      */     //   1586: aload 15
/*      */     //   1588: getfield 333	c:n	Z
/*      */     //   1591: ifeq +17 -> 1608
/*      */     //   1594: iload_2
/*      */     //   1595: ldc 193
/*      */     //   1597: if_icmpne +6 -> 1603
/*      */     //   1600: goto +3 -> 1603
/*      */     //   1603: bipush 8
/*      */     //   1605: goto +4 -> 1609
/*      */     //   1608: iconst_0
/*      */     //   1609: iadd
/*      */     //   1610: aaload
/*      */     //   1611: bipush 29
/*      */     //   1613: iload 12
/*      */     //   1615: iadd
/*      */     //   1616: iload 11
/*      */     //   1618: invokevirtual 264	ft:be	(II)V
/*      */     //   1621: aload_0
/*      */     //   1622: aload 15
/*      */     //   1624: getfield 349	c:r	I
/*      */     //   1627: ldc_w 350
/*      */     //   1630: imul
/*      */     //   1631: invokestatic 315	java/lang/Integer:toString	(I)Ljava/lang/String;
/*      */     //   1634: iload 12
/*      */     //   1636: bipush 15
/*      */     //   1638: iadd
/*      */     //   1639: iconst_5
/*      */     //   1640: iload 4
/*      */     //   1642: iconst_2
/*      */     //   1643: idiv
/*      */     //   1644: iload 11
/*      */     //   1646: iadd
/*      */     //   1647: iadd
/*      */     //   1648: iconst_0
/*      */     //   1649: iconst_m1
/*      */     //   1650: invokevirtual 258	fm:cs	(Ljava/lang/String;IIII)V
/*      */     //   1653: aload_1
/*      */     //   1654: aload 17
/*      */     //   1656: iload 12
/*      */     //   1658: bipush 60
/*      */     //   1660: iadd
/*      */     //   1661: iconst_5
/*      */     //   1662: iload 4
/*      */     //   1664: iconst_2
/*      */     //   1665: idiv
/*      */     //   1666: iload 11
/*      */     //   1668: iadd
/*      */     //   1669: iadd
/*      */     //   1670: ldc_w 351
/*      */     //   1673: iconst_m1
/*      */     //   1674: invokevirtual 258	fm:cs	(Ljava/lang/String;IIII)V
/*      */     //   1677: iload 11
/*      */     //   1679: iload 4
/*      */     //   1681: iload 8
/*      */     //   1683: iadd
/*      */     //   1684: iadd
/*      */     //   1685: istore 11
/*      */     //   1687: iinc 13 1
/*      */     //   1690: iload 13
/*      */     //   1692: iload 6
/*      */     //   1694: if_icmplt +29 -> 1723
/*      */     //   1697: iload_2
/*      */     //   1698: ldc 193
/*      */     //   1700: if_icmpne +4 -> 1704
/*      */     //   1703: return
/*      */     //   1704: iload 10
/*      */     //   1706: bipush 23
/*      */     //   1708: iadd
/*      */     //   1709: istore 11
/*      */     //   1711: iload 12
/*      */     //   1713: iload 7
/*      */     //   1715: iload_3
/*      */     //   1716: iadd
/*      */     //   1717: iadd
/*      */     //   1718: istore 12
/*      */     //   1720: iconst_0
/*      */     //   1721: istore 13
/*      */     //   1723: iinc 14 1
/*      */     //   1726: goto -486 -> 1240
/*      */     //   1729: getstatic 355	c:h	Ljava/awt/Canvas;
/*      */     //   1732: invokevirtual 361	java/awt/Canvas:getGraphics	()Ljava/awt/Graphics;
/*      */     //   1735: astore_3
/*      */     //   1736: getstatic 366	dj:o	Lab;
/*      */     //   1739: aload_3
/*      */     //   1740: iconst_0
/*      */     //   1741: iconst_0
/*      */     //   1742: ldc_w 367
/*      */     //   1745: invokevirtual 372	ab:l	(Ljava/awt/Graphics;III)V
/*      */     //   1748: goto +10 -> 1758
/*      */     //   1751: astore_3
/*      */     //   1752: getstatic 355	c:h	Ljava/awt/Canvas;
/*      */     //   1755: invokevirtual 375	java/awt/Canvas:repaint	()V
/*      */     //   1758: return
/*      */     //
/*      */     // Exception table:
/*      */     //   from	to	target	type
/*      */     //   1729	1748	1751	java/lang/Exception
/*      */   }
/*      */ }

/* Location:           C:\Users\Mike\IdeaProjects\RealityBot-2007 Updater\client-deob.jar
 * Qualified Name:     de
 * JD-Core Version:    0.6.2
 */