/*      */ public class ex extends dx
/*      */ {
/*   12 */   ee q = new ee();
/*      */ 
/*   11 */   cg g = new cg();
/*      */   ed z;
/*      */ 
/*      */   int z()
/*      */   {
/*   34 */     return 0;
/*      */   }
/*      */ 
/*      */   dx n()
/*      */   {
/*   19 */     ej localej = (ej)this.g.j();
/*   20 */     if (null == localej) return null;
/*   21 */     if (null != localej.o) return localej.o;
/*   22 */     return j();
/*      */   }
/*      */ 
/*      */   dx j() {
/*      */     while (true) {
/*   27 */       ej localej = (ej)this.g.g();
/*   28 */       if (localej == null) return null;
/*   29 */       if (null != localej.o) return localej.o;
/*      */     }
/*      */   }
/*      */ 
/*      */   void i(int paramInt)
/*      */   {
/*   58 */     this.q.i(paramInt);
/*   59 */     label115: for (ej localej = (ej)this.g.j(); localej != null; localej = (ej)this.g.g())
/*   60 */       if (!this.z.bs(localej, (byte)16)) {
/*   61 */         int i = paramInt;
/*   62 */         while (i > localej.a * -1116143793) {
/*   63 */           ad(localej, localej.a * -1116143793, 1995850478);
/*   64 */           i -= localej.a * -1116143793;
/*   65 */           if (this.z.bk(localej, null, 0, i, (byte)0)) break label115;
/*      */         }
/*   67 */         ad(localej, i, 2077158029);
/*   68 */         localej.a -= 364427183 * i;
/*      */       }
/*      */   }
/*      */ 
/*      */   void a(int paramInt)
/*      */   {
/*   58 */     this.q.i(paramInt);
/*   59 */     label115: for (ej localej = (ej)this.g.j(); localej != null; localej = (ej)this.g.g())
/*   60 */       if (!this.z.bs(localej, (byte)16)) {
/*   61 */         int i = paramInt;
/*   62 */         while (i > localej.a * -1116143793) {
/*   63 */           ad(localej, localej.a * -1116143793, 2146488803);
/*   64 */           i -= localej.a * -1116143793;
/*   65 */           if (this.z.bk(localej, null, 0, i, (byte)0)) break label115;
/*      */         }
/*   67 */         ad(localej, i, 1978762710);
/*   68 */         localej.a -= 364427183 * i;
/*      */       }
/*      */   }
/*      */ 
/*      */   dx w()
/*      */   {
/*   19 */     ej localej = (ej)this.g.j();
/*   20 */     if (null == localej) return null;
/*   21 */     if (null != localej.o) return localej.o;
/*   22 */     return j();
/*      */   }
/*      */ 
/*      */   void p(ej paramej, int[] paramArrayOfInt, int paramInt1, int paramInt2, int paramInt3, int paramInt4)
/*      */   {
/*   73 */     if (0 != (this.z.a[(1720864287 * paramej.m)] & 0x4)) { if (paramInt4 <= -957401312) throw new IllegalStateException(); if (-225172079 * paramej.y < 0) { if (paramInt4 > -957401312);
/*   74 */         int i = this.z.ac[(1720864287 * paramej.m)] / (y.r * -1570391439);
/*      */ 
/*   76 */         int j = (1048575 + i - paramej.x * 2108408535) / i;
/*   77 */         if (j > paramInt2) { if (paramInt4 <= -957401312); } else {
/*   78 */           paramej.o.q(paramArrayOfInt, paramInt1, j);
/*   79 */           paramInt1 += j;
/*   80 */           paramInt2 -= j;
/*   81 */           paramej.x += (j * i - 1048576) * -136294169;
/*   82 */           int k = y.r * -1570391439 / 100;
/*   83 */           int m = 262144 / i;
/*   84 */           if (m < k) { if (paramInt4 > -957401312);
/*   84 */             k = m; }
/*   85 */           et localet = paramej.o;
/*   86 */           if (this.z.p[(1720864287 * paramej.m)] == 0) { if (paramInt4 <= -957401312) throw new IllegalStateException();
/*   87 */             paramej.o = et.aa(paramej.n, localet.aq(), localet.az(), localet.an());
/*      */           } else
/*      */           {
/*   90 */             paramej.o = et.aa(paramej.n, localet.aq(), 0, localet.an());
/*   91 */             if (paramej.c.n[(paramej.g * -91733895)] < 0) tmpTernaryOp = 1;
/*      */           }
/*      */         }
/*      */       }
/*      */     }
/*      */   }
/*      */ 
/*      */   void ad(ej paramej, int paramInt1, int paramInt2)
/*      */   {
/*  105 */     if ((this.z.a[(1720864287 * paramej.m)] & 0x4) != 0) { if (paramInt2 <= 1924398875) return; if (-225172079 * paramej.y < 0) { if (paramInt2 <= 1924398875) throw new IllegalStateException();
/*  106 */         int i = this.z.ac[(paramej.m * 1720864287)] / (y.r * -1570391439);
/*  107 */         int j = (i + 1048575 - 2108408535 * paramej.x) / i;
/*  108 */         paramej.x = (-136294169 * (paramej.x * 2108408535 + i * paramInt1 & 0xFFFFF));
/*  109 */         if (j <= paramInt1) { if (paramInt2 <= 1924398875) return;
/*  110 */           if (this.z.p[(paramej.m * 1720864287)] == 0) { if (paramInt2 <= 1924398875) throw new IllegalStateException();
/*  111 */             paramej.o = et.aa(paramej.n, paramej.o.aq(), paramej.o.az(), paramej.o.an());
/*      */           } else
/*      */           {
/*  114 */             paramej.o = et.aa(paramej.n, paramej.o.aq(), 0, paramej.o.an());
/*  115 */             if (paramInt2 <= 1924398875) return; this.z.ay(paramej, paramej.c.n[(-91733895 * paramej.g)] < 0, 675379791);
/*      */           }
/*  117 */           if (paramej.c.n[(-91733895 * paramej.g)] < 0) { if (paramInt2 <= 1924398875) throw new IllegalStateException(); paramej.o.am(-1); }
/*  118 */           paramInt1 = 2108408535 * paramej.x / i; }
/*      */       }
/*      */     }
/*  121 */     paramej.o.i(paramInt1);
/*      */   }
/*      */ 
/*      */   dx v()
/*      */   {
/*   19 */     ej localej = (ej)this.g.j();
/*   20 */     if (null == localej) return null;
/*   21 */     if (null != localej.o) return localej.o;
/*   22 */     return j();
/*      */   }
/*      */ 
/*      */   void f(int[] paramArrayOfInt, int paramInt1, int paramInt2)
/*      */   {
/*   40 */     this.q.q(paramArrayOfInt, paramInt1, paramInt2);
/*   41 */     label168: for (ej localej = (ej)this.g.j(); null != localej; localej = (ej)this.g.g())
/*   42 */       if (!this.z.bs(localej, (byte)16)) {
/*   43 */         int i = paramInt1;
/*   44 */         int j = paramInt2;
/*   45 */         while (j > localej.a * -1116143793) {
/*   46 */           p(localej, paramArrayOfInt, i, -1116143793 * localej.a, j + i, 1523679234);
/*   47 */           i += localej.a * -1116143793;
/*   48 */           j -= localej.a * -1116143793;
/*   49 */           if (this.z.bk(localej, paramArrayOfInt, i, j, (byte)0)) break label168;
/*      */         }
/*   51 */         p(localej, paramArrayOfInt, i, j, j + i, 1306328517);
/*   52 */         localej.a -= 364427183 * j;
/*      */       }
/*      */   }
/*      */ 
/*      */   dx e()
/*      */   {
/*   19 */     ej localej = (ej)this.g.j();
/*   20 */     if (null == localej) return null;
/*   21 */     if (null != localej.o) return localej.o;
/*   22 */     return j();
/*      */   }
/*      */ 
/*      */   dx b() {
/*      */     while (true) {
/*   27 */       ej localej = (ej)this.g.g();
/*   28 */       if (localej == null) return null;
/*   29 */       if (null != localej.o) return localej.o;
/*      */     }
/*      */   }
/*      */ 
/*      */   dx y()
/*      */   {
/*      */     while (true)
/*      */     {
/*   27 */       ej localej = (ej)this.g.g();
/*   28 */       if (localej == null) return null;
/*   29 */       if (null != localej.o) return localej.o; 
/*      */     }
/*      */   }
/*      */ 
/*      */   int t()
/*      */   {
/*   34 */     return 0;
/*      */   }
/*      */ 
/*      */   void o(int[] paramArrayOfInt, int paramInt1, int paramInt2)
/*      */   {
/*   40 */     this.q.q(paramArrayOfInt, paramInt1, paramInt2);
/*   41 */     label168: for (ej localej = (ej)this.g.j(); null != localej; localej = (ej)this.g.g())
/*   42 */       if (!this.z.bs(localej, (byte)16)) {
/*   43 */         int i = paramInt1;
/*   44 */         int j = paramInt2;
/*   45 */         while (j > localej.a * -1116143793) {
/*   46 */           p(localej, paramArrayOfInt, i, -1116143793 * localej.a, j + i, -397368760);
/*   47 */           i += localej.a * -1116143793;
/*   48 */           j -= localej.a * -1116143793;
/*   49 */           if (this.z.bk(localej, paramArrayOfInt, i, j, (byte)0)) break label168;
/*      */         }
/*   51 */         p(localej, paramArrayOfInt, i, j, j + i, 588605003);
/*   52 */         localej.a -= 364427183 * j;
/*      */       }
/*      */   }
/*      */ 
/*      */   void k(int[] paramArrayOfInt, int paramInt1, int paramInt2)
/*      */   {
/*   40 */     this.q.q(paramArrayOfInt, paramInt1, paramInt2);
/*   41 */     label168: for (ej localej = (ej)this.g.j(); null != localej; localej = (ej)this.g.g())
/*   42 */       if (!this.z.bs(localej, (byte)16)) {
/*   43 */         int i = paramInt1;
/*   44 */         int j = paramInt2;
/*   45 */         while (j > localej.a * -1116143793) {
/*   46 */           p(localej, paramArrayOfInt, i, -1116143793 * localej.a, j + i, 152883151);
/*   47 */           i += localej.a * -1116143793;
/*   48 */           j -= localej.a * -1116143793;
/*   49 */           if (this.z.bk(localej, paramArrayOfInt, i, j, (byte)0)) break label168;
/*      */         }
/*   51 */         p(localej, paramArrayOfInt, i, j, j + i, 1277951157);
/*   52 */         localej.a -= 364427183 * j;
/*      */       }
/*      */   }
/*      */ 
/*      */   void h(int paramInt)
/*      */   {
/*   58 */     this.q.i(paramInt);
/*   59 */     label115: for (ej localej = (ej)this.g.j(); localej != null; localej = (ej)this.g.g())
/*   60 */       if (!this.z.bs(localej, (byte)16)) {
/*   61 */         int i = paramInt;
/*   62 */         while (i > localej.a * -1116143793) {
/*   63 */           ad(localej, localej.a * -1116143793, 2092834202);
/*   64 */           i -= localej.a * -1116143793;
/*   65 */           if (this.z.bk(localej, null, 0, i, (byte)0)) break label115;
/*      */         }
/*   67 */         ad(localej, i, 1927645954);
/*   68 */         localej.a -= 364427183 * i;
/*      */       }
/*      */   }
/*      */ 
/*      */   void q(int[] paramArrayOfInt, int paramInt1, int paramInt2)
/*      */   {
/*   40 */     this.q.q(paramArrayOfInt, paramInt1, paramInt2);
/*   41 */     label168: for (ej localej = (ej)this.g.j(); null != localej; localej = (ej)this.g.g())
/*   42 */       if (!this.z.bs(localej, (byte)16)) {
/*   43 */         int i = paramInt1;
/*   44 */         int j = paramInt2;
/*   45 */         while (j > localej.a * -1116143793) {
/*   46 */           p(localej, paramArrayOfInt, i, -1116143793 * localej.a, j + i, 1589966438);
/*   47 */           i += localej.a * -1116143793;
/*   48 */           j -= localej.a * -1116143793;
/*   49 */           if (this.z.bk(localej, paramArrayOfInt, i, j, (byte)0)) break label168;
/*      */         }
/*   51 */         p(localej, paramArrayOfInt, i, j, j + i, -172249771);
/*   52 */         localej.a -= 364427183 * j;
/*      */       }
/*      */   }
/*      */ 
/*      */   ex(ed paramed)
/*      */   {
/*   15 */     this.z = paramed;
/*      */   }
/*      */ 
/*      */   void ac(ej paramej, int[] paramArrayOfInt, int paramInt1, int paramInt2, int paramInt3)
/*      */   {
/*   73 */     if ((0 != (this.z.a[(1720864287 * paramej.m)] & 0x4)) && (-225172079 * paramej.y < 0)) {
/*   74 */       int i = this.z.ac[(1720864287 * paramej.m)] / (y.r * -1570391439);
/*      */       while (true) {
/*   76 */         int j = (1048575 + i - paramej.x * 2108408535) / i;
/*   77 */         if (j > paramInt2) break;
/*   78 */         paramej.o.q(paramArrayOfInt, paramInt1, j);
/*   79 */         paramInt1 += j;
/*   80 */         paramInt2 -= j;
/*   81 */         paramej.x += (j * i - 1048576) * -136294169;
/*   82 */         int k = y.r * -1570391439 / 100;
/*   83 */         int m = 262144 / i;
/*   84 */         if (m < k) k = m;
/*   85 */         et localet = paramej.o;
/*   86 */         if (this.z.p[(1720864287 * paramej.m)] == 0) {
/*   87 */           paramej.o = et.aa(paramej.n, localet.aq(), localet.az(), localet.an());
/*      */         }
/*      */         else {
/*   90 */           paramej.o = et.aa(paramej.n, localet.aq(), 0, localet.an());
/*   91 */           this.z.ay(paramej, paramej.c.n[(paramej.g * -91733895)] < 0, 431247695);
/*   92 */           paramej.o.ab(k, localet.az());
/*      */         }
/*   94 */         if (paramej.c.n[(-91733895 * paramej.g)] < 0) paramej.o.am(-1);
/*   95 */         localet.ag(k);
/*   96 */         localet.q(paramArrayOfInt, paramInt1, paramInt3 - paramInt1);
/*   97 */         if (localet.ae()) this.q.p(localet);
/*      */       }
/*   99 */       paramej.x += i * paramInt2 * -136294169;
/*      */     }
/*  101 */     paramej.o.q(paramArrayOfInt, paramInt1, paramInt2);
/*      */   }
/*      */ 
/*      */   void aa(ej paramej, int paramInt) {
/*  105 */     if (((this.z.a[(1720864287 * paramej.m)] & 0x4) != 0) && (-225172079 * paramej.y < 0)) {
/*  106 */       int i = this.z.ac[(paramej.m * 1720864287)] / (y.r * -1570391439);
/*  107 */       int j = (i + 1048575 - 2108408535 * paramej.x) / i;
/*  108 */       paramej.x = (-136294169 * (paramej.x * 2108408535 + i * paramInt & 0xFFFFF));
/*  109 */       if (j <= paramInt) {
/*  110 */         if (this.z.p[(paramej.m * 1720864287)] == 0) {
/*  111 */           paramej.o = et.aa(paramej.n, paramej.o.aq(), paramej.o.az(), paramej.o.an());
/*      */         }
/*      */         else {
/*  114 */           paramej.o = et.aa(paramej.n, paramej.o.aq(), 0, paramej.o.an());
/*  115 */           this.z.ay(paramej, paramej.c.n[(-91733895 * paramej.g)] < 0, 1837994727);
/*      */         }
/*  117 */         if (paramej.c.n[(-91733895 * paramej.g)] < 0) paramej.o.am(-1);
/*  118 */         paramInt = 2108408535 * paramej.x / i;
/*      */       }
/*      */     }
/*  121 */     paramej.o.i(paramInt);
/*      */   }
/*      */ 
/*      */   void as(ej paramej, int paramInt)
/*      */   {
/*  105 */     if (((this.z.a[(1720864287 * paramej.m)] & 0x4) != 0) && (-225172079 * paramej.y < 0)) {
/*  106 */       int i = this.z.ac[(paramej.m * 1720864287)] / (y.r * -1570391439);
/*  107 */       int j = (i + 1048575 - 2108408535 * paramej.x) / i;
/*  108 */       paramej.x = (-136294169 * (paramej.x * 2108408535 + i * paramInt & 0xFFFFF));
/*  109 */       if (j <= paramInt) {
/*  110 */         if (this.z.p[(paramej.m * 1720864287)] == 0) {
/*  111 */           paramej.o = et.aa(paramej.n, paramej.o.aq(), paramej.o.az(), paramej.o.an());
/*      */         }
/*      */         else {
/*  114 */           paramej.o = et.aa(paramej.n, paramej.o.aq(), 0, paramej.o.an());
/*  115 */           this.z.ay(paramej, paramej.c.n[(-91733895 * paramej.g)] < 0, -187466365);
/*      */         }
/*  117 */         if (paramej.c.n[(-91733895 * paramej.g)] < 0) paramej.o.am(-1);
/*  118 */         paramInt = 2108408535 * paramej.x / i;
/*      */       }
/*      */     }
/*  121 */     paramej.o.i(paramInt);
/*      */   }
/*      */ 
/*      */   // ERROR //
/*      */   static final void dg(int paramInt)
/*      */   {
/*      */     // Byte code:
/*      */     //   0: iconst_0
/*      */     //   1: getstatic 202	client:cw	I
/*      */     //   4: ldc 203
/*      */     //   6: imul
/*      */     //   7: if_icmpne +56 -> 63
/*      */     //   10: iload_0
/*      */     //   11: ldc 204
/*      */     //   13: if_icmplt +6 -> 19
/*      */     //   16: goto +0 -> 16
/*      */     //   19: getstatic 210	at:dd	Lam;
/*      */     //   22: ifnull +24 -> 46
/*      */     //   25: iload_0
/*      */     //   26: ldc 204
/*      */     //   28: if_icmplt +6 -> 34
/*      */     //   31: goto +0 -> 31
/*      */     //   34: getstatic 210	at:dd	Lam;
/*      */     //   37: ldc 211
/*      */     //   39: invokevirtual 214	am:m	(I)V
/*      */     //   42: aconst_null
/*      */     //   43: putstatic 210	at:dd	Lam;
/*      */     //   46: aconst_null
/*      */     //   47: putstatic 219	by:cg	Lah;
/*      */     //   50: iconst_0
/*      */     //   51: putstatic 223	client:di	Z
/*      */     //   54: iconst_0
/*      */     //   55: putstatic 226	client:cz	I
/*      */     //   58: ldc 227
/*      */     //   60: putstatic 202	client:cw	I
/*      */     //   63: iconst_1
/*      */     //   64: ldc 203
/*      */     //   66: getstatic 202	client:cw	I
/*      */     //   69: imul
/*      */     //   70: if_icmpne +131 -> 201
/*      */     //   73: iload_0
/*      */     //   74: ldc 204
/*      */     //   76: if_icmplt +11 -> 87
/*      */     //   79: new 79	java/lang/IllegalStateException
/*      */     //   82: dup
/*      */     //   83: invokespecial 83	java/lang/IllegalStateException:<init>	()V
/*      */     //   86: athrow
/*      */     //   87: aconst_null
/*      */     //   88: getstatic 219	by:cg	Lah;
/*      */     //   91: if_acmpne +32 -> 123
/*      */     //   94: iload_0
/*      */     //   95: ldc 204
/*      */     //   97: if_icmplt +6 -> 103
/*      */     //   100: goto +0 -> 100
/*      */     //   103: getstatic 230	client:r	Lak;
/*      */     //   106: getstatic 235	c:ck	Ljava/lang/String;
/*      */     //   109: getstatic 240	cu:cd	I
/*      */     //   112: ldc 241
/*      */     //   114: imul
/*      */     //   115: bipush 124
/*      */     //   117: invokevirtual 246	ak:n	(Ljava/lang/String;IB)Lah;
/*      */     //   120: putstatic 219	by:cg	Lah;
/*      */     //   123: iconst_2
/*      */     //   124: getstatic 219	by:cg	Lah;
/*      */     //   127: getfield 250	ah:c	I
/*      */     //   130: if_icmpne +20 -> 150
/*      */     //   133: iload_0
/*      */     //   134: ldc 204
/*      */     //   136: if_icmplt +6 -> 142
/*      */     //   139: goto +3 -> 142
/*      */     //   142: new 197	java/io/IOException
/*      */     //   145: dup
/*      */     //   146: invokespecial 251	java/io/IOException:<init>	()V
/*      */     //   149: athrow
/*      */     //   150: iconst_1
/*      */     //   151: getstatic 219	by:cg	Lah;
/*      */     //   154: getfield 250	ah:c	I
/*      */     //   157: if_icmpne +44 -> 201
/*      */     //   160: iload_0
/*      */     //   161: ldc 204
/*      */     //   163: if_icmplt +6 -> 169
/*      */     //   166: goto +3 -> 169
/*      */     //   169: new 212	am
/*      */     //   172: dup
/*      */     //   173: getstatic 219	by:cg	Lah;
/*      */     //   176: getfield 254	ah:g	Ljava/lang/Object;
/*      */     //   179: checkcast 256	java/net/Socket
/*      */     //   182: getstatic 230	client:r	Lak;
/*      */     //   185: invokespecial 259	am:<init>	(Ljava/net/Socket;Lak;)V
/*      */     //   188: putstatic 210	at:dd	Lam;
/*      */     //   191: aconst_null
/*      */     //   192: putstatic 219	by:cg	Lah;
/*      */     //   195: ldc_w 260
/*      */     //   198: putstatic 202	client:cw	I
/*      */     //   201: getstatic 202	client:cw	I
/*      */     //   204: ldc 203
/*      */     //   206: imul
/*      */     //   207: iconst_2
/*      */     //   208: if_icmpne +60 -> 268
/*      */     //   211: iload_0
/*      */     //   212: ldc 204
/*      */     //   214: if_icmplt +6 -> 220
/*      */     //   217: goto +0 -> 217
/*      */     //   220: getstatic 264	client:df	Lea;
/*      */     //   223: iconst_0
/*      */     //   224: putfield 267	ea:c	I
/*      */     //   227: getstatic 264	client:df	Lea;
/*      */     //   230: bipush 14
/*      */     //   232: ldc_w 268
/*      */     //   235: invokevirtual 270	ea:c	(II)V
/*      */     //   238: getstatic 210	at:dd	Lam;
/*      */     //   241: getstatic 264	client:df	Lea;
/*      */     //   244: getfield 273	ea:m	[B
/*      */     //   247: iconst_0
/*      */     //   248: iconst_1
/*      */     //   249: ldc_w 274
/*      */     //   252: invokevirtual 277	am:z	([BIII)V
/*      */     //   255: getstatic 280	client:dz	Lea;
/*      */     //   258: iconst_0
/*      */     //   259: putfield 267	ea:c	I
/*      */     //   262: ldc_w 281
/*      */     //   265: putstatic 202	client:cw	I
/*      */     //   268: ldc 203
/*      */     //   270: getstatic 202	client:cw	I
/*      */     //   273: imul
/*      */     //   274: iconst_3
/*      */     //   275: if_icmpne +156 -> 431
/*      */     //   278: iload_0
/*      */     //   279: ldc 204
/*      */     //   281: if_icmplt +11 -> 292
/*      */     //   284: new 79	java/lang/IllegalStateException
/*      */     //   287: dup
/*      */     //   288: invokespecial 83	java/lang/IllegalStateException:<init>	()V
/*      */     //   291: athrow
/*      */     //   292: getstatic 287	l:on	Ly;
/*      */     //   295: ifnull +20 -> 315
/*      */     //   298: iload_0
/*      */     //   299: ldc 204
/*      */     //   301: if_icmplt +6 -> 307
/*      */     //   304: goto +3 -> 307
/*      */     //   307: getstatic 287	l:on	Ly;
/*      */     //   310: bipush 54
/*      */     //   312: invokevirtual 290	y:c	(B)V
/*      */     //   315: aconst_null
/*      */     //   316: getstatic 295	dr:oi	Ly;
/*      */     //   319: if_acmpeq +20 -> 339
/*      */     //   322: iload_0
/*      */     //   323: ldc 204
/*      */     //   325: if_icmplt +6 -> 331
/*      */     //   328: goto +0 -> 328
/*      */     //   331: getstatic 295	dr:oi	Ly;
/*      */     //   334: bipush 123
/*      */     //   336: invokevirtual 290	y:c	(B)V
/*      */     //   339: getstatic 210	at:dd	Lam;
/*      */     //   342: ldc_w 296
/*      */     //   345: invokevirtual 299	am:c	(I)I
/*      */     //   348: istore_1
/*      */     //   349: aconst_null
/*      */     //   350: getstatic 287	l:on	Ly;
/*      */     //   353: if_acmpeq +20 -> 373
/*      */     //   356: iload_0
/*      */     //   357: ldc 204
/*      */     //   359: if_icmplt +6 -> 365
/*      */     //   362: goto +0 -> 362
/*      */     //   365: getstatic 287	l:on	Ly;
/*      */     //   368: bipush 37
/*      */     //   370: invokevirtual 290	y:c	(B)V
/*      */     //   373: aconst_null
/*      */     //   374: getstatic 295	dr:oi	Ly;
/*      */     //   377: if_acmpeq +20 -> 397
/*      */     //   380: iload_0
/*      */     //   381: ldc 204
/*      */     //   383: if_icmplt +6 -> 389
/*      */     //   386: goto +0 -> 386
/*      */     //   389: getstatic 295	dr:oi	Ly;
/*      */     //   392: bipush 124
/*      */     //   394: invokevirtual 290	y:c	(B)V
/*      */     //   397: iload_1
/*      */     //   398: ifeq +20 -> 418
/*      */     //   401: iload_0
/*      */     //   402: ldc 204
/*      */     //   404: if_icmplt +6 -> 410
/*      */     //   407: goto +3 -> 410
/*      */     //   410: iload_1
/*      */     //   411: ldc_w 300
/*      */     //   414: invokestatic 305	bf:dk	(II)V
/*      */     //   417: return
/*      */     //   418: getstatic 280	client:dz	Lea;
/*      */     //   421: iconst_0
/*      */     //   422: putfield 267	ea:c	I
/*      */     //   425: ldc_w 306
/*      */     //   428: putstatic 202	client:cw	I
/*      */     //   431: ldc 203
/*      */     //   433: getstatic 202	client:cw	I
/*      */     //   436: imul
/*      */     //   437: iconst_5
/*      */     //   438: if_icmpne +742 -> 1180
/*      */     //   441: iload_0
/*      */     //   442: ldc 204
/*      */     //   444: if_icmplt +11 -> 455
/*      */     //   447: new 79	java/lang/IllegalStateException
/*      */     //   450: dup
/*      */     //   451: invokespecial 83	java/lang/IllegalStateException:<init>	()V
/*      */     //   454: athrow
/*      */     //   455: iconst_4
/*      */     //   456: newarray int
/*      */     //   458: astore_1
/*      */     //   459: aload_1
/*      */     //   460: iconst_0
/*      */     //   461: invokestatic 312	java/lang/Math:random	()D
/*      */     //   464: ldc2_w 313
/*      */     //   467: dmul
/*      */     //   468: d2i
/*      */     //   469: iastore
/*      */     //   470: aload_1
/*      */     //   471: iconst_1
/*      */     //   472: invokestatic 312	java/lang/Math:random	()D
/*      */     //   475: ldc2_w 313
/*      */     //   478: dmul
/*      */     //   479: d2i
/*      */     //   480: iastore
/*      */     //   481: aload_1
/*      */     //   482: iconst_2
/*      */     //   483: invokestatic 312	java/lang/Math:random	()D
/*      */     //   486: ldc2_w 313
/*      */     //   489: dmul
/*      */     //   490: d2i
/*      */     //   491: iastore
/*      */     //   492: aload_1
/*      */     //   493: iconst_3
/*      */     //   494: invokestatic 312	java/lang/Math:random	()D
/*      */     //   497: ldc2_w 313
/*      */     //   500: dmul
/*      */     //   501: d2i
/*      */     //   502: iastore
/*      */     //   503: getstatic 264	client:df	Lea;
/*      */     //   506: iconst_0
/*      */     //   507: putfield 267	ea:c	I
/*      */     //   510: getstatic 264	client:df	Lea;
/*      */     //   513: bipush 10
/*      */     //   515: ldc_w 315
/*      */     //   518: invokevirtual 270	ea:c	(II)V
/*      */     //   521: getstatic 264	client:df	Lea;
/*      */     //   524: aload_1
/*      */     //   525: iconst_0
/*      */     //   526: iaload
/*      */     //   527: bipush 83
/*      */     //   529: invokevirtual 318	ea:z	(IB)V
/*      */     //   532: getstatic 264	client:df	Lea;
/*      */     //   535: aload_1
/*      */     //   536: iconst_1
/*      */     //   537: iaload
/*      */     //   538: bipush 7
/*      */     //   540: invokevirtual 318	ea:z	(IB)V
/*      */     //   543: getstatic 264	client:df	Lea;
/*      */     //   546: aload_1
/*      */     //   547: iconst_2
/*      */     //   548: iaload
/*      */     //   549: bipush 96
/*      */     //   551: invokevirtual 318	ea:z	(IB)V
/*      */     //   554: getstatic 264	client:df	Lea;
/*      */     //   557: aload_1
/*      */     //   558: iconst_3
/*      */     //   559: iaload
/*      */     //   560: bipush 14
/*      */     //   562: invokevirtual 318	ea:z	(IB)V
/*      */     //   565: getstatic 264	client:df	Lea;
/*      */     //   568: lconst_0
/*      */     //   569: invokevirtual 321	ea:g	(J)V
/*      */     //   572: getstatic 264	client:df	Lea;
/*      */     //   575: getstatic 324	g:ah	Ljava/lang/String;
/*      */     //   578: ldc_w 325
/*      */     //   581: invokevirtual 328	ea:i	(Ljava/lang/String;I)V
/*      */     //   584: getstatic 264	client:df	Lea;
/*      */     //   587: getstatic 333	d:r	Ljava/math/BigInteger;
/*      */     //   590: getstatic 335	d:d	Ljava/math/BigInteger;
/*      */     //   593: ldc_w 336
/*      */     //   596: invokevirtual 339	ea:ah	(Ljava/math/BigInteger;Ljava/math/BigInteger;I)V
/*      */     //   599: getstatic 341	client:dk	Lea;
/*      */     //   602: iconst_0
/*      */     //   603: putfield 267	ea:c	I
/*      */     //   606: bipush 40
/*      */     //   608: getstatic 343	client:at	I
/*      */     //   611: ldc_w 344
/*      */     //   614: imul
/*      */     //   615: if_icmpne +26 -> 641
/*      */     //   618: iload_0
/*      */     //   619: ldc 204
/*      */     //   621: if_icmplt +6 -> 627
/*      */     //   624: goto +0 -> 624
/*      */     //   627: getstatic 341	client:dk	Lea;
/*      */     //   630: bipush 18
/*      */     //   632: ldc_w 345
/*      */     //   635: invokevirtual 270	ea:c	(II)V
/*      */     //   638: goto +14 -> 652
/*      */     //   641: getstatic 341	client:dk	Lea;
/*      */     //   644: bipush 16
/*      */     //   646: ldc_w 346
/*      */     //   649: invokevirtual 270	ea:c	(II)V
/*      */     //   652: getstatic 341	client:dk	Lea;
/*      */     //   655: iconst_0
/*      */     //   656: ldc_w 347
/*      */     //   659: invokevirtual 349	ea:n	(II)V
/*      */     //   662: ldc_w 350
/*      */     //   665: getstatic 341	client:dk	Lea;
/*      */     //   668: getfield 267	ea:c	I
/*      */     //   671: imul
/*      */     //   672: istore_2
/*      */     //   673: getstatic 341	client:dk	Lea;
/*      */     //   676: iconst_1
/*      */     //   677: iconst_5
/*      */     //   678: invokevirtual 318	ea:z	(IB)V
/*      */     //   681: getstatic 341	client:dk	Lea;
/*      */     //   684: getstatic 264	client:df	Lea;
/*      */     //   687: getfield 273	ea:m	[B
/*      */     //   690: iconst_0
/*      */     //   691: ldc_w 350
/*      */     //   694: getstatic 264	client:df	Lea;
/*      */     //   697: getfield 267	ea:c	I
/*      */     //   700: imul
/*      */     //   701: bipush 27
/*      */     //   703: invokevirtual 354	ea:u	([BIIB)V
/*      */     //   706: ldc_w 350
/*      */     //   709: getstatic 341	client:dk	Lea;
/*      */     //   712: getfield 267	ea:c	I
/*      */     //   715: imul
/*      */     //   716: istore_3
/*      */     //   717: getstatic 341	client:dk	Lea;
/*      */     //   720: getstatic 356	g:an	Ljava/lang/String;
/*      */     //   723: ldc_w 357
/*      */     //   726: invokevirtual 328	ea:i	(Ljava/lang/String;I)V
/*      */     //   729: getstatic 341	client:dk	Lea;
/*      */     //   732: getstatic 360	client:ao	Z
/*      */     //   735: ifeq +16 -> 751
/*      */     //   738: iload_0
/*      */     //   739: ldc 204
/*      */     //   741: if_icmplt +6 -> 747
/*      */     //   744: goto +0 -> 744
/*      */     //   747: iconst_1
/*      */     //   748: goto +4 -> 752
/*      */     //   751: iconst_0
/*      */     //   752: ldc_w 361
/*      */     //   755: invokevirtual 270	ea:c	(II)V
/*      */     //   758: getstatic 341	client:dk	Lea;
/*      */     //   761: ldc_w 362
/*      */     //   764: invokestatic 365	l:l	(Lev;I)V
/*      */     //   767: getstatic 341	client:dk	Lea;
/*      */     //   770: ldc_w 366
/*      */     //   773: getstatic 372	bb:bp	Ldq;
/*      */     //   776: getfield 376	dq:v	I
/*      */     //   779: imul
/*      */     //   780: bipush 92
/*      */     //   782: invokevirtual 318	ea:z	(IB)V
/*      */     //   785: getstatic 341	client:dk	Lea;
/*      */     //   788: ldc_w 366
/*      */     //   791: getstatic 381	es:ba	Ldq;
/*      */     //   794: getfield 376	dq:v	I
/*      */     //   797: imul
/*      */     //   798: bipush 114
/*      */     //   800: invokevirtual 318	ea:z	(IB)V
/*      */     //   803: getstatic 341	client:dk	Lea;
/*      */     //   806: getstatic 386	cc:bc	Ldq;
/*      */     //   809: getfield 376	dq:v	I
/*      */     //   812: ldc_w 366
/*      */     //   815: imul
/*      */     //   816: bipush 76
/*      */     //   818: invokevirtual 318	ea:z	(IB)V
/*      */     //   821: getstatic 341	client:dk	Lea;
/*      */     //   824: ldc_w 366
/*      */     //   827: getstatic 391	bd:br	Ldq;
/*      */     //   830: getfield 376	dq:v	I
/*      */     //   833: imul
/*      */     //   834: bipush 122
/*      */     //   836: invokevirtual 318	ea:z	(IB)V
/*      */     //   839: getstatic 341	client:dk	Lea;
/*      */     //   842: ldc_w 366
/*      */     //   845: getstatic 394	df:bb	Ldq;
/*      */     //   848: getfield 376	dq:v	I
/*      */     //   851: imul
/*      */     //   852: bipush 7
/*      */     //   854: invokevirtual 318	ea:z	(IB)V
/*      */     //   857: getstatic 341	client:dk	Lea;
/*      */     //   860: getstatic 397	ck:bd	Ldq;
/*      */     //   863: getfield 376	dq:v	I
/*      */     //   866: ldc_w 366
/*      */     //   869: imul
/*      */     //   870: bipush 112
/*      */     //   872: invokevirtual 318	ea:z	(IB)V
/*      */     //   875: getstatic 341	client:dk	Lea;
/*      */     //   878: ldc_w 366
/*      */     //   881: getstatic 400	bb:cr	Ldq;
/*      */     //   884: getfield 376	dq:v	I
/*      */     //   887: imul
/*      */     //   888: bipush 73
/*      */     //   890: invokevirtual 318	ea:z	(IB)V
/*      */     //   893: getstatic 341	client:dk	Lea;
/*      */     //   896: getstatic 404	aa:cs	Ldq;
/*      */     //   899: getfield 376	dq:v	I
/*      */     //   902: ldc_w 366
/*      */     //   905: imul
/*      */     //   906: bipush 53
/*      */     //   908: invokevirtual 318	ea:z	(IB)V
/*      */     //   911: getstatic 341	client:dk	Lea;
/*      */     //   914: getstatic 407	client:cj	Ldq;
/*      */     //   917: getfield 376	dq:v	I
/*      */     //   920: ldc_w 366
/*      */     //   923: imul
/*      */     //   924: bipush 81
/*      */     //   926: invokevirtual 318	ea:z	(IB)V
/*      */     //   929: getstatic 341	client:dk	Lea;
/*      */     //   932: getstatic 410	client:cl	Ldq;
/*      */     //   935: getfield 376	dq:v	I
/*      */     //   938: ldc_w 366
/*      */     //   941: imul
/*      */     //   942: bipush 54
/*      */     //   944: invokevirtual 318	ea:z	(IB)V
/*      */     //   947: getstatic 341	client:dk	Lea;
/*      */     //   950: getstatic 414	ab:cp	Ldq;
/*      */     //   953: getfield 376	dq:v	I
/*      */     //   956: ldc_w 366
/*      */     //   959: imul
/*      */     //   960: bipush 75
/*      */     //   962: invokevirtual 318	ea:z	(IB)V
/*      */     //   965: getstatic 341	client:dk	Lea;
/*      */     //   968: ldc_w 366
/*      */     //   971: getstatic 418	dz:ca	Ldq;
/*      */     //   974: getfield 376	dq:v	I
/*      */     //   977: imul
/*      */     //   978: bipush 116
/*      */     //   980: invokevirtual 318	ea:z	(IB)V
/*      */     //   983: getstatic 341	client:dk	Lea;
/*      */     //   986: getstatic 423	ct:co	Ldq;
/*      */     //   989: getfield 376	dq:v	I
/*      */     //   992: ldc_w 366
/*      */     //   995: imul
/*      */     //   996: bipush 60
/*      */     //   998: invokevirtual 318	ea:z	(IB)V
/*      */     //   1001: getstatic 341	client:dk	Lea;
/*      */     //   1004: getstatic 427	cj:ch	Ldq;
/*      */     //   1007: getfield 376	dq:v	I
/*      */     //   1010: ldc_w 366
/*      */     //   1013: imul
/*      */     //   1014: bipush 101
/*      */     //   1016: invokevirtual 318	ea:z	(IB)V
/*      */     //   1019: getstatic 341	client:dk	Lea;
/*      */     //   1022: getstatic 431	ey:cu	Ldq;
/*      */     //   1025: getfield 376	dq:v	I
/*      */     //   1028: ldc_w 366
/*      */     //   1031: imul
/*      */     //   1032: bipush 92
/*      */     //   1034: invokevirtual 318	ea:z	(IB)V
/*      */     //   1037: getstatic 341	client:dk	Lea;
/*      */     //   1040: ldc_w 366
/*      */     //   1043: getstatic 434	z:cc	Ldq;
/*      */     //   1046: getfield 376	dq:v	I
/*      */     //   1049: imul
/*      */     //   1050: bipush 122
/*      */     //   1052: invokevirtual 318	ea:z	(IB)V
/*      */     //   1055: getstatic 341	client:dk	Lea;
/*      */     //   1058: aload_1
/*      */     //   1059: iload_3
/*      */     //   1060: getstatic 341	client:dk	Lea;
/*      */     //   1063: getfield 267	ea:c	I
/*      */     //   1066: ldc_w 350
/*      */     //   1069: imul
/*      */     //   1070: ldc_w 435
/*      */     //   1073: invokevirtual 438	ea:az	([IIII)V
/*      */     //   1076: getstatic 341	client:dk	Lea;
/*      */     //   1079: ldc_w 350
/*      */     //   1082: getstatic 341	client:dk	Lea;
/*      */     //   1085: getfield 267	ea:c	I
/*      */     //   1088: imul
/*      */     //   1089: iload_2
/*      */     //   1090: isub
/*      */     //   1091: ldc_w 439
/*      */     //   1094: invokevirtual 441	ea:w	(II)V
/*      */     //   1097: getstatic 210	at:dd	Lam;
/*      */     //   1100: getstatic 341	client:dk	Lea;
/*      */     //   1103: getfield 273	ea:m	[B
/*      */     //   1106: iconst_0
/*      */     //   1107: getstatic 341	client:dk	Lea;
/*      */     //   1110: getfield 267	ea:c	I
/*      */     //   1113: ldc_w 350
/*      */     //   1116: imul
/*      */     //   1117: ldc_w 442
/*      */     //   1120: invokevirtual 277	am:z	([BIII)V
/*      */     //   1123: getstatic 264	client:df	Lea;
/*      */     //   1126: aload_1
/*      */     //   1127: ldc_w 443
/*      */     //   1130: invokevirtual 447	ea:gv	([II)V
/*      */     //   1133: iconst_0
/*      */     //   1134: istore 4
/*      */     //   1136: iload 4
/*      */     //   1138: iconst_4
/*      */     //   1139: if_icmpge +25 -> 1164
/*      */     //   1142: iload_0
/*      */     //   1143: ldc 204
/*      */     //   1145: if_icmplt +4 -> 1149
/*      */     //   1148: return
/*      */     //   1149: aload_1
/*      */     //   1150: iload 4
/*      */     //   1152: dup2
/*      */     //   1153: iaload
/*      */     //   1154: bipush 50
/*      */     //   1156: iadd
/*      */     //   1157: iastore
/*      */     //   1158: iinc 4 1
/*      */     //   1161: goto -25 -> 1136
/*      */     //   1164: getstatic 280	client:dz	Lea;
/*      */     //   1167: aload_1
/*      */     //   1168: ldc_w 448
/*      */     //   1171: invokevirtual 447	ea:gv	([II)V
/*      */     //   1174: ldc_w 449
/*      */     //   1177: putstatic 202	client:cw	I
/*      */     //   1180: bipush 6
/*      */     //   1182: ldc 203
/*      */     //   1184: getstatic 202	client:cw	I
/*      */     //   1187: imul
/*      */     //   1188: if_icmpne +439 -> 1627
/*      */     //   1191: iload_0
/*      */     //   1192: ldc 204
/*      */     //   1194: if_icmplt +6 -> 1200
/*      */     //   1197: goto +3 -> 1200
/*      */     //   1200: getstatic 210	at:dd	Lam;
/*      */     //   1203: ldc_w 450
/*      */     //   1206: invokevirtual 452	am:n	(I)I
/*      */     //   1209: ifle +418 -> 1627
/*      */     //   1212: iload_0
/*      */     //   1213: ldc 204
/*      */     //   1215: if_icmplt +4 -> 1219
/*      */     //   1218: return
/*      */     //   1219: getstatic 210	at:dd	Lam;
/*      */     //   1222: ldc_w 296
/*      */     //   1225: invokevirtual 299	am:c	(I)I
/*      */     //   1228: istore_1
/*      */     //   1229: bipush 21
/*      */     //   1231: iload_1
/*      */     //   1232: if_icmpne +47 -> 1279
/*      */     //   1235: iload_0
/*      */     //   1236: ldc 204
/*      */     //   1238: if_icmplt +6 -> 1244
/*      */     //   1241: goto +3 -> 1244
/*      */     //   1244: bipush 20
/*      */     //   1246: getstatic 343	client:at	I
/*      */     //   1249: ldc_w 344
/*      */     //   1252: imul
/*      */     //   1253: if_icmpne +26 -> 1279
/*      */     //   1256: iload_0
/*      */     //   1257: ldc 204
/*      */     //   1259: if_icmplt +11 -> 1270
/*      */     //   1262: new 79	java/lang/IllegalStateException
/*      */     //   1265: dup
/*      */     //   1266: invokespecial 83	java/lang/IllegalStateException:<init>	()V
/*      */     //   1269: athrow
/*      */     //   1270: ldc_w 453
/*      */     //   1273: putstatic 202	client:cw	I
/*      */     //   1276: goto +351 -> 1627
/*      */     //   1279: iload_1
/*      */     //   1280: iconst_2
/*      */     //   1281: if_icmpne +21 -> 1302
/*      */     //   1284: iload_0
/*      */     //   1285: ldc 204
/*      */     //   1287: if_icmplt +6 -> 1293
/*      */     //   1290: goto +3 -> 1293
/*      */     //   1293: ldc_w 454
/*      */     //   1296: putstatic 202	client:cw	I
/*      */     //   1299: goto +328 -> 1627
/*      */     //   1302: bipush 15
/*      */     //   1304: iload_1
/*      */     //   1305: if_icmpne +264 -> 1569
/*      */     //   1308: iload_0
/*      */     //   1309: ldc 204
/*      */     //   1311: if_icmplt +4 -> 1315
/*      */     //   1314: return
/*      */     //   1315: ldc_w 344
/*      */     //   1318: getstatic 343	client:at	I
/*      */     //   1321: imul
/*      */     //   1322: bipush 40
/*      */     //   1324: if_icmpne +245 -> 1569
/*      */     //   1327: iload_0
/*      */     //   1328: ldc 204
/*      */     //   1330: if_icmplt +11 -> 1341
/*      */     //   1333: new 79	java/lang/IllegalStateException
/*      */     //   1336: dup
/*      */     //   1337: invokespecial 83	java/lang/IllegalStateException:<init>	()V
/*      */     //   1340: athrow
/*      */     //   1341: getstatic 264	client:df	Lea;
/*      */     //   1344: iconst_0
/*      */     //   1345: putfield 267	ea:c	I
/*      */     //   1348: getstatic 280	client:dz	Lea;
/*      */     //   1351: iconst_0
/*      */     //   1352: putfield 267	ea:c	I
/*      */     //   1355: ldc_w 455
/*      */     //   1358: putstatic 458	client:dj	I
/*      */     //   1361: ldc_w 459
/*      */     //   1364: putstatic 462	client:dc	I
/*      */     //   1367: ldc_w 463
/*      */     //   1370: putstatic 466	client:dp	I
/*      */     //   1373: ldc_w 467
/*      */     //   1376: putstatic 470	client:dm	I
/*      */     //   1379: iconst_0
/*      */     //   1380: putstatic 473	client:da	I
/*      */     //   1383: iconst_0
/*      */     //   1384: putstatic 476	client:dv	I
/*      */     //   1387: iconst_0
/*      */     //   1388: putstatic 478	client:bs	I
/*      */     //   1391: iconst_0
/*      */     //   1392: putstatic 481	client:jp	I
/*      */     //   1395: iconst_0
/*      */     //   1396: putstatic 484	client:jj	Z
/*      */     //   1399: iconst_0
/*      */     //   1400: putstatic 487	client:nt	I
/*      */     //   1403: iconst_0
/*      */     //   1404: putstatic 490	client:nv	I
/*      */     //   1407: iconst_0
/*      */     //   1408: istore_2
/*      */     //   1409: iload_2
/*      */     //   1410: getstatic 494	client:iq	[Lfi;
/*      */     //   1413: arraylength
/*      */     //   1414: if_icmpge +44 -> 1458
/*      */     //   1417: iload_0
/*      */     //   1418: ldc 204
/*      */     //   1420: if_icmplt +6 -> 1426
/*      */     //   1423: goto +3 -> 1426
/*      */     //   1426: getstatic 494	client:iq	[Lfi;
/*      */     //   1429: iload_2
/*      */     //   1430: aaload
/*      */     //   1431: ifnull +21 -> 1452
/*      */     //   1434: iload_0
/*      */     //   1435: ldc 204
/*      */     //   1437: if_icmplt +4 -> 1441
/*      */     //   1440: return
/*      */     //   1441: getstatic 494	client:iq	[Lfi;
/*      */     //   1444: iload_2
/*      */     //   1445: aaload
/*      */     //   1446: ldc_w 495
/*      */     //   1449: putfield 499	fi:am	I
/*      */     //   1452: iinc 2 1
/*      */     //   1455: goto -46 -> 1409
/*      */     //   1458: iconst_0
/*      */     //   1459: istore_2
/*      */     //   1460: iload_2
/*      */     //   1461: getstatic 503	client:ci	[Lge;
/*      */     //   1464: arraylength
/*      */     //   1465: if_icmpge +49 -> 1514
/*      */     //   1468: iload_0
/*      */     //   1469: ldc 204
/*      */     //   1471: if_icmplt +4 -> 1475
/*      */     //   1474: return
/*      */     //   1475: getstatic 503	client:ci	[Lge;
/*      */     //   1478: iload_2
/*      */     //   1479: aaload
/*      */     //   1480: ifnull +28 -> 1508
/*      */     //   1483: iload_0
/*      */     //   1484: ldc 204
/*      */     //   1486: if_icmplt +11 -> 1497
/*      */     //   1489: new 79	java/lang/IllegalStateException
/*      */     //   1492: dup
/*      */     //   1493: invokespecial 83	java/lang/IllegalStateException:<init>	()V
/*      */     //   1496: athrow
/*      */     //   1497: getstatic 503	client:ci	[Lge;
/*      */     //   1500: iload_2
/*      */     //   1501: aaload
/*      */     //   1502: ldc_w 495
/*      */     //   1505: putfield 506	ge:am	I
/*      */     //   1508: iinc 2 1
/*      */     //   1511: goto -51 -> 1460
/*      */     //   1514: new 508	cf
/*      */     //   1517: dup
/*      */     //   1518: bipush 32
/*      */     //   1520: invokespecial 510	cf:<init>	(I)V
/*      */     //   1523: putstatic 515	dl:m	Lcf;
/*      */     //   1526: bipush 30
/*      */     //   1528: ldc_w 516
/*      */     //   1531: invokestatic 521	aj:ce	(II)V
/*      */     //   1534: iconst_0
/*      */     //   1535: istore_2
/*      */     //   1536: iload_2
/*      */     //   1537: bipush 100
/*      */     //   1539: if_icmpge +29 -> 1568
/*      */     //   1542: iload_0
/*      */     //   1543: ldc 204
/*      */     //   1545: if_icmplt +11 -> 1556
/*      */     //   1548: new 79	java/lang/IllegalStateException
/*      */     //   1551: dup
/*      */     //   1552: invokespecial 83	java/lang/IllegalStateException:<init>	()V
/*      */     //   1555: athrow
/*      */     //   1556: getstatic 525	client:mq	[Z
/*      */     //   1559: iload_2
/*      */     //   1560: iconst_1
/*      */     //   1561: bastore
/*      */     //   1562: iinc 2 1
/*      */     //   1565: goto -29 -> 1536
/*      */     //   1568: return
/*      */     //   1569: iload_1
/*      */     //   1570: bipush 23
/*      */     //   1572: if_icmpne +47 -> 1619
/*      */     //   1575: iload_0
/*      */     //   1576: ldc 204
/*      */     //   1578: if_icmplt +4 -> 1582
/*      */     //   1581: return
/*      */     //   1582: getstatic 528	client:cv	I
/*      */     //   1585: ldc_w 529
/*      */     //   1588: imul
/*      */     //   1589: iconst_1
/*      */     //   1590: if_icmpge +29 -> 1619
/*      */     //   1593: iload_0
/*      */     //   1594: ldc 204
/*      */     //   1596: if_icmplt +6 -> 1602
/*      */     //   1599: goto +0 -> 1599
/*      */     //   1602: getstatic 528	client:cv	I
/*      */     //   1605: ldc_w 530
/*      */     //   1608: iadd
/*      */     //   1609: putstatic 528	client:cv	I
/*      */     //   1612: iconst_0
/*      */     //   1613: putstatic 202	client:cw	I
/*      */     //   1616: goto +11 -> 1627
/*      */     //   1619: iload_1
/*      */     //   1620: ldc_w 531
/*      */     //   1623: invokestatic 305	bf:dk	(II)V
/*      */     //   1626: return
/*      */     //   1627: bipush 7
/*      */     //   1629: ldc 203
/*      */     //   1631: getstatic 202	client:cw	I
/*      */     //   1634: imul
/*      */     //   1635: if_icmpne +57 -> 1692
/*      */     //   1638: iload_0
/*      */     //   1639: ldc 204
/*      */     //   1641: if_icmplt +6 -> 1647
/*      */     //   1644: goto +3 -> 1647
/*      */     //   1647: getstatic 210	at:dd	Lam;
/*      */     //   1650: ldc_w 450
/*      */     //   1653: invokevirtual 452	am:n	(I)I
/*      */     //   1656: ifle +36 -> 1692
/*      */     //   1659: iload_0
/*      */     //   1660: ldc 204
/*      */     //   1662: if_icmplt +6 -> 1668
/*      */     //   1665: goto +0 -> 1665
/*      */     //   1668: getstatic 210	at:dd	Lam;
/*      */     //   1671: ldc_w 296
/*      */     //   1674: invokevirtual 299	am:c	(I)I
/*      */     //   1677: iconst_3
/*      */     //   1678: iadd
/*      */     //   1679: ldc_w 532
/*      */     //   1682: imul
/*      */     //   1683: putstatic 534	client:ct	I
/*      */     //   1686: ldc_w 535
/*      */     //   1689: putstatic 202	client:cw	I
/*      */     //   1692: ldc 203
/*      */     //   1694: getstatic 202	client:cw	I
/*      */     //   1697: imul
/*      */     //   1698: bipush 8
/*      */     //   1700: if_icmpne +92 -> 1792
/*      */     //   1703: iload_0
/*      */     //   1704: ldc 204
/*      */     //   1706: if_icmplt +4 -> 1710
/*      */     //   1709: return
/*      */     //   1710: iconst_0
/*      */     //   1711: putstatic 226	client:cz	I
/*      */     //   1714: getstatic 539	ba:ap	Ljava/lang/String;
/*      */     //   1717: getstatic 542	ba:av	Ljava/lang/String;
/*      */     //   1720: new 544	java/lang/StringBuilder
/*      */     //   1723: dup
/*      */     //   1724: invokespecial 545	java/lang/StringBuilder:<init>	()V
/*      */     //   1727: ldc_w 546
/*      */     //   1730: getstatic 534	client:ct	I
/*      */     //   1733: imul
/*      */     //   1734: bipush 60
/*      */     //   1736: idiv
/*      */     //   1737: invokevirtual 550	java/lang/StringBuilder:append	(I)Ljava/lang/StringBuilder;
/*      */     //   1740: getstatic 552	ba:ak	Ljava/lang/String;
/*      */     //   1743: invokevirtual 555	java/lang/StringBuilder:append	(Ljava/lang/String;)Ljava/lang/StringBuilder;
/*      */     //   1746: invokevirtual 559	java/lang/StringBuilder:toString	()Ljava/lang/String;
/*      */     //   1749: ldc_w 560
/*      */     //   1752: invokestatic 565	em:c	(Ljava/lang/String;Ljava/lang/String;Ljava/lang/String;I)V
/*      */     //   1755: getstatic 534	client:ct	I
/*      */     //   1758: ldc_w 566
/*      */     //   1761: isub
/*      */     //   1762: dup
/*      */     //   1763: putstatic 534	client:ct	I
/*      */     //   1766: ldc_w 546
/*      */     //   1769: imul
/*      */     //   1770: ifgt +21 -> 1791
/*      */     //   1773: iload_0
/*      */     //   1774: ldc 204
/*      */     //   1776: if_icmplt +11 -> 1787
/*      */     //   1779: new 79	java/lang/IllegalStateException
/*      */     //   1782: dup
/*      */     //   1783: invokespecial 83	java/lang/IllegalStateException:<init>	()V
/*      */     //   1786: athrow
/*      */     //   1787: iconst_0
/*      */     //   1788: putstatic 202	client:cw	I
/*      */     //   1791: return
/*      */     //   1792: bipush 9
/*      */     //   1794: ldc 203
/*      */     //   1796: getstatic 202	client:cw	I
/*      */     //   1799: imul
/*      */     //   1800: if_icmpne +240 -> 2040
/*      */     //   1803: iload_0
/*      */     //   1804: ldc 204
/*      */     //   1806: if_icmplt +6 -> 1812
/*      */     //   1809: goto +0 -> 1809
/*      */     //   1812: getstatic 210	at:dd	Lam;
/*      */     //   1815: ldc_w 450
/*      */     //   1818: invokevirtual 452	am:n	(I)I
/*      */     //   1821: bipush 8
/*      */     //   1823: if_icmplt +217 -> 2040
/*      */     //   1826: iload_0
/*      */     //   1827: ldc 204
/*      */     //   1829: if_icmplt +11 -> 1840
/*      */     //   1832: new 79	java/lang/IllegalStateException
/*      */     //   1835: dup
/*      */     //   1836: invokespecial 83	java/lang/IllegalStateException:<init>	()V
/*      */     //   1839: athrow
/*      */     //   1840: getstatic 210	at:dd	Lam;
/*      */     //   1843: ldc_w 296
/*      */     //   1846: invokevirtual 299	am:c	(I)I
/*      */     //   1849: ldc_w 567
/*      */     //   1852: imul
/*      */     //   1853: putstatic 570	client:kp	I
/*      */     //   1856: getstatic 210	at:dd	Lam;
/*      */     //   1859: ldc_w 296
/*      */     //   1862: invokevirtual 299	am:c	(I)I
/*      */     //   1865: iconst_1
/*      */     //   1866: if_icmpne +16 -> 1882
/*      */     //   1869: iload_0
/*      */     //   1870: ldc 204
/*      */     //   1872: if_icmplt +6 -> 1878
/*      */     //   1875: goto +0 -> 1875
/*      */     //   1878: iconst_1
/*      */     //   1879: goto +4 -> 1883
/*      */     //   1882: iconst_0
/*      */     //   1883: putstatic 573	client:kw	Z
/*      */     //   1886: getstatic 210	at:dd	Lam;
/*      */     //   1889: ldc_w 296
/*      */     //   1892: invokevirtual 299	am:c	(I)I
/*      */     //   1895: ldc_w 574
/*      */     //   1898: imul
/*      */     //   1899: putstatic 577	client:ik	I
/*      */     //   1902: ldc_w 578
/*      */     //   1905: getstatic 577	client:ik	I
/*      */     //   1908: imul
/*      */     //   1909: bipush 8
/*      */     //   1911: ishl
/*      */     //   1912: ldc_w 574
/*      */     //   1915: imul
/*      */     //   1916: putstatic 577	client:ik	I
/*      */     //   1919: getstatic 577	client:ik	I
/*      */     //   1922: getstatic 210	at:dd	Lam;
/*      */     //   1925: ldc_w 296
/*      */     //   1928: invokevirtual 299	am:c	(I)I
/*      */     //   1931: ldc_w 574
/*      */     //   1934: imul
/*      */     //   1935: iadd
/*      */     //   1936: putstatic 577	client:ik	I
/*      */     //   1939: getstatic 210	at:dd	Lam;
/*      */     //   1942: ldc_w 296
/*      */     //   1945: invokevirtual 299	am:c	(I)I
/*      */     //   1948: ldc_w 579
/*      */     //   1951: imul
/*      */     //   1952: putstatic 582	client:iy	I
/*      */     //   1955: getstatic 210	at:dd	Lam;
/*      */     //   1958: getstatic 280	client:dz	Lea;
/*      */     //   1961: getfield 273	ea:m	[B
/*      */     //   1964: iconst_0
/*      */     //   1965: iconst_1
/*      */     //   1966: ldc_w 583
/*      */     //   1969: invokevirtual 585	am:j	([BIII)V
/*      */     //   1972: getstatic 280	client:dz	Lea;
/*      */     //   1975: iconst_0
/*      */     //   1976: putfield 267	ea:c	I
/*      */     //   1979: getstatic 280	client:dz	Lea;
/*      */     //   1982: bipush 69
/*      */     //   1984: invokevirtual 589	ea:gg	(B)I
/*      */     //   1987: ldc_w 590
/*      */     //   1990: imul
/*      */     //   1991: putstatic 458	client:dj	I
/*      */     //   1994: getstatic 210	at:dd	Lam;
/*      */     //   1997: getstatic 280	client:dz	Lea;
/*      */     //   2000: getfield 273	ea:m	[B
/*      */     //   2003: iconst_0
/*      */     //   2004: iconst_2
/*      */     //   2005: ldc_w 591
/*      */     //   2008: invokevirtual 585	am:j	([BIII)V
/*      */     //   2011: getstatic 280	client:dz	Lea;
/*      */     //   2014: iconst_0
/*      */     //   2015: putfield 267	ea:c	I
/*      */     //   2018: getstatic 280	client:dz	Lea;
/*      */     //   2021: ldc_w 592
/*      */     //   2024: invokevirtual 594	ea:k	(I)I
/*      */     //   2027: ldc_w 595
/*      */     //   2030: imul
/*      */     //   2031: putstatic 473	client:da	I
/*      */     //   2034: ldc_w 596
/*      */     //   2037: putstatic 202	client:cw	I
/*      */     //   2040: ldc 203
/*      */     //   2042: getstatic 202	client:cw	I
/*      */     //   2045: imul
/*      */     //   2046: bipush 10
/*      */     //   2048: if_icmpne +96 -> 2144
/*      */     //   2051: iload_0
/*      */     //   2052: ldc 204
/*      */     //   2054: if_icmplt +6 -> 2060
/*      */     //   2057: goto +3 -> 2060
/*      */     //   2060: getstatic 210	at:dd	Lam;
/*      */     //   2063: ldc_w 450
/*      */     //   2066: invokevirtual 452	am:n	(I)I
/*      */     //   2069: getstatic 473	client:da	I
/*      */     //   2072: ldc_w 597
/*      */     //   2075: imul
/*      */     //   2076: if_icmplt +67 -> 2143
/*      */     //   2079: iload_0
/*      */     //   2080: ldc 204
/*      */     //   2082: if_icmplt +6 -> 2088
/*      */     //   2085: goto +0 -> 2085
/*      */     //   2088: getstatic 280	client:dz	Lea;
/*      */     //   2091: iconst_0
/*      */     //   2092: putfield 267	ea:c	I
/*      */     //   2095: getstatic 210	at:dd	Lam;
/*      */     //   2098: getstatic 280	client:dz	Lea;
/*      */     //   2101: getfield 273	ea:m	[B
/*      */     //   2104: iconst_0
/*      */     //   2105: ldc_w 597
/*      */     //   2108: getstatic 473	client:da	I
/*      */     //   2111: imul
/*      */     //   2112: ldc_w 598
/*      */     //   2115: invokevirtual 585	am:j	([BIII)V
/*      */     //   2118: sipush 255
/*      */     //   2121: invokestatic 601	dr:df	(S)V
/*      */     //   2124: ldc_w 602
/*      */     //   2127: putstatic 606	cd:dn	I
/*      */     //   2130: iconst_0
/*      */     //   2131: ldc_w 607
/*      */     //   2134: invokestatic 613	cy:ei	(ZI)V
/*      */     //   2137: ldc_w 455
/*      */     //   2140: putstatic 458	client:dj	I
/*      */     //   2143: return
/*      */     //   2144: getstatic 226	client:cz	I
/*      */     //   2147: ldc_w 614
/*      */     //   2150: iadd
/*      */     //   2151: putstatic 226	client:cz	I
/*      */     //   2154: getstatic 226	client:cz	I
/*      */     //   2157: ldc_w 615
/*      */     //   2160: imul
/*      */     //   2161: sipush 2000
/*      */     //   2164: if_icmple +109 -> 2273
/*      */     //   2167: iload_0
/*      */     //   2168: ldc 204
/*      */     //   2170: if_icmplt +6 -> 2176
/*      */     //   2173: goto +3 -> 2176
/*      */     //   2176: getstatic 528	client:cv	I
/*      */     //   2179: ldc_w 529
/*      */     //   2182: imul
/*      */     //   2183: iconst_1
/*      */     //   2184: if_icmpge +80 -> 2264
/*      */     //   2187: iload_0
/*      */     //   2188: ldc 204
/*      */     //   2190: if_icmplt +6 -> 2196
/*      */     //   2193: goto +0 -> 2193
/*      */     //   2196: ldc_w 616
/*      */     //   2199: getstatic 619	dn:cy	I
/*      */     //   2202: imul
/*      */     //   2203: ldc 241
/*      */     //   2205: getstatic 240	cu:cd	I
/*      */     //   2208: imul
/*      */     //   2209: if_icmpne +30 -> 2239
/*      */     //   2212: iload_0
/*      */     //   2213: ldc 204
/*      */     //   2215: if_icmplt +11 -> 2226
/*      */     //   2218: new 79	java/lang/IllegalStateException
/*      */     //   2221: dup
/*      */     //   2222: invokespecial 83	java/lang/IllegalStateException:<init>	()V
/*      */     //   2225: athrow
/*      */     //   2226: ldc_w 620
/*      */     //   2229: getstatic 623	d:cq	I
/*      */     //   2232: imul
/*      */     //   2233: putstatic 240	cu:cd	I
/*      */     //   2236: goto +13 -> 2249
/*      */     //   2239: ldc_w 624
/*      */     //   2242: getstatic 619	dn:cy	I
/*      */     //   2245: imul
/*      */     //   2246: putstatic 240	cu:cd	I
/*      */     //   2249: getstatic 528	client:cv	I
/*      */     //   2252: ldc_w 530
/*      */     //   2255: iadd
/*      */     //   2256: putstatic 528	client:cv	I
/*      */     //   2259: iconst_0
/*      */     //   2260: putstatic 202	client:cw	I
/*      */     //   2263: return
/*      */     //   2264: bipush 253
/*      */     //   2266: ldc_w 625
/*      */     //   2269: invokestatic 305	bf:dk	(II)V
/*      */     //   2272: return
/*      */     //   2273: goto +96 -> 2369
/*      */     //   2276: astore_1
/*      */     //   2277: getstatic 528	client:cv	I
/*      */     //   2280: ldc_w 529
/*      */     //   2283: imul
/*      */     //   2284: iconst_1
/*      */     //   2285: if_icmpge +75 -> 2360
/*      */     //   2288: iload_0
/*      */     //   2289: ldc 204
/*      */     //   2291: if_icmplt +6 -> 2297
/*      */     //   2294: goto +0 -> 2294
/*      */     //   2297: ldc_w 616
/*      */     //   2300: getstatic 619	dn:cy	I
/*      */     //   2303: imul
/*      */     //   2304: getstatic 240	cu:cd	I
/*      */     //   2307: ldc 241
/*      */     //   2309: imul
/*      */     //   2310: if_icmpne +25 -> 2335
/*      */     //   2313: iload_0
/*      */     //   2314: ldc 204
/*      */     //   2316: if_icmplt +6 -> 2322
/*      */     //   2319: goto +3 -> 2322
/*      */     //   2322: ldc_w 620
/*      */     //   2325: getstatic 623	d:cq	I
/*      */     //   2328: imul
/*      */     //   2329: putstatic 240	cu:cd	I
/*      */     //   2332: goto +13 -> 2345
/*      */     //   2335: getstatic 619	dn:cy	I
/*      */     //   2338: ldc_w 624
/*      */     //   2341: imul
/*      */     //   2342: putstatic 240	cu:cd	I
/*      */     //   2345: getstatic 528	client:cv	I
/*      */     //   2348: ldc_w 530
/*      */     //   2351: iadd
/*      */     //   2352: putstatic 528	client:cv	I
/*      */     //   2355: iconst_0
/*      */     //   2356: putstatic 202	client:cw	I
/*      */     //   2359: return
/*      */     //   2360: bipush 254
/*      */     //   2362: ldc_w 626
/*      */     //   2365: invokestatic 305	bf:dk	(II)V
/*      */     //   2368: return
/*      */     //   2369: return
/*      */     //
/*      */     // Exception table:
/*      */     //   from	to	target	type
/*      */     //   0	2272	2276	java/io/IOException
/*      */   }
/*      */ 
/*      */   static void z(int paramInt1, int paramInt2, int paramInt3, int paramInt4, int paramInt5)
/*      */   {
/*   85 */     for (de localde = (de)de.m.j(); null != localde; localde = (de)de.m.g()) if ((paramInt5 != -1782857976) || (
/*   86 */         (-1 == 1995197999 * localde.i) && ((paramInt5 != -1782857976) || (localde.w == null)))) { if (paramInt5 != -1782857976); } else {
/*   87 */         int i = 0;
/*   88 */         if (paramInt2 > localde.z * -122421739) { if (paramInt5 != -1782857976) return; i += paramInt2 - localde.z * -122421739;
/*   89 */         } else if (paramInt2 < localde.n * -594801031) { if (paramInt5 == -1782857976);
/*   89 */           i += localde.n * -594801031 - paramInt2; }
/*   90 */         if (paramInt3 > 226236917 * localde.g) { if (paramInt5 == -1782857976);
/*   90 */           i += paramInt3 - localde.g * 226236917;
/*   91 */         } else if (paramInt3 < -690851833 * localde.j) { if (paramInt5 == -1782857976);
/*   91 */           i += -690851833 * localde.j - paramInt3; }
/*   92 */         if (i - 64 <= localde.q * 600383925) { if (paramInt5 != -1782857976) return; if (-1639239111 * client.oz != 0) { if ((paramInt5 == -1782857976) && (paramInt1 == localde.c * -299207229)) break label403; if (paramInt5 != -1782857976) throw new IllegalStateException();  } 
/*      */         }
/*   93 */         if (localde.u != null) { if (paramInt5 != -1782857976) throw new IllegalStateException();
/*   94 */           cq.oc.ad(localde.u);
/*   95 */           localde.u = null;
/*      */         }
/*   97 */         if (null != localde.b) { if (paramInt5 != -1782857976) throw new IllegalStateException();
/*   98 */           cq.oc.ad(localde.b);
/*   99 */           localde.b = null; continue;
/*      */ 
/*  103 */           label403: i -= 64;
/*  104 */           if (i < 0) { if (paramInt5 != -1782857976) throw new IllegalStateException(); i = 0; }
/*  105 */           int j = (localde.q * 600383925 - i) * (-1639239111 * client.oz) / (600383925 * localde.q);
/*      */           Object localObject1;
/*      */           Object localObject2;
/*  106 */           if (null == localde.u) { if (paramInt5 != -1782857976) return;
/*  107 */             if (1995197999 * localde.i >= 0) { if (paramInt5 != -1782857976) throw new IllegalStateException();
/*  108 */               o localo = o.r(df.bb, 1995197999 * localde.i, 0);
/*  109 */               if (null != localo) { if (paramInt5 != -1782857976) return;
/*  110 */                 localObject1 = localo.d().c(ev.od);
/*  111 */                 localObject2 = et.ac((eq)localObject1, 100, j);
/*  112 */                 ((et)localObject2).am(-1);
/*  113 */                 cq.oc.p((dx)localObject2);
/*  114 */                 localde.u = ((et)localObject2); } }
/*      */           }
/*      */           else
/*      */           {
/*  118 */             localde.u.ap(j);
/*  119 */           }if (localde.b == null) { if (paramInt5 != -1782857976) throw new IllegalStateException();
/*  120 */             if (null != localde.w) { if (paramInt5 != -1782857976) throw new IllegalStateException(); if ((localde.e -= paramInt4 * 1914159225) * 2031790537 <= 0) { if (paramInt5 != -1782857976) return;
/*  121 */                 int k = (int)(Math.random() * localde.w.length);
/*  122 */                 localObject1 = o.r(df.bb, localde.w[k], 0);
/*  123 */                 if (localObject1 != null) { if (paramInt5 != -1782857976) throw new IllegalStateException();
/*  124 */                   localObject2 = ((o)localObject1).d().c(ev.od);
/*  125 */                   et localet = et.ac((eq)localObject2, 100, j);
/*  126 */                   localet.am(0);
/*  127 */                   cq.oc.p(localet);
/*  128 */                   localde.b = localet;
/*  129 */                   localde.e = ((126224035 * localde.s + (int)(Math.random() * (540356717 * localde.v - localde.s * 126224035))) * 1914159225); } }
/*      */             }
/*      */           }
/*      */           else
/*      */           {
/*  134 */             localde.b.ap(j);
/*  135 */             if (!localde.b.d()) { if (paramInt5 == -1782857976);
/*  136 */               localde.b = null;
/*      */             }
/*      */           }
/*      */         }
/*      */       }
/*      */   }
/*      */ 
/*      */   public static void m(ev paramev, int paramInt1, int paramInt2)
/*      */   {
/*  229 */     if (ay.i != null) { if (paramInt2 == 409525042);
/*      */       try {
/*  231 */         ay.i.d(0L);
/*  232 */         ay.i.j(paramev.m, paramInt1, 24, (byte)74);
/*      */       }
/*      */       catch (Exception localException)
/*      */       {
/*      */       }
/*      */     }
/*      */   }
/*      */ }

/* Location:           C:\Users\Mike\IdeaProjects\RealityBot-2007 Updater\client-deob.jar
 * Qualified Name:     ex
 * JD-Core Version:    0.6.2
 */