/*     */ import java.io.DataInputStream;
/*     */ import java.io.IOException;
/*     */ import java.net.URL;
/*     */ 
/*     */ public class i
/*     */ {
/*     */   byte[] n;
/*     */   int r;
/*     */   DataInputStream l;
/*     */   ah d;
/*     */   int c;
/*     */   long z;
/*     */   int j;
/*  15 */   byte[] m = new byte[4];
/*     */   static byte[][] eh;
/*     */   static fq[] ft;
/*     */ 
/*     */   byte[] r(int paramInt)
/*     */     throws IOException
/*     */   {
/*  28 */     if (cm.r(854194521) > -6286787868142241225L * this.z) { if (paramInt == 320771376) throw new IllegalStateException(); throw new IOException(); }
/*  29 */     if (this.r * -1177019123 == 0) { if ((paramInt == 320771376) || 
/*  30 */         (this.d.c == 2)) { if (paramInt != 320771376);
/*  30 */         throw new IOException(); }
/*  31 */       if (1 == this.d.c) { if (paramInt != 320771376);
/*  32 */         this.l = ((DataInputStream)this.d.g);
/*  33 */         this.r = 774961605;
/*     */       }
/*     */     }
/*  36 */     int i;
/*  36 */     if (this.r * -1177019123 == 1) { if (paramInt != 320771376);
/*  37 */       i = this.l.available();
/*  38 */       if (i > 0) { if ((paramInt == 320771376) || 
/*  39 */           (i + this.c * -1565939971 > 4)) { if (paramInt == 320771376) throw new IllegalStateException(); i = 4 - -1565939971 * this.c; }
/*  40 */         this.c += this.l.read(this.m, -1565939971 * this.c, i) * 1024075349;
/*  41 */         if (this.c * -1565939971 == 4) { if (paramInt != 320771376);
/*  42 */           int k = new ev(this.m).h(1398284839);
/*  43 */           this.n = new byte[k];
/*  44 */           this.r = 1549923210;
/*     */         }
/*     */       }
/*     */     }
/*  48 */     if (2 == this.r * -1177019123) { if (paramInt == 320771376) throw new IllegalStateException();
/*  49 */       i = this.l.available();
/*  50 */       if (i > 0) { if ((paramInt == 320771376) || 
/*  51 */           (i + -1352251289 * this.j > this.n.length)) { if (paramInt != 320771376);
/*  51 */           i = this.n.length - -1352251289 * this.j; }
/*  52 */         this.j += this.l.read(this.n, -1352251289 * this.j, i) * -2070129833;
/*  53 */         if (-1352251289 * this.j == this.n.length) { if (paramInt != 320771376);
/*  53 */           return this.n; }
/*     */       }
/*     */     }
/*  56 */     return null;
/*     */   }
/*     */ 
/*     */   i(ak paramak, URL paramURL)
/*     */   {
/*  22 */     this.d = paramak.g(paramURL, 806337868);
/*  23 */     this.r = 0;
/*  24 */     this.z = ((cm.r(1942902745) + 30000L) * 1134493823641934727L);
/*     */   }
/*     */ 
/*     */   byte[] d() throws IOException {
/*  28 */     if (cm.r(2044623178) > -6286787868142241225L * this.z) throw new IOException();
/*  29 */     if (this.r * -1177019123 == 0) {
/*  30 */       if (this.d.c == 2) throw new IOException();
/*  31 */       if (1 == this.d.c) {
/*  32 */         this.l = ((DataInputStream)this.d.g);
/*  33 */         this.r = 774961605;
/*     */       }
/*     */     }
/*     */     int i;
/*  36 */     if (this.r * -1177019123 == 1) {
/*  37 */       i = this.l.available();
/*  38 */       if (i > 0) {
/*  39 */         if (i + this.c * -1565939971 > 4) i = 4 - -1565939971 * this.c;
/*  40 */         this.c += this.l.read(this.m, -1565939971 * this.c, i) * 1024075349;
/*  41 */         if (this.c * -1565939971 == 4) {
/*  42 */           int k = new ev(this.m).h(2037112147);
/*  43 */           this.n = new byte[k];
/*  44 */           this.r = 1549923210;
/*     */         }
/*     */       }
/*     */     }
/*  48 */     if (2 == this.r * -1177019123) {
/*  49 */       i = this.l.available();
/*  50 */       if (i > 0) {
/*  51 */         if (i + -1352251289 * this.j > this.n.length) i = this.n.length - -1352251289 * this.j;
/*  52 */         this.j += this.l.read(this.n, -1352251289 * this.j, i) * -2070129833;
/*  53 */         if (-1352251289 * this.j == this.n.length) return this.n;
/*     */       }
/*     */     }
/*  56 */     return null;
/*     */   }
/*     */ 
/*     */   byte[] l()
/*     */     throws IOException
/*     */   {
/*  28 */     if (cm.r(1805804264) > -6286787868142241225L * this.z) throw new IOException();
/*  29 */     if (this.r * -1177019123 == 0) {
/*  30 */       if (this.d.c == 2) throw new IOException();
/*  31 */       if (1 == this.d.c) {
/*  32 */         this.l = ((DataInputStream)this.d.g);
/*  33 */         this.r = 774961605;
/*     */       }
/*     */     }
/*     */     int i;
/*  36 */     if (this.r * -1177019123 == 1) {
/*  37 */       i = this.l.available();
/*  38 */       if (i > 0) {
/*  39 */         if (i + this.c * -1565939971 > 4) i = 4 - -1565939971 * this.c;
/*  40 */         this.c += this.l.read(this.m, -1565939971 * this.c, i) * 1024075349;
/*  41 */         if (this.c * -1565939971 == 4) {
/*  42 */           int k = new ev(this.m).h(-2056380020);
/*  43 */           this.n = new byte[k];
/*  44 */           this.r = 1549923210;
/*     */         }
/*     */       }
/*     */     }
/*  48 */     if (2 == this.r * -1177019123) {
/*  49 */       i = this.l.available();
/*  50 */       if (i > 0) {
/*  51 */         if (i + -1352251289 * this.j > this.n.length) i = this.n.length - -1352251289 * this.j;
/*  52 */         this.j += this.l.read(this.n, -1352251289 * this.j, i) * -2070129833;
/*  53 */         if (-1352251289 * this.j == this.n.length) return this.n;
/*     */       }
/*     */     }
/*  56 */     return null;
/*     */   }
/*     */ 
/*     */   // ERROR //
/*     */   public static java.io.File r(String paramString1, String paramString2, int paramInt1, int paramInt2)
/*     */   {
/*     */     // Byte code:
/*     */     //   0: iload_2
/*     */     //   1: ifne +17 -> 18
/*     */     //   4: iload_3
/*     */     //   5: ldc 113
/*     */     //   7: if_icmpeq +6 -> 13
/*     */     //   10: goto +3 -> 13
/*     */     //   13: ldc 115
/*     */     //   15: goto +22 -> 37
/*     */     //   18: new 117	java/lang/StringBuilder
/*     */     //   21: dup
/*     */     //   22: invokespecial 118	java/lang/StringBuilder:<init>	()V
/*     */     //   25: ldc 115
/*     */     //   27: invokevirtual 122	java/lang/StringBuilder:append	(Ljava/lang/String;)Ljava/lang/StringBuilder;
/*     */     //   30: iload_2
/*     */     //   31: invokevirtual 125	java/lang/StringBuilder:append	(I)Ljava/lang/StringBuilder;
/*     */     //   34: invokevirtual 129	java/lang/StringBuilder:toString	()Ljava/lang/String;
/*     */     //   37: astore 4
/*     */     //   39: new 133	java/io/File
/*     */     //   42: dup
/*     */     //   43: getstatic 139	ez:o	Ljava/lang/String;
/*     */     //   46: new 117	java/lang/StringBuilder
/*     */     //   49: dup
/*     */     //   50: invokespecial 118	java/lang/StringBuilder:<init>	()V
/*     */     //   53: ldc 141
/*     */     //   55: invokevirtual 122	java/lang/StringBuilder:append	(Ljava/lang/String;)Ljava/lang/StringBuilder;
/*     */     //   58: aload_0
/*     */     //   59: invokevirtual 122	java/lang/StringBuilder:append	(Ljava/lang/String;)Ljava/lang/StringBuilder;
/*     */     //   62: ldc 143
/*     */     //   64: invokevirtual 122	java/lang/StringBuilder:append	(Ljava/lang/String;)Ljava/lang/StringBuilder;
/*     */     //   67: aload_1
/*     */     //   68: invokevirtual 122	java/lang/StringBuilder:append	(Ljava/lang/String;)Ljava/lang/StringBuilder;
/*     */     //   71: aload 4
/*     */     //   73: invokevirtual 122	java/lang/StringBuilder:append	(Ljava/lang/String;)Ljava/lang/StringBuilder;
/*     */     //   76: ldc 145
/*     */     //   78: invokevirtual 122	java/lang/StringBuilder:append	(Ljava/lang/String;)Ljava/lang/StringBuilder;
/*     */     //   81: invokevirtual 129	java/lang/StringBuilder:toString	()Ljava/lang/String;
/*     */     //   84: invokespecial 148	java/io/File:<init>	(Ljava/lang/String;Ljava/lang/String;)V
/*     */     //   87: putstatic 153	ay:m	Ljava/io/File;
/*     */     //   90: aconst_null
/*     */     //   91: astore 5
/*     */     //   93: aconst_null
/*     */     //   94: astore 6
/*     */     //   96: iconst_0
/*     */     //   97: istore 7
/*     */     //   99: getstatic 153	ay:m	Ljava/io/File;
/*     */     //   102: invokevirtual 157	java/io/File:exists	()Z
/*     */     //   105: ifeq +546 -> 651
/*     */     //   108: iload_3
/*     */     //   109: ldc 113
/*     */     //   111: if_icmpeq +6 -> 117
/*     */     //   114: goto +3 -> 117
/*     */     //   117: new 159	u
/*     */     //   120: dup
/*     */     //   121: getstatic 153	ay:m	Ljava/io/File;
/*     */     //   124: ldc 161
/*     */     //   126: ldc2_w 162
/*     */     //   129: invokespecial 166	u:<init>	(Ljava/io/File;Ljava/lang/String;J)V
/*     */     //   132: astore 8
/*     */     //   134: new 76	ev
/*     */     //   137: dup
/*     */     //   138: aload 8
/*     */     //   140: ldc 167
/*     */     //   142: invokevirtual 169	u:m	(I)J
/*     */     //   145: l2i
/*     */     //   146: invokespecial 172	ev:<init>	(I)V
/*     */     //   149: astore 9
/*     */     //   151: aload 9
/*     */     //   153: getfield 173	ev:c	I
/*     */     //   156: ldc 174
/*     */     //   158: imul
/*     */     //   159: aload 9
/*     */     //   161: getfield 175	ev:m	[B
/*     */     //   164: arraylength
/*     */     //   165: if_icmpge +100 -> 265
/*     */     //   168: iload_3
/*     */     //   169: ldc 113
/*     */     //   171: if_icmpeq +11 -> 182
/*     */     //   174: new 38	java/lang/IllegalStateException
/*     */     //   177: dup
/*     */     //   178: invokespecial 42	java/lang/IllegalStateException:<init>	()V
/*     */     //   181: athrow
/*     */     //   182: aload 8
/*     */     //   184: aload 9
/*     */     //   186: getfield 175	ev:m	[B
/*     */     //   189: aload 9
/*     */     //   191: getfield 173	ev:c	I
/*     */     //   194: ldc 174
/*     */     //   196: imul
/*     */     //   197: aload 9
/*     */     //   199: getfield 175	ev:m	[B
/*     */     //   202: arraylength
/*     */     //   203: aload 9
/*     */     //   205: getfield 173	ev:c	I
/*     */     //   208: ldc 174
/*     */     //   210: imul
/*     */     //   211: isub
/*     */     //   212: ldc 176
/*     */     //   214: invokevirtual 179	u:c	([BIII)I
/*     */     //   217: istore 10
/*     */     //   219: iload 10
/*     */     //   221: iconst_m1
/*     */     //   222: if_icmpne +25 -> 247
/*     */     //   225: iload_3
/*     */     //   226: ldc 113
/*     */     //   228: if_icmpeq +11 -> 239
/*     */     //   231: new 38	java/lang/IllegalStateException
/*     */     //   234: dup
/*     */     //   235: invokespecial 42	java/lang/IllegalStateException:<init>	()V
/*     */     //   238: athrow
/*     */     //   239: new 25	java/io/IOException
/*     */     //   242: dup
/*     */     //   243: invokespecial 43	java/io/IOException:<init>	()V
/*     */     //   246: athrow
/*     */     //   247: aload 9
/*     */     //   249: dup
/*     */     //   250: getfield 173	ev:c	I
/*     */     //   253: ldc 180
/*     */     //   255: iload 10
/*     */     //   257: imul
/*     */     //   258: iadd
/*     */     //   259: putfield 173	ev:c	I
/*     */     //   262: goto -111 -> 151
/*     */     //   265: aload 9
/*     */     //   267: iconst_0
/*     */     //   268: putfield 173	ev:c	I
/*     */     //   271: aload 9
/*     */     //   273: ldc 181
/*     */     //   275: invokevirtual 184	ev:t	(I)I
/*     */     //   278: istore 10
/*     */     //   280: iload 10
/*     */     //   282: iconst_1
/*     */     //   283: if_icmplt +32 -> 315
/*     */     //   286: iload_3
/*     */     //   287: ldc 113
/*     */     //   289: if_icmpeq +6 -> 295
/*     */     //   292: goto +3 -> 295
/*     */     //   295: iload 10
/*     */     //   297: iconst_3
/*     */     //   298: if_icmple +45 -> 343
/*     */     //   301: iload_3
/*     */     //   302: ldc 113
/*     */     //   304: if_icmpeq +11 -> 315
/*     */     //   307: new 38	java/lang/IllegalStateException
/*     */     //   310: dup
/*     */     //   311: invokespecial 42	java/lang/IllegalStateException:<init>	()V
/*     */     //   314: athrow
/*     */     //   315: new 25	java/io/IOException
/*     */     //   318: dup
/*     */     //   319: new 117	java/lang/StringBuilder
/*     */     //   322: dup
/*     */     //   323: invokespecial 118	java/lang/StringBuilder:<init>	()V
/*     */     //   326: ldc 115
/*     */     //   328: invokevirtual 122	java/lang/StringBuilder:append	(Ljava/lang/String;)Ljava/lang/StringBuilder;
/*     */     //   331: iload 10
/*     */     //   333: invokevirtual 125	java/lang/StringBuilder:append	(I)Ljava/lang/StringBuilder;
/*     */     //   336: invokevirtual 129	java/lang/StringBuilder:toString	()Ljava/lang/String;
/*     */     //   339: invokespecial 187	java/io/IOException:<init>	(Ljava/lang/String;)V
/*     */     //   342: athrow
/*     */     //   343: iconst_0
/*     */     //   344: istore 11
/*     */     //   346: iload 10
/*     */     //   348: iconst_1
/*     */     //   349: if_icmple +26 -> 375
/*     */     //   352: iload_3
/*     */     //   353: ldc 113
/*     */     //   355: if_icmpeq +11 -> 366
/*     */     //   358: new 38	java/lang/IllegalStateException
/*     */     //   361: dup
/*     */     //   362: invokespecial 42	java/lang/IllegalStateException:<init>	()V
/*     */     //   365: athrow
/*     */     //   366: aload 9
/*     */     //   368: ldc 181
/*     */     //   370: invokevirtual 184	ev:t	(I)I
/*     */     //   373: istore 11
/*     */     //   375: iload 10
/*     */     //   377: iconst_2
/*     */     //   378: if_icmpgt +53 -> 431
/*     */     //   381: iload_3
/*     */     //   382: ldc 113
/*     */     //   384: if_icmpeq +11 -> 395
/*     */     //   387: new 38	java/lang/IllegalStateException
/*     */     //   390: dup
/*     */     //   391: invokespecial 42	java/lang/IllegalStateException:<init>	()V
/*     */     //   394: athrow
/*     */     //   395: aload 9
/*     */     //   397: bipush 144
/*     */     //   399: invokevirtual 191	ev:ac	(B)Ljava/lang/String;
/*     */     //   402: astore 5
/*     */     //   404: iload 11
/*     */     //   406: iconst_1
/*     */     //   407: if_icmpne +62 -> 469
/*     */     //   410: iload_3
/*     */     //   411: ldc 113
/*     */     //   413: if_icmpeq +6 -> 419
/*     */     //   416: goto +0 -> 416
/*     */     //   419: aload 9
/*     */     //   421: bipush 232
/*     */     //   423: invokevirtual 191	ev:ac	(B)Ljava/lang/String;
/*     */     //   426: astore 6
/*     */     //   428: goto +41 -> 469
/*     */     //   431: aload 9
/*     */     //   433: ldc 192
/*     */     //   435: invokevirtual 196	ev:aa	(I)Ljava/lang/String;
/*     */     //   438: astore 5
/*     */     //   440: iload 11
/*     */     //   442: iconst_1
/*     */     //   443: if_icmpne +26 -> 469
/*     */     //   446: iload_3
/*     */     //   447: ldc 113
/*     */     //   449: if_icmpeq +11 -> 460
/*     */     //   452: new 38	java/lang/IllegalStateException
/*     */     //   455: dup
/*     */     //   456: invokespecial 42	java/lang/IllegalStateException:<init>	()V
/*     */     //   459: athrow
/*     */     //   460: aload 9
/*     */     //   462: ldc 197
/*     */     //   464: invokevirtual 196	ev:aa	(I)Ljava/lang/String;
/*     */     //   467: astore 6
/*     */     //   469: aload 8
/*     */     //   471: ldc 198
/*     */     //   473: invokevirtual 200	u:l	(I)V
/*     */     //   476: goto +10 -> 486
/*     */     //   479: astore 9
/*     */     //   481: aload 9
/*     */     //   483: invokevirtual 203	java/io/IOException:printStackTrace	()V
/*     */     //   486: aload 5
/*     */     //   488: ifnull +48 -> 536
/*     */     //   491: iload_3
/*     */     //   492: ldc 113
/*     */     //   494: if_icmpeq +6 -> 500
/*     */     //   497: goto +0 -> 497
/*     */     //   500: new 133	java/io/File
/*     */     //   503: dup
/*     */     //   504: aload 5
/*     */     //   506: invokespecial 204	java/io/File:<init>	(Ljava/lang/String;)V
/*     */     //   509: astore 9
/*     */     //   511: aload 9
/*     */     //   513: invokevirtual 157	java/io/File:exists	()Z
/*     */     //   516: ifne +20 -> 536
/*     */     //   519: iload_3
/*     */     //   520: ldc 113
/*     */     //   522: if_icmpeq +11 -> 533
/*     */     //   525: new 38	java/lang/IllegalStateException
/*     */     //   528: dup
/*     */     //   529: invokespecial 42	java/lang/IllegalStateException:<init>	()V
/*     */     //   532: athrow
/*     */     //   533: aconst_null
/*     */     //   534: astore 5
/*     */     //   536: aload 5
/*     */     //   538: ifnull +113 -> 651
/*     */     //   541: iload_3
/*     */     //   542: ldc 113
/*     */     //   544: if_icmpeq +11 -> 555
/*     */     //   547: new 38	java/lang/IllegalStateException
/*     */     //   550: dup
/*     */     //   551: invokespecial 42	java/lang/IllegalStateException:<init>	()V
/*     */     //   554: athrow
/*     */     //   555: new 133	java/io/File
/*     */     //   558: dup
/*     */     //   559: aload 5
/*     */     //   561: ldc 206
/*     */     //   563: invokespecial 148	java/io/File:<init>	(Ljava/lang/String;Ljava/lang/String;)V
/*     */     //   566: astore 9
/*     */     //   568: new 208	java/io/RandomAccessFile
/*     */     //   571: dup
/*     */     //   572: aload 9
/*     */     //   574: ldc 161
/*     */     //   576: invokespecial 211	java/io/RandomAccessFile:<init>	(Ljava/io/File;Ljava/lang/String;)V
/*     */     //   579: astore 11
/*     */     //   581: aload 11
/*     */     //   583: invokevirtual 213	java/io/RandomAccessFile:read	()I
/*     */     //   586: istore 12
/*     */     //   588: aload 11
/*     */     //   590: lconst_0
/*     */     //   591: invokevirtual 217	java/io/RandomAccessFile:seek	(J)V
/*     */     //   594: aload 11
/*     */     //   596: iload 12
/*     */     //   598: invokevirtual 220	java/io/RandomAccessFile:write	(I)V
/*     */     //   601: aload 11
/*     */     //   603: lconst_0
/*     */     //   604: invokevirtual 217	java/io/RandomAccessFile:seek	(J)V
/*     */     //   607: aload 11
/*     */     //   609: invokevirtual 223	java/io/RandomAccessFile:close	()V
/*     */     //   612: aload 9
/*     */     //   614: invokevirtual 226	java/io/File:delete	()Z
/*     */     //   617: pop
/*     */     //   618: iconst_1
/*     */     //   619: istore 10
/*     */     //   621: goto +8 -> 629
/*     */     //   624: astore 11
/*     */     //   626: iconst_0
/*     */     //   627: istore 10
/*     */     //   629: iload 10
/*     */     //   631: ifne +20 -> 651
/*     */     //   634: iload_3
/*     */     //   635: ldc 113
/*     */     //   637: if_icmpeq +11 -> 648
/*     */     //   640: new 38	java/lang/IllegalStateException
/*     */     //   643: dup
/*     */     //   644: invokespecial 42	java/lang/IllegalStateException:<init>	()V
/*     */     //   647: athrow
/*     */     //   648: aconst_null
/*     */     //   649: astore 5
/*     */     //   651: aload 5
/*     */     //   653: ifnonnull +255 -> 908
/*     */     //   656: iload_3
/*     */     //   657: ldc 113
/*     */     //   659: if_icmpeq +6 -> 665
/*     */     //   662: goto +3 -> 665
/*     */     //   665: iload_2
/*     */     //   666: ifne +242 -> 908
/*     */     //   669: iload_3
/*     */     //   670: ldc 113
/*     */     //   672: if_icmpeq +6 -> 678
/*     */     //   675: goto +3 -> 678
/*     */     //   678: iconst_0
/*     */     //   679: istore 8
/*     */     //   681: iload 8
/*     */     //   683: getstatic 232	ag:b	[Ljava/lang/String;
/*     */     //   686: arraylength
/*     */     //   687: if_icmpge +221 -> 908
/*     */     //   690: iload_3
/*     */     //   691: ldc 113
/*     */     //   693: if_icmpeq +11 -> 704
/*     */     //   696: new 38	java/lang/IllegalStateException
/*     */     //   699: dup
/*     */     //   700: invokespecial 42	java/lang/IllegalStateException:<init>	()V
/*     */     //   703: athrow
/*     */     //   704: iconst_0
/*     */     //   705: istore 9
/*     */     //   707: iload 9
/*     */     //   709: getstatic 237	by:e	[Ljava/lang/String;
/*     */     //   712: arraylength
/*     */     //   713: if_icmpge +189 -> 902
/*     */     //   716: iload_3
/*     */     //   717: ldc 113
/*     */     //   719: if_icmpeq +6 -> 725
/*     */     //   722: goto +3 -> 725
/*     */     //   725: new 133	java/io/File
/*     */     //   728: dup
/*     */     //   729: new 117	java/lang/StringBuilder
/*     */     //   732: dup
/*     */     //   733: invokespecial 118	java/lang/StringBuilder:<init>	()V
/*     */     //   736: getstatic 237	by:e	[Ljava/lang/String;
/*     */     //   739: iload 9
/*     */     //   741: aaload
/*     */     //   742: invokevirtual 122	java/lang/StringBuilder:append	(Ljava/lang/String;)Ljava/lang/StringBuilder;
/*     */     //   745: getstatic 232	ag:b	[Ljava/lang/String;
/*     */     //   748: iload 8
/*     */     //   750: aaload
/*     */     //   751: invokevirtual 122	java/lang/StringBuilder:append	(Ljava/lang/String;)Ljava/lang/StringBuilder;
/*     */     //   754: getstatic 241	java/io/File:separatorChar	C
/*     */     //   757: invokevirtual 244	java/lang/StringBuilder:append	(C)Ljava/lang/StringBuilder;
/*     */     //   760: aload_0
/*     */     //   761: invokevirtual 122	java/lang/StringBuilder:append	(Ljava/lang/String;)Ljava/lang/StringBuilder;
/*     */     //   764: getstatic 241	java/io/File:separatorChar	C
/*     */     //   767: invokevirtual 244	java/lang/StringBuilder:append	(C)Ljava/lang/StringBuilder;
/*     */     //   770: invokevirtual 129	java/lang/StringBuilder:toString	()Ljava/lang/String;
/*     */     //   773: invokespecial 204	java/io/File:<init>	(Ljava/lang/String;)V
/*     */     //   776: astore 10
/*     */     //   778: aload 10
/*     */     //   780: invokevirtual 157	java/io/File:exists	()Z
/*     */     //   783: ifeq +113 -> 896
/*     */     //   786: iload_3
/*     */     //   787: ldc 113
/*     */     //   789: if_icmpeq +6 -> 795
/*     */     //   792: goto +0 -> 792
/*     */     //   795: new 133	java/io/File
/*     */     //   798: dup
/*     */     //   799: aload 10
/*     */     //   801: ldc 206
/*     */     //   803: invokespecial 245	java/io/File:<init>	(Ljava/io/File;Ljava/lang/String;)V
/*     */     //   806: astore 12
/*     */     //   808: new 208	java/io/RandomAccessFile
/*     */     //   811: dup
/*     */     //   812: aload 12
/*     */     //   814: ldc 161
/*     */     //   816: invokespecial 211	java/io/RandomAccessFile:<init>	(Ljava/io/File;Ljava/lang/String;)V
/*     */     //   819: astore 13
/*     */     //   821: aload 13
/*     */     //   823: invokevirtual 213	java/io/RandomAccessFile:read	()I
/*     */     //   826: istore 14
/*     */     //   828: aload 13
/*     */     //   830: lconst_0
/*     */     //   831: invokevirtual 217	java/io/RandomAccessFile:seek	(J)V
/*     */     //   834: aload 13
/*     */     //   836: iload 14
/*     */     //   838: invokevirtual 220	java/io/RandomAccessFile:write	(I)V
/*     */     //   841: aload 13
/*     */     //   843: lconst_0
/*     */     //   844: invokevirtual 217	java/io/RandomAccessFile:seek	(J)V
/*     */     //   847: aload 13
/*     */     //   849: invokevirtual 223	java/io/RandomAccessFile:close	()V
/*     */     //   852: aload 12
/*     */     //   854: invokevirtual 226	java/io/File:delete	()Z
/*     */     //   857: pop
/*     */     //   858: iconst_1
/*     */     //   859: istore 11
/*     */     //   861: goto +8 -> 869
/*     */     //   864: astore 13
/*     */     //   866: iconst_0
/*     */     //   867: istore 11
/*     */     //   869: iload 11
/*     */     //   871: ifeq +25 -> 896
/*     */     //   874: iload_3
/*     */     //   875: ldc 113
/*     */     //   877: if_icmpeq +6 -> 883
/*     */     //   880: goto +3 -> 883
/*     */     //   883: aload 10
/*     */     //   885: invokevirtual 246	java/io/File:toString	()Ljava/lang/String;
/*     */     //   888: astore 5
/*     */     //   890: iconst_1
/*     */     //   891: istore 7
/*     */     //   893: goto +15 -> 908
/*     */     //   896: iinc 9 1
/*     */     //   899: goto -192 -> 707
/*     */     //   902: iinc 8 1
/*     */     //   905: goto -224 -> 681
/*     */     //   908: aconst_null
/*     */     //   909: aload 5
/*     */     //   911: if_acmpne +75 -> 986
/*     */     //   914: iload_3
/*     */     //   915: ldc 113
/*     */     //   917: if_icmpeq +6 -> 923
/*     */     //   920: goto +3 -> 923
/*     */     //   923: new 117	java/lang/StringBuilder
/*     */     //   926: dup
/*     */     //   927: invokespecial 118	java/lang/StringBuilder:<init>	()V
/*     */     //   930: getstatic 139	ez:o	Ljava/lang/String;
/*     */     //   933: invokevirtual 122	java/lang/StringBuilder:append	(Ljava/lang/String;)Ljava/lang/StringBuilder;
/*     */     //   936: getstatic 241	java/io/File:separatorChar	C
/*     */     //   939: invokevirtual 244	java/lang/StringBuilder:append	(C)Ljava/lang/StringBuilder;
/*     */     //   942: ldc 248
/*     */     //   944: invokevirtual 122	java/lang/StringBuilder:append	(Ljava/lang/String;)Ljava/lang/StringBuilder;
/*     */     //   947: aload 4
/*     */     //   949: invokevirtual 122	java/lang/StringBuilder:append	(Ljava/lang/String;)Ljava/lang/StringBuilder;
/*     */     //   952: getstatic 241	java/io/File:separatorChar	C
/*     */     //   955: invokevirtual 244	java/lang/StringBuilder:append	(C)Ljava/lang/StringBuilder;
/*     */     //   958: aload_0
/*     */     //   959: invokevirtual 122	java/lang/StringBuilder:append	(Ljava/lang/String;)Ljava/lang/StringBuilder;
/*     */     //   962: getstatic 241	java/io/File:separatorChar	C
/*     */     //   965: invokevirtual 244	java/lang/StringBuilder:append	(C)Ljava/lang/StringBuilder;
/*     */     //   968: aload_1
/*     */     //   969: invokevirtual 122	java/lang/StringBuilder:append	(Ljava/lang/String;)Ljava/lang/StringBuilder;
/*     */     //   972: getstatic 241	java/io/File:separatorChar	C
/*     */     //   975: invokevirtual 244	java/lang/StringBuilder:append	(C)Ljava/lang/StringBuilder;
/*     */     //   978: invokevirtual 129	java/lang/StringBuilder:toString	()Ljava/lang/String;
/*     */     //   981: astore 5
/*     */     //   983: iconst_1
/*     */     //   984: istore 7
/*     */     //   986: aload 6
/*     */     //   988: ifnull +143 -> 1131
/*     */     //   991: iload_3
/*     */     //   992: ldc 113
/*     */     //   994: if_icmpeq +11 -> 1005
/*     */     //   997: new 38	java/lang/IllegalStateException
/*     */     //   1000: dup
/*     */     //   1001: invokespecial 42	java/lang/IllegalStateException:<init>	()V
/*     */     //   1004: athrow
/*     */     //   1005: new 133	java/io/File
/*     */     //   1008: dup
/*     */     //   1009: aload 6
/*     */     //   1011: invokespecial 204	java/io/File:<init>	(Ljava/lang/String;)V
/*     */     //   1014: astore 8
/*     */     //   1016: new 133	java/io/File
/*     */     //   1019: dup
/*     */     //   1020: aload 5
/*     */     //   1022: invokespecial 204	java/io/File:<init>	(Ljava/lang/String;)V
/*     */     //   1025: astore 9
/*     */     //   1027: aload 8
/*     */     //   1029: invokevirtual 252	java/io/File:listFiles	()[Ljava/io/File;
/*     */     //   1032: astore 10
/*     */     //   1034: aload 10
/*     */     //   1036: astore 11
/*     */     //   1038: iconst_0
/*     */     //   1039: istore 12
/*     */     //   1041: iload 12
/*     */     //   1043: aload 11
/*     */     //   1045: arraylength
/*     */     //   1046: if_icmpge +72 -> 1118
/*     */     //   1049: iload_3
/*     */     //   1050: ldc 113
/*     */     //   1052: if_icmpeq +6 -> 1058
/*     */     //   1055: goto +3 -> 1058
/*     */     //   1058: aload 11
/*     */     //   1060: iload 12
/*     */     //   1062: aaload
/*     */     //   1063: astore 13
/*     */     //   1065: new 133	java/io/File
/*     */     //   1068: dup
/*     */     //   1069: aload 9
/*     */     //   1071: aload 13
/*     */     //   1073: invokevirtual 257	java/io/File:getName	()Ljava/lang/String;
/*     */     //   1076: invokespecial 245	java/io/File:<init>	(Ljava/io/File;Ljava/lang/String;)V
/*     */     //   1079: astore 14
/*     */     //   1081: aload 13
/*     */     //   1083: aload 14
/*     */     //   1085: invokevirtual 261	java/io/File:renameTo	(Ljava/io/File;)Z
/*     */     //   1088: istore 15
/*     */     //   1090: iload 15
/*     */     //   1092: ifne +20 -> 1112
/*     */     //   1095: iload_3
/*     */     //   1096: ldc 113
/*     */     //   1098: if_icmpeq +6 -> 1104
/*     */     //   1101: goto +0 -> 1101
/*     */     //   1104: new 25	java/io/IOException
/*     */     //   1107: dup
/*     */     //   1108: invokespecial 43	java/io/IOException:<init>	()V
/*     */     //   1111: athrow
/*     */     //   1112: iinc 12 1
/*     */     //   1115: goto -74 -> 1041
/*     */     //   1118: goto +10 -> 1128
/*     */     //   1121: astore 10
/*     */     //   1123: aload 10
/*     */     //   1125: invokevirtual 262	java/lang/Exception:printStackTrace	()V
/*     */     //   1128: iconst_1
/*     */     //   1129: istore 7
/*     */     //   1131: iload 7
/*     */     //   1133: ifeq +171 -> 1304
/*     */     //   1136: iload_3
/*     */     //   1137: ldc 113
/*     */     //   1139: if_icmpeq +6 -> 1145
/*     */     //   1142: goto +3 -> 1145
/*     */     //   1145: new 133	java/io/File
/*     */     //   1148: dup
/*     */     //   1149: aload 5
/*     */     //   1151: invokespecial 204	java/io/File:<init>	(Ljava/lang/String;)V
/*     */     //   1154: astore 8
/*     */     //   1156: aconst_null
/*     */     //   1157: astore 9
/*     */     //   1159: new 159	u
/*     */     //   1162: dup
/*     */     //   1163: getstatic 153	ay:m	Ljava/io/File;
/*     */     //   1166: ldc 161
/*     */     //   1168: ldc2_w 162
/*     */     //   1171: invokespecial 166	u:<init>	(Ljava/io/File;Ljava/lang/String;J)V
/*     */     //   1174: astore 10
/*     */     //   1176: new 76	ev
/*     */     //   1179: dup
/*     */     //   1180: sipush 500
/*     */     //   1183: invokespecial 172	ev:<init>	(I)V
/*     */     //   1186: astore 11
/*     */     //   1188: aload 11
/*     */     //   1190: iconst_3
/*     */     //   1191: ldc_w 263
/*     */     //   1194: invokevirtual 266	ev:c	(II)V
/*     */     //   1197: aload 11
/*     */     //   1199: aconst_null
/*     */     //   1200: aload 9
/*     */     //   1202: if_acmpeq +16 -> 1218
/*     */     //   1205: iload_3
/*     */     //   1206: ldc 113
/*     */     //   1208: if_icmpeq +6 -> 1214
/*     */     //   1211: goto +0 -> 1211
/*     */     //   1214: iconst_1
/*     */     //   1215: goto +4 -> 1219
/*     */     //   1218: iconst_0
/*     */     //   1219: ldc_w 267
/*     */     //   1222: invokevirtual 266	ev:c	(II)V
/*     */     //   1225: aload 11
/*     */     //   1227: aload 8
/*     */     //   1229: invokevirtual 270	java/io/File:getPath	()Ljava/lang/String;
/*     */     //   1232: ldc_w 271
/*     */     //   1235: invokevirtual 275	ev:s	(Ljava/lang/CharSequence;I)V
/*     */     //   1238: aload 9
/*     */     //   1240: ifnull +25 -> 1265
/*     */     //   1243: iload_3
/*     */     //   1244: ldc 113
/*     */     //   1246: if_icmpeq +6 -> 1252
/*     */     //   1249: goto +3 -> 1252
/*     */     //   1252: aload 11
/*     */     //   1254: aload 9
/*     */     //   1256: invokevirtual 270	java/io/File:getPath	()Ljava/lang/String;
/*     */     //   1259: ldc_w 271
/*     */     //   1262: invokevirtual 275	ev:s	(Ljava/lang/CharSequence;I)V
/*     */     //   1265: aload 10
/*     */     //   1267: aload 11
/*     */     //   1269: getfield 175	ev:m	[B
/*     */     //   1272: iconst_0
/*     */     //   1273: aload 11
/*     */     //   1275: getfield 173	ev:c	I
/*     */     //   1278: ldc 174
/*     */     //   1280: imul
/*     */     //   1281: ldc_w 276
/*     */     //   1284: invokevirtual 279	u:d	([BIII)V
/*     */     //   1287: aload 10
/*     */     //   1289: ldc 198
/*     */     //   1291: invokevirtual 200	u:l	(I)V
/*     */     //   1294: goto +10 -> 1304
/*     */     //   1297: astore 11
/*     */     //   1299: aload 11
/*     */     //   1301: invokevirtual 203	java/io/IOException:printStackTrace	()V
/*     */     //   1304: new 133	java/io/File
/*     */     //   1307: dup
/*     */     //   1308: aload 5
/*     */     //   1310: invokespecial 204	java/io/File:<init>	(Ljava/lang/String;)V
/*     */     //   1313: areturn
/*     */     //
/*     */     // Exception table:
/*     */     //   from	to	target	type
/*     */     //   117	476	479	java/io/IOException
/*     */     //   568	621	624	java/lang/Exception
/*     */     //   808	861	864	java/lang/Exception
/*     */     //   1027	1118	1121	java/lang/Exception
/*     */     //   1159	1294	1297	java/io/IOException
/*     */   }
/*     */ 
/*     */   static String d(int paramInt1, int paramInt2)
/*     */   {
/*  22 */     return "<col=" + Integer.toHexString(paramInt1) + ">";
/*     */   }
/*     */ 
/*     */   public static eo g(int paramInt, byte paramByte)
/*     */   {
/*  41 */     eo localeo = (eo)eo.g.r(paramInt);
/*  42 */     if (localeo != null) { if (paramByte != 0) throw new IllegalStateException(); return localeo; }
/*  43 */     byte[] arrayOfByte = dz.n.l(12, paramInt, 1575040314);
/*  44 */     localeo = new eo();
/*  45 */     if (arrayOfByte != null) { if (paramByte != 0) throw new IllegalStateException(); localeo.q(new ev(arrayOfByte), (short)-11430); }
/*  46 */     localeo.s((byte)1);
/*  47 */     eo.g.l(localeo, paramInt);
/*  48 */     return localeo;
/*     */   }
/*     */ 
/*     */   public static void l(int paramInt1, int paramInt2)
/*     */   {
/*  44 */     if (0 != 153881033 * bd.c) { if (paramInt2 < -44855497);
/*  44 */       bd.g = -895834111 * paramInt1; } else {
/*  45 */       bd.m.p(paramInt1, 2119343925);
/*     */     }
/*     */   }
/*     */ }

/* Location:           C:\Users\Mike\IdeaProjects\RealityBot-2007 Updater\client-deob.jar
 * Qualified Name:     i
 * JD-Core Version:    0.6.2
 */